Workbook

Sheet Synthèse agences R
D3: Total (2023) | E3: Fermeture | H3: Autonomie
C4: Synthèse Résolution | E4: Cession d'actif | F4: Suppression | G4: Internali-sation | H4: EPIC - musée & patrimoine | I4: EPIC - enseignement & recherche | J4: Autorité indépendante
C5: Agences Etat | D5: =SUM(D6:D7,D8:D9) -> 1104 | E5: =SUM(E6:E9) -> 78 | F5: =SUM(F6:F9) -> 668 | G5: =SUM(G6:G9) -> 55 | H5: =SUM(H6:H9) -> 40 | I5: =SUM(I6:I9) -> 258 | J5: =SUM(J6:J9) -> 5
C6: Opérateurs (PLF) | D6: ='Opérateurs R'!F3 -> 434 | E6: ='Opérateurs R'!N3 -> 15 | F6: ='Opérateurs R'!O3 -> 123 | G6: ='Opérateurs R'!R3 -> 34 | H6: ='Opérateurs R'!P3 -> 36 | I6: ='Opérateurs R'!Q3 -> 226
C7: Organismes hors PLF | D7: ='ODAC-ODAL R'!B4-'ODAC-ODAL R'!C4 -> 328 | E7: ='ODAC-ODAL R'!D4 -> 63 | F7: ='ODAC-ODAL R'!E4 -> 217 | G7: ='ODAC-ODAL R'!H4 -> 12 | H7: ='ODAC-ODAL R'!F4 -> 4 | I7: ='ODAC-ODAL R'!G4 -> 32
C8: Autorités indépendantes | D8: ='ODAC-ODAL R'!B752-'ODAC-ODAL R'!C752 -> 24 | F8: ='ODAC-ODAL R'!E752 -> 10 | G8: ='ODAC-ODAL R'!H752 -> 9 | J8: ='ODAC-ODAL R'!I752 -> 5
C9: Commissions | D9: 318 | F9: =D9 -> 318
C10: Agences locales | D10: =D11 -> 23264 | E10: =E11 -> 347 | F10: =F11 -> 13481 | G10: =G11 -> 296 | I10: =I11 -> 9140
C11: Organismes hors PLF | D11: ='ODAC-ODAL R'!B726-'ODAC-ODAL R'!C726 -> 23264 | E11: ='ODAC-ODAL R'!D726 -> 347 | F11: ='ODAC-ODAL R'!E726 -> 13481 | G11: ='ODAC-ODAL R'!H726 -> 296 | I11: ='ODAC-ODAL R'!G726 -> 9140
C12: Total agences | D12: =D5+D10 -> 24368 | E12: =E5+E10 -> 425 | F12: =F5+F10 -> 14149 | G12: =G5+G10 -> 351 | H12: =H5+H10 -> 40 | I12: =I5+I10 -> 9398 | J12: =J5+J10 -> 5

Sheet Opérateurs R
A2: M | B2: Mission | C2: Pg | D2: Programme | E2: Intitulé de l'opérateur | F2: Nb/cat. | G2: LFI 2025 - ETPT total | H2: LFI 2025 – ETPT sous plafond | I2: LFI 2025 – ETPT hors plafond | J2: PLF 2026 - ETPT total | K2: PLF 2026 – ETPT sous plafond | L2: PLF 2026 – ETPT hors plafond | N2: Vente | O2: Suppression | P2: EPIC - musée | Q2: EPIC - études | R2: Internalisation
E3: Total général | F3: =SUM(F5:F184) -> 434 | N3: =SUMIFS($F5:$F184,N5:N184,"X") -> 15 | O3: =SUMIFS($F5:$F184,O5:O184,"X") -> 123 | P3: =SUMIFS($F5:$F184,P5:P184,"X") -> 36 | Q3: =SUMIFS($F5:$F184,Q5:Q184,"X") -> 226 | R3: =SUMIFS($F5:$F184,R5:R184,"X") -> 34
G4: =H4+I4 -> 479514 | H4: 402456 | I4: 77058 | J4: =K4+L4 -> 478026 | K4: 401310 | L4: 76716 | N4: =SUMIFS($G5:$G184,N5:N184,"X") -> 10476 | O4: =SUMIFS($G5:$G184,O5:O184,"X") -> 99885 | P4: =SUMIFS($G5:$G184,P5:P184,"X") -> 25039 | Q4: =SUMIFS($G5:$G184,Q5:Q184,"X") -> 326723 | R4: =SUMIFS($G5:$G184,R5:R184,"X") -> 17391 | S4: ETP
A5: =_xlfn.XLOOKUP(C5,'Annexe Etat'!$I$2:$I$164,'Annexe Etat'!$H$2:$H$164) -> RA | B5: =_xlfn.XLOOKUP(A5,'Annexe Etat'!$A$2:$A$164,'Annexe Etat'!$B$2:$B$164) -> Recherche et enseignement supérieur | C5: 172 | D5: =_xlfn.XLOOKUP(C5,'Annexe Etat'!$I$2:$I$164,'Annexe Etat'!$J$2:$J$164) -> Recherches scientifiques et technologiques pluridisciplinaires | E5: Académie des technologies | F5: 1 | G5: =H5+I5 -> 10 | H5: 9 | I5: 1 | J5: =K5+L5 -> 9 | K5: 9 | L5: 0 | O5: X
A6: =_xlfn.XLOOKUP(C6,'Annexe Etat'!$I$2:$I$164,'Annexe Etat'!$H$2:$H$164) -> AB | B6: =_xlfn.XLOOKUP(A6,'Annexe Etat'!$A$2:$A$164,'Annexe Etat'!$B$2:$B$164) -> Administration générale et territoriale de l'État | C6: 216 | D6: =_xlfn.XLOOKUP(C6,'Annexe Etat'!$I$2:$I$164,'Annexe Etat'!$J$2:$J$164) -> Conduite et pilotage des politiques de l'intérieur | E6: ACMOSS - Agence des Communications Mobiles Opérationnelles de Sécurité et de Secours | F6: 1 | G6: =H6+I6 -> 81 | H6: 76 | I6: 5 | J6: =K6+L6 -> 101 | K6: 98 | L6: 3 | R6: X
A7: =_xlfn.XLOOKUP(C7,'Annexe Etat'!$I$2:$I$164,'Annexe Etat'!$H$2:$H$164) -> TA | B7: =_xlfn.XLOOKUP(A7,'Annexe Etat'!$A$2:$A$164,'Annexe Etat'!$B$2:$B$164) -> Écologie, développement et mobilité durables | C7: 181 | D7: =_xlfn.XLOOKUP(C7,'Annexe Etat'!$I$2:$I$164,'Annexe Etat'!$J$2:$J$164) -> Prévention des risques | E7: ADEME - Agence de l'environnement et de la maîtrise de l'énergie | F7: 1 | G7: =H7+I7 -> 1334 | H7: 1069 | I7: 265 | J7: =K7+L7 -> 1330 | K7: 1070 | L7: 260 | O7: X
A8: =_xlfn.XLOOKUP(C8,'Annexe Etat'!$I$2:$I$164,'Annexe Etat'!$H$2:$H$164) -> AA | B8: =_xlfn.XLOOKUP(A8,'Annexe Etat'!$A$2:$A$164,'Annexe Etat'!$B$2:$B$164) -> Action extérieure de l'État | C8: 185 | D8: =_xlfn.XLOOKUP(C8,'Annexe Etat'!$I$2:$I$164,'Annexe Etat'!$J$2:$J$164) -> Diplomatie culturelle et d'influence | E8: AEFE - Agence pour l'enseignement français à l'étranger | F8: 1 | G8: =H8+I8 -> 10740 | H8: 5579 | I8: 5161 | J8: =K8+L8 -> 10722 | K8: 5561 | L8: 5161 | Q8: X
A9: =_xlfn.XLOOKUP(C9,'Annexe Etat'!$I$2:$I$164,'Annexe Etat'!$H$2:$H$164) -> TA | B9: =_xlfn.XLOOKUP(A9,'Annexe Etat'!$A$2:$A$164,'Annexe Etat'!$B$2:$B$164) -> Écologie, développement et mobilité durables | C9: 203 | D9: =_xlfn.XLOOKUP(C9,'Annexe Etat'!$I$2:$I$164,'Annexe Etat'!$J$2:$J$164) -> Infrastructures et services de transports | E9: AFITF - Agence de financement des infrastructures de transport de France | F9: 1 | G9: =H9+I9 -> 0 | H9: 0 | I9: 0 | J9: =K9+L9 -> 0 | K9: 0 | L9: 0 | O9: X
A10: =_xlfn.XLOOKUP(C10,'Annexe Etat'!$I$2:$I$164,'Annexe Etat'!$H$2:$H$164) -> TB | B10: =_xlfn.XLOOKUP(A10,'Annexe Etat'!$A$2:$A$164,'Annexe Etat'!$B$2:$B$164) -> Travail, emploi et administration des ministères sociaux | C10: 103 | D10: =_xlfn.XLOOKUP(C10,'Annexe Etat'!$I$2:$I$164,'Annexe Etat'!$J$2:$J$164) -> Accompagnement des mutations économiques et développement de l'emploi | E10: AFPA - Agence nationale pour la formation professionnelle des adultes | F10: 1 | G10: =H10+I10 -> 5330 | H10: 5330 | I10: 0 | J10: =K10+L10 -> 4824 | K10: 4824 | L10: 0 | O10: X
A11: =_xlfn.XLOOKUP(C11,'Annexe Etat'!$I$2:$I$164,'Annexe Etat'!$H$2:$H$164) -> CB | B11: =_xlfn.XLOOKUP(A11,'Annexe Etat'!$A$2:$A$164,'Annexe Etat'!$B$2:$B$164) -> Culture | C11: 131 | D11: =_xlfn.XLOOKUP(C11,'Annexe Etat'!$I$2:$I$164,'Annexe Etat'!$J$2:$J$164) -> Création | E11: AFR - Académie de France à Rome | F11: 1 | G11: =H11+I11 -> 47 | H11: 47 | I11: 0 | J11: =K11+L11 -> 47 | K11: 47 | L11: 0 | P11: X
A12: =_xlfn.XLOOKUP(C12,'Annexe Etat'!$I$2:$I$164,'Annexe Etat'!$H$2:$H$164) -> TA | B12: =_xlfn.XLOOKUP(A12,'Annexe Etat'!$A$2:$A$164,'Annexe Etat'!$B$2:$B$164) -> Écologie, développement et mobilité durables | C12: 113 | D12: =_xlfn.XLOOKUP(C12,'Annexe Etat'!$I$2:$I$164,'Annexe Etat'!$J$2:$J$164) -> Paysages, eau et biodiversité | E12: Agences de l'eau | F12: 6 | G12: =H12+I12 -> 1575 | H12: 1551 | I12: 24 | J12: =K12+L12 -> 1562 | K12: 1539 | L12: 23 | O12: X
A13: =_xlfn.XLOOKUP(C13,'Annexe Etat'!$I$2:$I$164,'Annexe Etat'!$H$2:$H$164) -> JA | B13: =_xlfn.XLOOKUP(A13,'Annexe Etat'!$A$2:$A$164,'Annexe Etat'!$B$2:$B$164) -> Justice | C13: 310 | D13: =_xlfn.XLOOKUP(C13,'Annexe Etat'!$I$2:$I$164,'Annexe Etat'!$J$2:$J$164) -> Conduite et pilotage de la politique de la justice | E13: AGRASC - Agence de gestion et de recouvrement des avoirs saisis et confisqués | F13: 1 | G13: =H13+I13 -> 69 | H13: 69 | I13: 0 | J13: =K13+L13 -> 69 | K13: 69 | L13: 0 | R13: X
A14: =_xlfn.XLOOKUP(C14,'Annexe Etat'!$I$2:$I$164,'Annexe Etat'!$H$2:$H$164) -> TB | B14: =_xlfn.XLOOKUP(A14,'Annexe Etat'!$A$2:$A$164,'Annexe Etat'!$B$2:$B$164) -> Travail, emploi et administration des ministères sociaux | C14: 111 | D14: =_xlfn.XLOOKUP(C14,'Annexe Etat'!$I$2:$I$164,'Annexe Etat'!$J$2:$J$164) -> Amélioration de la qualité de l'emploi et des relations du travail | E14: ANACT - Agence nationale pour l'amélioration des conditions de travail | F14: 1 | G14: =H14+I14 -> 290 | H14: 265 | I14: 25 | J14: =K14+L14 -> 290 | K14: 265 | L14: 25 | O14: X
A15: =_xlfn.XLOOKUP(C15,'Annexe Etat'!$I$2:$I$164,'Annexe Etat'!$H$2:$H$164) -> VA | B15: =_xlfn.XLOOKUP(A15,'Annexe Etat'!$A$2:$A$164,'Annexe Etat'!$B$2:$B$164) -> Cohésion des territoires | C15: 135 | D15: =_xlfn.XLOOKUP(C15,'Annexe Etat'!$I$2:$I$164,'Annexe Etat'!$J$2:$J$164) -> Urbanisme, territoires et amélioration de l'habitat | E15: ANAH - Agence nationale de l'habitat | F15: 1 | G15: =H15+I15 -> 285 | H15: 285 | I15: 0 | J15: =K15+L15 -> 287 | K15: 287 | L15: 0 | O15: X
A16: =_xlfn.XLOOKUP(C16,'Annexe Etat'!$I$2:$I$164,'Annexe Etat'!$H$2:$H$164) -> VA | B16: =_xlfn.XLOOKUP(A16,'Annexe Etat'!$A$2:$A$164,'Annexe Etat'!$B$2:$B$164) -> Cohésion des territoires | C16: 135 | D16: =_xlfn.XLOOKUP(C16,'Annexe Etat'!$I$2:$I$164,'Annexe Etat'!$J$2:$J$164) -> Urbanisme, territoires et amélioration de l'habitat | E16: ANCOLS - Agence nationale de contrôle du logement social | F16: 1 | G16: =H16+I16 -> 136 | H16: 136 | I16: 0 | J16: =K16+L16 -> 133 | K16: 133 | L16: 0 | R16: X
A17: =_xlfn.XLOOKUP(C17,'Annexe Etat'!$I$2:$I$164,'Annexe Etat'!$H$2:$H$164) -> VA | B17: =_xlfn.XLOOKUP(A17,'Annexe Etat'!$A$2:$A$164,'Annexe Etat'!$B$2:$B$164) -> Cohésion des territoires | C17: 112 | D17: =_xlfn.XLOOKUP(C17,'Annexe Etat'!$I$2:$I$164,'Annexe Etat'!$J$2:$J$164) -> Impulsion et coordination de la politique d'aménagement du territoire | E17: ANCT - Agence nationale de la cohésion des territoires | F17: 1 | G17: =H17+I17 -> 358 | H17: 350 | I17: 8 | J17: =K17+L17 -> 340 | K17: 320 | L17: 20 | O17: X
A18: =_xlfn.XLOOKUP(C18,'Annexe Etat'!$I$2:$I$164,'Annexe Etat'!$H$2:$H$164) -> TA | B18: =_xlfn.XLOOKUP(A18,'Annexe Etat'!$A$2:$A$164,'Annexe Etat'!$B$2:$B$164) -> Écologie, développement et mobilité durables | C18: 174 | D18: =_xlfn.XLOOKUP(C18,'Annexe Etat'!$I$2:$I$164,'Annexe Etat'!$J$2:$J$164) -> Énergie, climat et après-mines | E18: ANDRA - Agence nationale pour la gestion des déchets radioactifs | F18: 1 | G18: =H18+I18 -> 791 | H18: 263 | I18: 528 | J18: =K18+L18 -> 871 | K18: 260 | L18: 611 | R18: X
A19: =_xlfn.XLOOKUP(C19,'Annexe Etat'!$I$2:$I$164,'Annexe Etat'!$H$2:$H$164) -> DB | B19: =_xlfn.XLOOKUP(A19,'Annexe Etat'!$A$2:$A$164,'Annexe Etat'!$B$2:$B$164) -> Économie | C19: 134 | D19: =_xlfn.XLOOKUP(C19,'Annexe Etat'!$I$2:$I$164,'Annexe Etat'!$J$2:$J$164) -> Développement des entreprises et régulations | E19: ANFr - Agence nationale des fréquences | F19: 1 | G19: =H19+I19 -> 297 | H19: 292 | I19: 5 | J19: =K19+L19 -> 292 | K19: 287 | L19: 5 | R19: X
A20: =_xlfn.XLOOKUP(C20,'Annexe Etat'!$I$2:$I$164,'Annexe Etat'!$H$2:$H$164) -> TA | B20: =_xlfn.XLOOKUP(A20,'Annexe Etat'!$A$2:$A$164,'Annexe Etat'!$B$2:$B$164) -> Écologie, développement et mobilité durables | C20: 174 | D20: =_xlfn.XLOOKUP(C20,'Annexe Etat'!$I$2:$I$164,'Annexe Etat'!$J$2:$J$164) -> Énergie, climat et après-mines | E20: ANGDM - Agence nationale pour la garantie des droits des mineurs | F20: 1 | G20: =H20+I20 -> 113 | H20: 113 | I20: 0 | J20: =K20+L20 -> 112 | K20: 110 | L20: 2 | R20: X
A21: =_xlfn.XLOOKUP(C21,'Annexe Etat'!$I$2:$I$164,'Annexe Etat'!$H$2:$H$164) -> RA | B21: =_xlfn.XLOOKUP(A21,'Annexe Etat'!$A$2:$A$164,'Annexe Etat'!$B$2:$B$164) -> Recherche et enseignement supérieur | C21: 172 | D21: =_xlfn.XLOOKUP(C21,'Annexe Etat'!$I$2:$I$164,'Annexe Etat'!$J$2:$J$164) -> Recherches scientifiques et technologiques pluridisciplinaires | E21: ANR - Agence nationale de la recherche | F21: 1 | G21: =H21+I21 -> 385 | H21: 355 | I21: 30 | J21: =K21+L21 -> 398 | K21: 355 | L21: 43 | R21: X
A22: =_xlfn.XLOOKUP(C22,'Annexe Etat'!$I$2:$I$164,'Annexe Etat'!$H$2:$H$164) -> SF | B22: =_xlfn.XLOOKUP(A22,'Annexe Etat'!$A$2:$A$164,'Annexe Etat'!$B$2:$B$164) -> Sport, jeunesse et vie associative | C22: 219 | D22: =_xlfn.XLOOKUP(C22,'Annexe Etat'!$I$2:$I$164,'Annexe Etat'!$J$2:$J$164) -> Sport | E22: ANS - Agence nationale du sport | F22: 1 | G22: =H22+I22 -> 71 | H22: 71 | I22: 0 | J22: =K22+L22 -> 67 | K22: 67 | L22: 0 | O22: X
A23: =_xlfn.XLOOKUP(C23,'Annexe Etat'!$I$2:$I$164,'Annexe Etat'!$H$2:$H$164) -> SB | B23: =_xlfn.XLOOKUP(A23,'Annexe Etat'!$A$2:$A$164,'Annexe Etat'!$B$2:$B$164) -> Sécurités | C23: 161 | D23: =_xlfn.XLOOKUP(C23,'Annexe Etat'!$I$2:$I$164,'Annexe Etat'!$J$2:$J$164) -> Sécurité civile | E23: ANSC - Agence nationale du numérique de la sécurité civile | F23: 1 | G23: =H23+I23 -> 27 | H23: 23 | I23: 4 | J23: =K23+L23 -> 28 | K23: 23 | L23: 5 | R23: X
A24: =_xlfn.XLOOKUP(C24,'Annexe Etat'!$I$2:$I$164,'Annexe Etat'!$H$2:$H$164) -> AC | B24: =_xlfn.XLOOKUP(A24,'Annexe Etat'!$A$2:$A$164,'Annexe Etat'!$B$2:$B$164) -> Agriculture, alimentation, forêt et affaires rurales | C24: 206 | D24: =_xlfn.XLOOKUP(C24,'Annexe Etat'!$I$2:$I$164,'Annexe Etat'!$J$2:$J$164) -> Sécurité et qualité sanitaires de l'alimentation | E24: ANSES - Agence nationale de sécurité sanitaire, de l'alimentation, de l'environnement et du travail | F24: 1 | G24: =H24+I24 -> 1447 | H24: 1327 | I24: 120 | J24: =K24+L24 -> 1458 | K24: 1317 | L24: 141 | R24: X
A25: =_xlfn.XLOOKUP(C25,'Annexe Etat'!$I$2:$I$164,'Annexe Etat'!$H$2:$H$164) -> YE | B25: =_xlfn.XLOOKUP(A25,'Annexe Etat'!$A$2:$A$164,'Annexe Etat'!$B$2:$B$164) -> Contrôle de la circulation et du stationnement routiers | C25: 753 | D25: =_xlfn.XLOOKUP(C25,'Annexe Etat'!$I$2:$I$164,'Annexe Etat'!$J$2:$J$164) -> Contrôle et modernisation de la politique de la circulation et du stationnement routiers | E25: ANTAI - Agence nationale de traitement automatisé des infractions | F25: 1 | G25: =H25+I25 -> 76 | H25: 61 | I25: 15 | J25: =K25+L25 -> 76 | K25: 61 | L25: 15 | R25: X
A26: =_xlfn.XLOOKUP(C26,'Annexe Etat'!$I$2:$I$164,'Annexe Etat'!$H$2:$H$164) -> AB | B26: =_xlfn.XLOOKUP(A26,'Annexe Etat'!$A$2:$A$164,'Annexe Etat'!$B$2:$B$164) -> Administration générale et territoriale de l'État | C26: 354 | D26: =_xlfn.XLOOKUP(C26,'Annexe Etat'!$I$2:$I$164,'Annexe Etat'!$J$2:$J$164) -> Administration territoriale de l'État | E26: ANTS - Agence nationale des titres sécurisés | F26: 1 | G26: =H26+I26 -> 171 | H26: 163 | I26: 8 | J26: =K26+L26 -> 171 | K26: 163 | L26: 8 | R26: X
A27: =_xlfn.XLOOKUP(C27,'Annexe Etat'!$I$2:$I$164,'Annexe Etat'!$H$2:$H$164) -> JA | B27: =_xlfn.XLOOKUP(A27,'Annexe Etat'!$A$2:$A$164,'Annexe Etat'!$B$2:$B$164) -> Justice | C27: 310 | D27: =_xlfn.XLOOKUP(C27,'Annexe Etat'!$I$2:$I$164,'Annexe Etat'!$J$2:$J$164) -> Conduite et pilotage de la politique de la justice | E27: APIJ - Agence publique pour l'immobilier de la Justice | F27: 1 | G27: =H27+I27 -> 169 | H27: 164 | I27: 5 | J27: =K27+L27 -> 169 | K27: 164 | L27: 5 | O27: X
A28: =_xlfn.XLOOKUP(C28,'Annexe Etat'!$I$2:$I$164,'Annexe Etat'!$H$2:$H$164) -> TB | B28: =_xlfn.XLOOKUP(A28,'Annexe Etat'!$A$2:$A$164,'Annexe Etat'!$B$2:$B$164) -> Travail, emploi et administration des ministères sociaux | C28: 155 | D28: =_xlfn.XLOOKUP(C28,'Annexe Etat'!$I$2:$I$164,'Annexe Etat'!$J$2:$J$164) -> Soutien des ministères sociaux | E28: ARS - Agences régionales de santé | F28: 18 | G28: =H28+I28 -> 8273 | H28: 8273 | I28: 0 | J28: =K28+L28 -> 8114 | K28: 8114 | L28: 0 | O28: X
A29: =_xlfn.XLOOKUP(C29,'Annexe Etat'!$I$2:$I$164,'Annexe Etat'!$H$2:$H$164) -> SF | B29: =_xlfn.XLOOKUP(A29,'Annexe Etat'!$A$2:$A$164,'Annexe Etat'!$B$2:$B$164) -> Sport, jeunesse et vie associative | C29: 163 | D29: =_xlfn.XLOOKUP(C29,'Annexe Etat'!$I$2:$I$164,'Annexe Etat'!$J$2:$J$164) -> Jeunesse et vie associative | E29: ASC - Agence du service civique | F29: 1 | G29: =H29+I29 -> 126 | H29: 69 | I29: 57 | J29: =K29+L29 -> 131 | K29: 69 | L29: 62 | O29: X
A30: =_xlfn.XLOOKUP(C30,'Annexe Etat'!$I$2:$I$164,'Annexe Etat'!$H$2:$H$164) -> AC | B30: =_xlfn.XLOOKUP(A30,'Annexe Etat'!$A$2:$A$164,'Annexe Etat'!$B$2:$B$164) -> Agriculture, alimentation, forêt et affaires rurales | C30: 149 | D30: =_xlfn.XLOOKUP(C30,'Annexe Etat'!$I$2:$I$164,'Annexe Etat'!$J$2:$J$164) -> Compétitivité et durabilité de l'agriculture, de l'agroalimentaire et de la forêt | E30: ASP - Agence de services et de paiement | F30: 1 | G30: =H30+I30 -> 2027 | H30: 1786 | I30: 241 | J30: =K30+L30 -> 2063 | K30: 1773 | L30: 290 | R30: X
A31: =_xlfn.XLOOKUP(C31,'Annexe Etat'!$I$2:$I$164,'Annexe Etat'!$H$2:$H$164) -> RA | B31: =_xlfn.XLOOKUP(A31,'Annexe Etat'!$A$2:$A$164,'Annexe Etat'!$B$2:$B$164) -> Recherche et enseignement supérieur | C31: 142 | D31: =_xlfn.XLOOKUP(C31,'Annexe Etat'!$I$2:$I$164,'Annexe Etat'!$J$2:$J$164) -> Enseignement supérieur et recherche agricoles | E31: Associations de coordination technique agricole et des industries agroalimentaires | F31: 2 | G31: =H31+I31 -> 0 | H31: 0 | I31: 0 | J31: =K31+L31 -> 0 | K31: 0 | L31: 0 | O31: X
A32: =_xlfn.XLOOKUP(C32,'Annexe Etat'!$I$2:$I$164,'Annexe Etat'!$H$2:$H$164) -> DB | B32: =_xlfn.XLOOKUP(A32,'Annexe Etat'!$A$2:$A$164,'Annexe Etat'!$B$2:$B$164) -> Économie | C32: 134 | D32: =_xlfn.XLOOKUP(C32,'Annexe Etat'!$I$2:$I$164,'Annexe Etat'!$J$2:$J$164) -> Développement des entreprises et régulations | E32: Atout-France | F32: 1 | G32: =H32+I32 -> 277 | H32: 237 | I32: 40 | J32: =K32+L32 -> 230 | K32: 215 | L32: 15 | O32: X
A33: =_xlfn.XLOOKUP(C33,'Annexe Etat'!$I$2:$I$164,'Annexe Etat'!$H$2:$H$164) -> RA | B33: =_xlfn.XLOOKUP(A33,'Annexe Etat'!$A$2:$A$164,'Annexe Etat'!$B$2:$B$164) -> Recherche et enseignement supérieur | C33: 150 | D33: =_xlfn.XLOOKUP(C33,'Annexe Etat'!$I$2:$I$164,'Annexe Etat'!$J$2:$J$164) -> Formations supérieures et recherche universitaire | E33: Autres opérateurs d'enseignement supérieur et de recherche | F33: 37 | G33: =H33+I33 -> 14747 | H33: 11088 | I33: 3659 | J33: =K33+L33 -> 14844 | K33: 11088 | L33: 3756 | Q33: X
A34: =_xlfn.XLOOKUP(C34,'Annexe Etat'!$I$2:$I$164,'Annexe Etat'!$H$2:$H$164) -> MA | B34: =_xlfn.XLOOKUP(A34,'Annexe Etat'!$A$2:$A$164,'Annexe Etat'!$B$2:$B$164) -> Médias, livre et industries culturelles | C34: 334 | D34: =_xlfn.XLOOKUP(C34,'Annexe Etat'!$I$2:$I$164,'Annexe Etat'!$J$2:$J$164) -> Livre et industries culturelles | E34: BnF - Bibliothèque nationale de France | F34: 1 | G34: =H34+I34 -> 2215 | H34: 2202 | I34: 13 | J34: =K34+L34 -> 2195 | K34: 2195 | L34: 0 | P34: X
A35: =_xlfn.XLOOKUP(C35,'Annexe Etat'!$I$2:$I$164,'Annexe Etat'!$H$2:$H$164) -> MA | B35: =_xlfn.XLOOKUP(A35,'Annexe Etat'!$A$2:$A$164,'Annexe Etat'!$B$2:$B$164) -> Médias, livre et industries culturelles | C35: 334 | D35: =_xlfn.XLOOKUP(C35,'Annexe Etat'!$I$2:$I$164,'Annexe Etat'!$J$2:$J$164) -> Livre et industries culturelles | E35: BPI - Bibliothèque publique d'information | F35: 1 | G35: =H35+I35 -> 61 | H35: 60 | I35: 1 | J35: =K35+L35 -> 60 | K35: 60 | L35: 0 | O35: X
A36: =_xlfn.XLOOKUP(C36,'Annexe Etat'!$I$2:$I$164,'Annexe Etat'!$H$2:$H$164) -> RA | B36: =_xlfn.XLOOKUP(A36,'Annexe Etat'!$A$2:$A$164,'Annexe Etat'!$B$2:$B$164) -> Recherche et enseignement supérieur | C36: 172 | D36: =_xlfn.XLOOKUP(C36,'Annexe Etat'!$I$2:$I$164,'Annexe Etat'!$J$2:$J$164) -> Recherches scientifiques et technologiques pluridisciplinaires | E36: BRGM - Bureau de recherches géologiques et minières | F36: 1 | G36: =H36+I36 -> 1065 | H36: 965 | I36: 100 | J36: =K36+L36 -> 1087 | K36: 967 | L36: 120 | Q36: X
A37: =_xlfn.XLOOKUP(C37,'Annexe Etat'!$I$2:$I$164,'Annexe Etat'!$H$2:$H$164) -> DB | B37: =_xlfn.XLOOKUP(A37,'Annexe Etat'!$A$2:$A$164,'Annexe Etat'!$B$2:$B$164) -> Économie | C37: 134 | D37: =_xlfn.XLOOKUP(C37,'Annexe Etat'!$I$2:$I$164,'Annexe Etat'!$J$2:$J$164) -> Développement des entreprises et régulations | E37: Business France | F37: 1 | G37: =H37+I37 -> 1418 | H37: 1418 | I37: 0 | J37: =K37+L37 -> 1476 | K37: 1392 | L37: 84 | O37: X
A38: =_xlfn.XLOOKUP(C38,'Annexe Etat'!$I$2:$I$164,'Annexe Etat'!$H$2:$H$164) -> AA | B38: =_xlfn.XLOOKUP(A38,'Annexe Etat'!$A$2:$A$164,'Annexe Etat'!$B$2:$B$164) -> Action extérieure de l'État | C38: 185 | D38: =_xlfn.XLOOKUP(C38,'Annexe Etat'!$I$2:$I$164,'Annexe Etat'!$J$2:$J$164) -> Diplomatie culturelle et d'influence | E38: CAMPUS France | F38: 1 | G38: =H38+I38 -> 258 | H38: 233 | I38: 25 | J38: =K38+L38 -> 258 | K38: 233 | L38: 25 | O38: X
A39: =_xlfn.XLOOKUP(C39,'Annexe Etat'!$I$2:$I$164,'Annexe Etat'!$H$2:$H$164) -> CB | B39: =_xlfn.XLOOKUP(A39,'Annexe Etat'!$A$2:$A$164,'Annexe Etat'!$B$2:$B$164) -> Culture | C39: 175 | D39: =_xlfn.XLOOKUP(C39,'Annexe Etat'!$I$2:$I$164,'Annexe Etat'!$J$2:$J$164) -> Patrimoines | E39: CAPA - Cité de l'architecture et du patrimoine | F39: 1 | G39: =H39+I39 -> 134 | H39: 134 | J39: =K39+L39 -> 135 | K39: 135 | P39: X
A40: =_xlfn.XLOOKUP(C40,'Annexe Etat'!$I$2:$I$164,'Annexe Etat'!$H$2:$H$164) -> RA | B40: =_xlfn.XLOOKUP(A40,'Annexe Etat'!$A$2:$A$164,'Annexe Etat'!$B$2:$B$164) -> Recherche et enseignement supérieur | C40: 172 | D40: =_xlfn.XLOOKUP(C40,'Annexe Etat'!$I$2:$I$164,'Annexe Etat'!$J$2:$J$164) -> Recherches scientifiques et technologiques pluridisciplinaires | E40: CEA - Commissariat à l'énergie atomique et aux énergies alternatives | F40: 1 | G40: =H40+I40 -> 20639 | H40: 17296 | I40: 3343 | J40: =K40+L40 -> 20702 | K40: 17319 | L40: 3383 | Q40: X
A41: =_xlfn.XLOOKUP(C41,'Annexe Etat'!$I$2:$I$164,'Annexe Etat'!$H$2:$H$164) -> TA | B41: =_xlfn.XLOOKUP(A41,'Annexe Etat'!$A$2:$A$164,'Annexe Etat'!$B$2:$B$164) -> Écologie, développement et mobilité durables | C41: 113 | D41: =_xlfn.XLOOKUP(C41,'Annexe Etat'!$I$2:$I$164,'Annexe Etat'!$J$2:$J$164) -> Paysages, eau et biodiversité | E41: CELRL - Conservatoire de l'espace littoral et des rivages lacustres | F41: 1 | G41: =H41+I41 -> 208 | H41: 178 | I41: 30 | J41: =K41+L41 -> 206 | K41: 178 | L41: 28 | N41: X
A42: =_xlfn.XLOOKUP(C42,'Annexe Etat'!$I$2:$I$164,'Annexe Etat'!$H$2:$H$164) -> TB | B42: =_xlfn.XLOOKUP(A42,'Annexe Etat'!$A$2:$A$164,'Annexe Etat'!$B$2:$B$164) -> Travail, emploi et administration des ministères sociaux | C42: 103 | D42: =_xlfn.XLOOKUP(C42,'Annexe Etat'!$I$2:$I$164,'Annexe Etat'!$J$2:$J$164) -> Accompagnement des mutations économiques et développement de l'emploi | E42: Centre inffo - Centre pour le développement de l'information sur la formation permanente | F42: 1 | G42: =H42+I42 -> 72 | H42: 72 | I42: 0 | J42: =K42+L42 -> 0 | K42: 0 | L42: 0 | O42: X
A43: =_xlfn.XLOOKUP(C43,'Annexe Etat'!$I$2:$I$164,'Annexe Etat'!$H$2:$H$164) -> TA | B43: =_xlfn.XLOOKUP(A43,'Annexe Etat'!$A$2:$A$164,'Annexe Etat'!$B$2:$B$164) -> Écologie, développement et mobilité durables | C43: 159 | D43: =_xlfn.XLOOKUP(C43,'Annexe Etat'!$I$2:$I$164,'Annexe Etat'!$J$2:$J$164) -> Expertise, information géographique et météorologie | E43: CEREMA - Centre d'études et d'expertise sur les risques, l'environnement, la mobilité et l'aménagement | F43: 1 | G43: =H43+I43 -> 2617 | H43: 2495 | I43: 122 | J43: =K43+L43 -> 2610 | K43: 2470 | L43: 140 | N43: X
A44: =_xlfn.XLOOKUP(C44,'Annexe Etat'!$I$2:$I$164,'Annexe Etat'!$H$2:$H$164) -> EC | B44: =_xlfn.XLOOKUP(A44,'Annexe Etat'!$A$2:$A$164,'Annexe Etat'!$B$2:$B$164) -> Enseignement scolaire | C44: 214 | D44: =_xlfn.XLOOKUP(C44,'Annexe Etat'!$I$2:$I$164,'Annexe Etat'!$J$2:$J$164) -> Soutien de la politique de l'éducation nationale | E44: CEREQ - Centre d'Etudes et de Recherches sur les Qualifications | F44: 1 | G44: =H44+I44 -> 107 | H44: 99 | I44: 8 | J44: =K44+L44 -> 102 | K44: 96 | L44: 6 | O44: X
A45: =_xlfn.XLOOKUP(C45,'Annexe Etat'!$I$2:$I$164,'Annexe Etat'!$H$2:$H$164) -> VA | B45: =_xlfn.XLOOKUP(A45,'Annexe Etat'!$A$2:$A$164,'Annexe Etat'!$B$2:$B$164) -> Cohésion des territoires | C45: 135 | D45: =_xlfn.XLOOKUP(C45,'Annexe Etat'!$I$2:$I$164,'Annexe Etat'!$J$2:$J$164) -> Urbanisme, territoires et amélioration de l'habitat | E45: CGLLS - Caisse de garantie du logement locatif social | F45: 1 | G45: =H45+I45 -> 29 | H45: 29 | I45: 0 | J45: =K45+L45 -> 29 | K45: 29 | L45: 0 | O45: X
A46: =_xlfn.XLOOKUP(C46,'Annexe Etat'!$I$2:$I$164,'Annexe Etat'!$H$2:$H$164) -> CB | B46: =_xlfn.XLOOKUP(A46,'Annexe Etat'!$A$2:$A$164,'Annexe Etat'!$B$2:$B$164) -> Culture | C46: 131 | D46: =_xlfn.XLOOKUP(C46,'Annexe Etat'!$I$2:$I$164,'Annexe Etat'!$J$2:$J$164) -> Création | E46: Chaillot – Théâtre national de la Danse | F46: 1 | G46: =H46+I46 -> 137 | H46: 137 | I46: 0 | J46: =K46+L46 -> 136 | K46: 136 | L46: 0 | N46: X
A47: =_xlfn.XLOOKUP(C47,'Annexe Etat'!$I$2:$I$164,'Annexe Etat'!$H$2:$H$164) -> MA | B47: =_xlfn.XLOOKUP(A47,'Annexe Etat'!$A$2:$A$164,'Annexe Etat'!$B$2:$B$164) -> Médias, livre et industries culturelles | C47: 334 | D47: =_xlfn.XLOOKUP(C47,'Annexe Etat'!$I$2:$I$164,'Annexe Etat'!$J$2:$J$164) -> Livre et industries culturelles | E47: Cinémathèque française | F47: 1 | G47: =H47+I47 -> 213 | H47: 213 | I47: 0 | J47: =K47+L47 -> 212 | K47: 212 | L47: 0 | N47: X
A48: =_xlfn.XLOOKUP(C48,'Annexe Etat'!$I$2:$I$164,'Annexe Etat'!$H$2:$H$164) -> RA | B48: =_xlfn.XLOOKUP(A48,'Annexe Etat'!$A$2:$A$164,'Annexe Etat'!$B$2:$B$164) -> Recherche et enseignement supérieur | C48: 172 | D48: =_xlfn.XLOOKUP(C48,'Annexe Etat'!$I$2:$I$164,'Annexe Etat'!$J$2:$J$164) -> Recherches scientifiques et technologiques pluridisciplinaires | E48: CIRAD - Centre de coopération internationale en recherche agronomique pour le développement | F48: 1 | G48: =H48+I48 -> 1895 | H48: 1779 | I48: 116 | J48: =K48+L48 -> 1898 | K48: 1779 | L48: 119 | O48: X
A49: =_xlfn.XLOOKUP(C49,'Annexe Etat'!$I$2:$I$164,'Annexe Etat'!$H$2:$H$164) -> CB | B49: =_xlfn.XLOOKUP(A49,'Annexe Etat'!$A$2:$A$164,'Annexe Etat'!$B$2:$B$164) -> Culture | C49: 175 | D49: =_xlfn.XLOOKUP(C49,'Annexe Etat'!$I$2:$I$164,'Annexe Etat'!$J$2:$J$164) -> Patrimoines | E49: CMN - Centre des monuments nationaux | F49: 1 | G49: =H49+I49 -> 1529 | H49: 1493 | I49: 36 | J49: =K49+L49 -> 1553 | K49: 1517 | L49: 36 | P49: X
A50: =_xlfn.XLOOKUP(C50,'Annexe Etat'!$I$2:$I$164,'Annexe Etat'!$H$2:$H$164) -> CB | B50: =_xlfn.XLOOKUP(A50,'Annexe Etat'!$A$2:$A$164,'Annexe Etat'!$B$2:$B$164) -> Culture | C50: 361 | D50: =_xlfn.XLOOKUP(C50,'Annexe Etat'!$I$2:$I$164,'Annexe Etat'!$J$2:$J$164) -> Transmission des savoirs et démocratisation de la culture | E50: CNAC - Centre national des arts du cirque | F50: 1 | G50: =H50+I50 -> 37 | H50: 37 | I50: 0 | J50: =K50+L50 -> 37 | K50: 37 | L50: 0 | N50: X
A51: =_xlfn.XLOOKUP(C51,'Annexe Etat'!$I$2:$I$164,'Annexe Etat'!$H$2:$H$164) -> CB | B51: =_xlfn.XLOOKUP(A51,'Annexe Etat'!$A$2:$A$164,'Annexe Etat'!$B$2:$B$164) -> Culture | C51: 175 | D51: =_xlfn.XLOOKUP(C51,'Annexe Etat'!$I$2:$I$164,'Annexe Etat'!$J$2:$J$164) -> Patrimoines | E51: CNAC-GP - Centre national d'art et de culture - Georges Pompidou | F51: 1 | G51: =H51+I51 -> 1007 | H51: 1007 | I51: 0 | J51: =K51+L51 -> 945 | K51: 945 | L51: 0 | P51: X
A52: =_xlfn.XLOOKUP(C52,'Annexe Etat'!$I$2:$I$164,'Annexe Etat'!$H$2:$H$164) -> CB | B52: =_xlfn.XLOOKUP(A52,'Annexe Etat'!$A$2:$A$164,'Annexe Etat'!$B$2:$B$164) -> Culture | C52: 131 | D52: =_xlfn.XLOOKUP(C52,'Annexe Etat'!$I$2:$I$164,'Annexe Etat'!$J$2:$J$164) -> Création | E52: CNAP - Centre national des arts plastiques | F52: 1 | G52: =H52+I52 -> 21 | H52: 21 | I52: 0 | J52: =K52+L52 -> 21 | K52: 21 | L52: 0 | N52: X
A53: =_xlfn.XLOOKUP(C53,'Annexe Etat'!$I$2:$I$164,'Annexe Etat'!$H$2:$H$164) -> AB | B53: =_xlfn.XLOOKUP(A53,'Annexe Etat'!$A$2:$A$164,'Annexe Etat'!$B$2:$B$164) -> Administration générale et territoriale de l'État | C53: 216 | D53: =_xlfn.XLOOKUP(C53,'Annexe Etat'!$I$2:$I$164,'Annexe Etat'!$J$2:$J$164) -> Conduite et pilotage des politiques de l'intérieur | E53: CNAPS - Conseil national des activités privées de sécurité | F53: 1 | G53: =H53+I53 -> 217 | H53: 217 | I53: 0 | J53: =K53+L53 -> 217 | K53: 217 | L53: 0 | O53: X
A54: =_xlfn.XLOOKUP(C54,'Annexe Etat'!$I$2:$I$164,'Annexe Etat'!$H$2:$H$164) -> MA | B54: =_xlfn.XLOOKUP(A54,'Annexe Etat'!$A$2:$A$164,'Annexe Etat'!$B$2:$B$164) -> Médias, livre et industries culturelles | C54: 334 | D54: =_xlfn.XLOOKUP(C54,'Annexe Etat'!$I$2:$I$164,'Annexe Etat'!$J$2:$J$164) -> Livre et industries culturelles | E54: CNC - Centre national du cinéma et de l'image animée | F54: 1 | G54: =H54+I54 -> 450 | H54: 450 | I54: 0 | J54: =K54+L54 -> 458 | K54: 458 | L54: 0 | O54: X
A55: =_xlfn.XLOOKUP(C55,'Annexe Etat'!$I$2:$I$164,'Annexe Etat'!$H$2:$H$164) -> CB | B55: =_xlfn.XLOOKUP(A55,'Annexe Etat'!$A$2:$A$164,'Annexe Etat'!$B$2:$B$164) -> Culture | C55: 131 | D55: =_xlfn.XLOOKUP(C55,'Annexe Etat'!$I$2:$I$164,'Annexe Etat'!$J$2:$J$164) -> Création | E55: CND - Centre national de la danse | F55: 1 | G55: =H55+I55 -> 99 | H55: 99 | I55: 0 | J55: =K55+L55 -> 98 | K55: 98 | L55: 0 | O55: X
A56: =_xlfn.XLOOKUP(C56,'Annexe Etat'!$I$2:$I$164,'Annexe Etat'!$H$2:$H$164) -> EC | B56: =_xlfn.XLOOKUP(A56,'Annexe Etat'!$A$2:$A$164,'Annexe Etat'!$B$2:$B$164) -> Enseignement scolaire | C56: 214 | D56: =_xlfn.XLOOKUP(C56,'Annexe Etat'!$I$2:$I$164,'Annexe Etat'!$J$2:$J$164) -> Soutien de la politique de l'éducation nationale | E56: CNED - Centre national d'enseignement à distance | F56: 1 | G56: =H56+I56 -> 957 | H56: 927 | I56: 30 | J56: =K56+L56 -> 957 | K56: 927 | L56: 30 | Q56: X
A57: =_xlfn.XLOOKUP(C57,'Annexe Etat'!$I$2:$I$164,'Annexe Etat'!$H$2:$H$164) -> RA | B57: =_xlfn.XLOOKUP(A57,'Annexe Etat'!$A$2:$A$164,'Annexe Etat'!$B$2:$B$164) -> Recherche et enseignement supérieur | C57: 193 | D57: =_xlfn.XLOOKUP(C57,'Annexe Etat'!$I$2:$I$164,'Annexe Etat'!$J$2:$J$164) -> Recherche spatiale | E57: CNES - Centre national d'études spatiales | F57: 1 | G57: =H57+I57 -> 2674 | H57: 2404 | I57: 270 | J57: =K57+L57 -> 2394 | K57: 2394 | L57: 0 | Q57: X
A58: =_xlfn.XLOOKUP(C58,'Annexe Etat'!$I$2:$I$164,'Annexe Etat'!$H$2:$H$164) -> MA | B58: =_xlfn.XLOOKUP(A58,'Annexe Etat'!$A$2:$A$164,'Annexe Etat'!$B$2:$B$164) -> Médias, livre et industries culturelles | C58: 334 | D58: =_xlfn.XLOOKUP(C58,'Annexe Etat'!$I$2:$I$164,'Annexe Etat'!$J$2:$J$164) -> Livre et industries culturelles | E58: CNL - Centre national du livre | F58: 1 | G58: =H58+I58 -> 66 | H58: 63 | I58: 3 | J58: =K58+L58 -> 63 | K58: 63 | L58: 0 | O58: X
A59: =_xlfn.XLOOKUP(C59,'Annexe Etat'!$I$2:$I$164,'Annexe Etat'!$H$2:$H$164) -> MA | B59: =_xlfn.XLOOKUP(A59,'Annexe Etat'!$A$2:$A$164,'Annexe Etat'!$B$2:$B$164) -> Médias, livre et industries culturelles | C59: 334 | D59: =_xlfn.XLOOKUP(C59,'Annexe Etat'!$I$2:$I$164,'Annexe Etat'!$J$2:$J$164) -> Livre et industries culturelles | E59: CNM - Centre national de la musique | F59: 1 | G59: =H59+I59 -> 131 | H59: 121 | I59: 10 | J59: =K59+L59 -> 121 | K59: 121 | L59: 0 | O59: X
A60: =_xlfn.XLOOKUP(C60,'Annexe Etat'!$I$2:$I$164,'Annexe Etat'!$H$2:$H$164) -> AC | B60: =_xlfn.XLOOKUP(A60,'Annexe Etat'!$A$2:$A$164,'Annexe Etat'!$B$2:$B$164) -> Agriculture, alimentation, forêt et affaires rurales | C60: 149 | D60: =_xlfn.XLOOKUP(C60,'Annexe Etat'!$I$2:$I$164,'Annexe Etat'!$J$2:$J$164) -> Compétitivité et durabilité de l'agriculture, de l'agroalimentaire et de la forêt | E60: CNPF - Centre national de la propriété forestière | F60: 1 | G60: =H60+I60 -> 468 | H60: 368 | I60: 100 | J60: =K60+L60 -> 471 | K60: 374 | L60: 97 | O60: X
A61: =_xlfn.XLOOKUP(C61,'Annexe Etat'!$I$2:$I$164,'Annexe Etat'!$H$2:$H$164) -> RA | B61: =_xlfn.XLOOKUP(A61,'Annexe Etat'!$A$2:$A$164,'Annexe Etat'!$B$2:$B$164) -> Recherche et enseignement supérieur | C61: 172 | D61: =_xlfn.XLOOKUP(C61,'Annexe Etat'!$I$2:$I$164,'Annexe Etat'!$J$2:$J$164) -> Recherches scientifiques et technologiques pluridisciplinaires | E61: CNRS - Centre national de la recherche scientifique | F61: 1 | G61: =H61+I61 -> 37199 | H61: 25999 | I61: 11200 | J61: =K61+L61 -> 37747 | K61: 26047 | L61: 11700 | Q61: X
A62: =_xlfn.XLOOKUP(C62,'Annexe Etat'!$I$2:$I$164,'Annexe Etat'!$H$2:$H$164) -> CB | B62: =_xlfn.XLOOKUP(A62,'Annexe Etat'!$A$2:$A$164,'Annexe Etat'!$B$2:$B$164) -> Culture | C62: 361 | D62: =_xlfn.XLOOKUP(C62,'Annexe Etat'!$I$2:$I$164,'Annexe Etat'!$J$2:$J$164) -> Transmission des savoirs et démocratisation de la culture | E62: CNSAD - Conservatoire national supérieur d'art dramatique | F62: 1 | G62: =H62+I62 -> 41 | H62: 41 | I62: 0 | J62: =K62+L62 -> 41 | K62: 41 | L62: 0 | Q62: X
A63: =_xlfn.XLOOKUP(C63,'Annexe Etat'!$I$2:$I$164,'Annexe Etat'!$H$2:$H$164) -> CB | B63: =_xlfn.XLOOKUP(A63,'Annexe Etat'!$A$2:$A$164,'Annexe Etat'!$B$2:$B$164) -> Culture | C63: 361 | D63: =_xlfn.XLOOKUP(C63,'Annexe Etat'!$I$2:$I$164,'Annexe Etat'!$J$2:$J$164) -> Transmission des savoirs et démocratisation de la culture | E63: CNSMD Lyon - Conservatoire national supérieur de musique et de danse de Lyon | F63: 1 | G63: =H63+I63 -> 206 | H63: 206 | I63: 0 | J63: =K63+L63 -> 206 | K63: 206 | L63: 0 | Q63: X
A64: =_xlfn.XLOOKUP(C64,'Annexe Etat'!$I$2:$I$164,'Annexe Etat'!$H$2:$H$164) -> CB | B64: =_xlfn.XLOOKUP(A64,'Annexe Etat'!$A$2:$A$164,'Annexe Etat'!$B$2:$B$164) -> Culture | C64: 361 | D64: =_xlfn.XLOOKUP(C64,'Annexe Etat'!$I$2:$I$164,'Annexe Etat'!$J$2:$J$164) -> Transmission des savoirs et démocratisation de la culture | E64: CNSMD Paris - Conservatoire national supérieur de musique et de danse de Paris | F64: 1 | G64: =H64+I64 -> 349 | H64: 349 | I64: 0 | J64: =K64+L64 -> 349 | K64: 349 | L64: 0 | Q64: X
A65: =_xlfn.XLOOKUP(C65,'Annexe Etat'!$I$2:$I$164,'Annexe Etat'!$H$2:$H$164) -> CB | B65: =_xlfn.XLOOKUP(A65,'Annexe Etat'!$A$2:$A$164,'Annexe Etat'!$B$2:$B$164) -> Culture | C65: 131 | D65: =_xlfn.XLOOKUP(C65,'Annexe Etat'!$I$2:$I$164,'Annexe Etat'!$J$2:$J$164) -> Création | E65: Comédie Française | F65: 1 | G65: =H65+I65 -> 399 | H65: 399 | I65: 0 | J65: =K65+L65 -> 397 | K65: 397 | L65: 0 | P65: X
A66: =_xlfn.XLOOKUP(C66,'Annexe Etat'!$I$2:$I$164,'Annexe Etat'!$H$2:$H$164) -> RA | B66: =_xlfn.XLOOKUP(A66,'Annexe Etat'!$A$2:$A$164,'Annexe Etat'!$B$2:$B$164) -> Recherche et enseignement supérieur | C66: 150 | D66: =_xlfn.XLOOKUP(C66,'Annexe Etat'!$I$2:$I$164,'Annexe Etat'!$J$2:$J$164) -> Formations supérieures et recherche universitaire | E66: Communautés d'universités et d'établissements | F66: 5 | G66: =H66+I66 -> 1419 | H66: 978 | I66: 441 | J66: =K66+L66 -> 1529 | K66: 978 | L66: 551 | O66: X
A67: =_xlfn.XLOOKUP(C67,'Annexe Etat'!$I$2:$I$164,'Annexe Etat'!$H$2:$H$164) -> DA | B67: =_xlfn.XLOOKUP(A67,'Annexe Etat'!$A$2:$A$164,'Annexe Etat'!$B$2:$B$164) -> Défense | C67: 178 | D67: =_xlfn.XLOOKUP(C67,'Annexe Etat'!$I$2:$I$164,'Annexe Etat'!$J$2:$J$164) -> Préparation et emploi des forces | E67: Ecole de l'air et de l'espace | F67: 1 | G67: =H67+I67 -> 319 | H67: 300 | I67: 19 | J67: =K67+L67 -> 319 | K67: 300 | L67: 19 | Q67: X
A68: =_xlfn.XLOOKUP(C68,'Annexe Etat'!$I$2:$I$164,'Annexe Etat'!$H$2:$H$164) -> CB | B68: =_xlfn.XLOOKUP(A68,'Annexe Etat'!$A$2:$A$164,'Annexe Etat'!$B$2:$B$164) -> Culture | C68: 361 | D68: =_xlfn.XLOOKUP(C68,'Annexe Etat'!$I$2:$I$164,'Annexe Etat'!$J$2:$J$164) -> Transmission des savoirs et démocratisation de la culture | E68: Ecole du Louvre | F68: 1 | G68: =H68+I68 -> 41 | H68: 32 | I68: 9 | J68: =K68+L68 -> 41 | K68: 32 | L68: 9 | Q68: X
A69: =_xlfn.XLOOKUP(C69,'Annexe Etat'!$I$2:$I$164,'Annexe Etat'!$H$2:$H$164) -> DA | B69: =_xlfn.XLOOKUP(A69,'Annexe Etat'!$A$2:$A$164,'Annexe Etat'!$B$2:$B$164) -> Défense | C69: 178 | D69: =_xlfn.XLOOKUP(C69,'Annexe Etat'!$I$2:$I$164,'Annexe Etat'!$J$2:$J$164) -> Préparation et emploi des forces | E69: Ecole navale | F69: 1 | G69: =H69+I69 -> 410 | H69: 370 | I69: 40 | J69: =K69+L69 -> 412 | K69: 372 | L69: 40 | Q69: X
A70: =_xlfn.XLOOKUP(C70,'Annexe Etat'!$I$2:$I$164,'Annexe Etat'!$H$2:$H$164) -> CB | B70: =_xlfn.XLOOKUP(A70,'Annexe Etat'!$A$2:$A$164,'Annexe Etat'!$B$2:$B$164) -> Culture | C70: 361 | D70: =_xlfn.XLOOKUP(C70,'Annexe Etat'!$I$2:$I$164,'Annexe Etat'!$J$2:$J$164) -> Transmission des savoirs et démocratisation de la culture | E70: Ecoles d'architecture - Ecoles nationales supérieures d'architecture | F70: 20 | G70: =H70+I70 -> 789 | H70: 789 | I70: 0 | J70: =K70+L70 -> 789 | K70: 789 | L70: 0 | Q70: X
A71: =_xlfn.XLOOKUP(C71,'Annexe Etat'!$I$2:$I$164,'Annexe Etat'!$H$2:$H$164) -> CB | B71: =_xlfn.XLOOKUP(A71,'Annexe Etat'!$A$2:$A$164,'Annexe Etat'!$B$2:$B$164) -> Culture | C71: 361 | D71: =_xlfn.XLOOKUP(C71,'Annexe Etat'!$I$2:$I$164,'Annexe Etat'!$J$2:$J$164) -> Transmission des savoirs et démocratisation de la culture | E71: Ecoles d'art en Région | F71: 7 | G71: =H71+I71 -> 105 | H71: 105 | I71: 0 | J71: =K71+L71 -> 105 | K71: 105 | L71: 0 | Q71: X
A72: =_xlfn.XLOOKUP(C72,'Annexe Etat'!$I$2:$I$164,'Annexe Etat'!$H$2:$H$164) -> RA | B72: =_xlfn.XLOOKUP(A72,'Annexe Etat'!$A$2:$A$164,'Annexe Etat'!$B$2:$B$164) -> Recherche et enseignement supérieur | C72: 142 | D72: =_xlfn.XLOOKUP(C72,'Annexe Etat'!$I$2:$I$164,'Annexe Etat'!$J$2:$J$164) -> Enseignement supérieur et recherche agricoles | E72: Ecoles d'enseignement supérieur agricole et vétérinaire | F72: 10 | G72: =H72+I72 -> 1451 | H72: 1137 | I72: 314 | J72: =K72+L72 -> 1127 | K72: 1127 | L72: 0 | Q72: X
A73: =_xlfn.XLOOKUP(C73,'Annexe Etat'!$I$2:$I$164,'Annexe Etat'!$H$2:$H$164) -> RA | B73: =_xlfn.XLOOKUP(A73,'Annexe Etat'!$A$2:$A$164,'Annexe Etat'!$B$2:$B$164) -> Recherche et enseignement supérieur | C73: 150 | D73: =_xlfn.XLOOKUP(C73,'Annexe Etat'!$I$2:$I$164,'Annexe Etat'!$J$2:$J$164) -> Formations supérieures et recherche universitaire | E73: Ecoles et formations d'ingénieurs | F73: 35 | G73: =H73+I73 -> 13338 | H73: 9964 | I73: 3374 | J73: =K73+L73 -> 13693 | K73: 9964 | L73: 3729 | Q73: X
A74: =_xlfn.XLOOKUP(C74,'Annexe Etat'!$I$2:$I$164,'Annexe Etat'!$H$2:$H$164) -> SF | B74: =_xlfn.XLOOKUP(A74,'Annexe Etat'!$A$2:$A$164,'Annexe Etat'!$B$2:$B$164) -> Sport, jeunesse et vie associative | C74: 219 | D74: =_xlfn.XLOOKUP(C74,'Annexe Etat'!$I$2:$I$164,'Annexe Etat'!$J$2:$J$164) -> Sport | E74: Ecoles nationales des sports | F74: 2 | G74: =H74+I74 -> 200 | H74: 193 | I74: 7 | J74: =K74+L74 -> 199 | K74: 193 | L74: 6 | Q74: X
A75: =_xlfn.XLOOKUP(C75,'Annexe Etat'!$I$2:$I$164,'Annexe Etat'!$H$2:$H$164) -> DA | B75: =_xlfn.XLOOKUP(A75,'Annexe Etat'!$A$2:$A$164,'Annexe Etat'!$B$2:$B$164) -> Défense | C75: 212 | D75: =_xlfn.XLOOKUP(C75,'Annexe Etat'!$I$2:$I$164,'Annexe Etat'!$J$2:$J$164) -> Soutien de la politique de la défense | E75: ECPAD - Etablissement de communication et de production audiovisuelle de la défense | F75: 1 | G75: =H75+I75 -> 263 | H75: 257 | I75: 6 | J75: =K75+L75 -> 263 | K75: 257 | L75: 6 | N75: X
A76: =_xlfn.XLOOKUP(C76,'Annexe Etat'!$I$2:$I$164,'Annexe Etat'!$H$2:$H$164) -> XC | B76: =_xlfn.XLOOKUP(A76,'Annexe Etat'!$A$2:$A$164,'Annexe Etat'!$B$2:$B$164) -> Contrôle et exploitation aériens | C76: 613 | D76: =_xlfn.XLOOKUP(C76,'Annexe Etat'!$I$2:$I$164,'Annexe Etat'!$J$2:$J$164) -> Soutien aux prestations de l'aviation civile | E76: ENAC - Ecole nationale de l'aviation civile | F76: 1 | G76: =H76+I76 -> 929 | H76: 789 | I76: 140 | J76: =K76+L76 -> 922 | K76: 782 | L76: 140 | Q76: X
A77: =_xlfn.XLOOKUP(C77,'Annexe Etat'!$I$2:$I$164,'Annexe Etat'!$H$2:$H$164) -> JA | B77: =_xlfn.XLOOKUP(A77,'Annexe Etat'!$A$2:$A$164,'Annexe Etat'!$B$2:$B$164) -> Justice | C77: 107 | D77: =_xlfn.XLOOKUP(C77,'Annexe Etat'!$I$2:$I$164,'Annexe Etat'!$J$2:$J$164) -> Administration pénitentiaire | E77: ENAP - Ecole nationale de l'administration pénitentiaire | F77: 1 | G77: =H77+I77 -> 275 | H77: 275 | I77: 0 | J77: =K77+L77 -> 275 | K77: 275 | L77: 0 | Q77: X
A78: =_xlfn.XLOOKUP(C78,'Annexe Etat'!$I$2:$I$164,'Annexe Etat'!$H$2:$H$164) -> RB | B78: =_xlfn.XLOOKUP(A78,'Annexe Etat'!$A$2:$A$164,'Annexe Etat'!$B$2:$B$164) -> Régimes sociaux et de retraite | C78: 197 | D78: =_xlfn.XLOOKUP(C78,'Annexe Etat'!$I$2:$I$164,'Annexe Etat'!$J$2:$J$164) -> Régimes de retraite et de sécurité sociale des marins | E78: ENIM - Etablissement national des invalides de la marine | F78: 1 | G78: =H78+I78 -> 293 | H78: 286 | I78: 7 | J78: =K78+L78 -> 290 | K78: 283 | L78: 7 | R78: X
A79: =_xlfn.XLOOKUP(C79,'Annexe Etat'!$I$2:$I$164,'Annexe Etat'!$H$2:$H$164) -> JA | B79: =_xlfn.XLOOKUP(A79,'Annexe Etat'!$A$2:$A$164,'Annexe Etat'!$B$2:$B$164) -> Justice | C79: 166 | D79: =_xlfn.XLOOKUP(C79,'Annexe Etat'!$I$2:$I$164,'Annexe Etat'!$J$2:$J$164) -> Justice judiciaire | E79: ENM - Ecole nationale de la magistrature | F79: 1 | G79: =H79+I79 -> 283 | H79: 283 | I79: 0 | J79: =K79+L79 -> 283 | K79: 283 | L79: 0 | Q79: X
A80: =_xlfn.XLOOKUP(C80,'Annexe Etat'!$I$2:$I$164,'Annexe Etat'!$H$2:$H$164) -> TA | B80: =_xlfn.XLOOKUP(A80,'Annexe Etat'!$A$2:$A$164,'Annexe Etat'!$B$2:$B$164) -> Écologie, développement et mobilité durables | C80: 217 | D80: =_xlfn.XLOOKUP(C80,'Annexe Etat'!$I$2:$I$164,'Annexe Etat'!$J$2:$J$164) -> Conduite et pilotage des politiques de l'écologie, du développement et de la mobilité durables | E80: ENPC - Ecole nationale des Ponts et Chaussées | F80: 1 | G80: =H80+I80 -> 509 | H80: 309 | I80: 200 | J80: =K80+L80 -> 489 | K80: 307 | L80: 182 | Q80: X
A81: =_xlfn.XLOOKUP(C81,'Annexe Etat'!$I$2:$I$164,'Annexe Etat'!$H$2:$H$164) -> CB | B81: =_xlfn.XLOOKUP(A81,'Annexe Etat'!$A$2:$A$164,'Annexe Etat'!$B$2:$B$164) -> Culture | C81: 361 | D81: =_xlfn.XLOOKUP(C81,'Annexe Etat'!$I$2:$I$164,'Annexe Etat'!$J$2:$J$164) -> Transmission des savoirs et démocratisation de la culture | E81: ENSAD - Ecole nationale supérieure des arts décoratifs | F81: 1 | G81: =H81+I81 -> 152 | H81: 152 | I81: 0 | J81: =K81+L81 -> 152 | K81: 152 | L81: 0 | Q81: X
A82: =_xlfn.XLOOKUP(C82,'Annexe Etat'!$I$2:$I$164,'Annexe Etat'!$H$2:$H$164) -> CB | B82: =_xlfn.XLOOKUP(A82,'Annexe Etat'!$A$2:$A$164,'Annexe Etat'!$B$2:$B$164) -> Culture | C82: 361 | D82: =_xlfn.XLOOKUP(C82,'Annexe Etat'!$I$2:$I$164,'Annexe Etat'!$J$2:$J$164) -> Transmission des savoirs et démocratisation de la culture | E82: ENSBA - Ecole nationale supérieure des beaux-arts | F82: 1 | G82: =H82+I82 -> 111 | H82: 111 | I82: 0 | J82: =K82+L82 -> 111 | K82: 111 | L82: 0 | Q82: X
A83: =_xlfn.XLOOKUP(C83,'Annexe Etat'!$I$2:$I$164,'Annexe Etat'!$H$2:$H$164) -> CB | B83: =_xlfn.XLOOKUP(A83,'Annexe Etat'!$A$2:$A$164,'Annexe Etat'!$B$2:$B$164) -> Culture | C83: 361 | D83: =_xlfn.XLOOKUP(C83,'Annexe Etat'!$I$2:$I$164,'Annexe Etat'!$J$2:$J$164) -> Transmission des savoirs et démocratisation de la culture | E83: ENSCI - Ecole nationale supérieure de création industrielle | F83: 1 | G83: =H83+I83 -> 68 | H83: 68 | I83: 0 | J83: =K83+L83 -> 68 | K83: 68 | L83: 0 | Q83: X
A84: =_xlfn.XLOOKUP(C84,'Annexe Etat'!$I$2:$I$164,'Annexe Etat'!$H$2:$H$164) -> CB | B84: =_xlfn.XLOOKUP(A84,'Annexe Etat'!$A$2:$A$164,'Annexe Etat'!$B$2:$B$164) -> Culture | C84: 131 | D84: =_xlfn.XLOOKUP(C84,'Annexe Etat'!$I$2:$I$164,'Annexe Etat'!$J$2:$J$164) -> Création | E84: Ensemble intercontemporain | F84: 1 | G84: =H84+I84 -> 46 | H84: 46 | I84: 0 | J84: =K84+L84 -> 46 | K84: 46 | L84: 0 | N84: X
A85: =_xlfn.XLOOKUP(C85,'Annexe Etat'!$I$2:$I$164,'Annexe Etat'!$H$2:$H$164) -> TA | B85: =_xlfn.XLOOKUP(A85,'Annexe Etat'!$A$2:$A$164,'Annexe Etat'!$B$2:$B$164) -> Écologie, développement et mobilité durables | C85: 205 | D85: =_xlfn.XLOOKUP(C85,'Annexe Etat'!$I$2:$I$164,'Annexe Etat'!$J$2:$J$164) -> Affaires maritimes, pêche et aquaculture | E85: ENSM - Ecole nationale supérieure maritime | F85: 1 | G85: =H85+I85 -> 239 | H85: 239 | I85: 0 | J85: =K85+L85 -> 249 | K85: 239 | L85: 10 | Q85: X
A86: =_xlfn.XLOOKUP(C86,'Annexe Etat'!$I$2:$I$164,'Annexe Etat'!$H$2:$H$164) -> CB | B86: =_xlfn.XLOOKUP(A86,'Annexe Etat'!$A$2:$A$164,'Annexe Etat'!$B$2:$B$164) -> Culture | C86: 361 | D86: =_xlfn.XLOOKUP(C86,'Annexe Etat'!$I$2:$I$164,'Annexe Etat'!$J$2:$J$164) -> Transmission des savoirs et démocratisation de la culture | E86: ENSMIS - Ecole nationale supérieure des métiers de l'image et du son | F86: 1 | G86: =H86+I86 -> 69 | H86: 69 | I86: 0 | J86: =K86+L86 -> 69 | K86: 69 | L86: 0 | Q86: X
A87: =_xlfn.XLOOKUP(C87,'Annexe Etat'!$I$2:$I$164,'Annexe Etat'!$H$2:$H$164) -> SB | B87: =_xlfn.XLOOKUP(A87,'Annexe Etat'!$A$2:$A$164,'Annexe Etat'!$B$2:$B$164) -> Sécurités | C87: 176 | D87: =_xlfn.XLOOKUP(C87,'Annexe Etat'!$I$2:$I$164,'Annexe Etat'!$J$2:$J$164) -> Police nationale | E87: ENSPolice - Ecole nationale supérieure de la police | F87: 1 | G87: =H87+I87 -> 298 | H87: 290 | I87: 8 | J87: =K87+L87 -> 298 | K87: 290 | L87: 8 | Q87: X
A88: =_xlfn.XLOOKUP(C88,'Annexe Etat'!$I$2:$I$164,'Annexe Etat'!$H$2:$H$164) -> DA | B88: =_xlfn.XLOOKUP(A88,'Annexe Etat'!$A$2:$A$164,'Annexe Etat'!$B$2:$B$164) -> Défense | C88: 144 | D88: =_xlfn.XLOOKUP(C88,'Annexe Etat'!$I$2:$I$164,'Annexe Etat'!$J$2:$J$164) -> Environnement et prospective de la politique de défense | E88: ENSTA - Ecole nationale supérieure de techniques avancées | F88: 1 | G88: =H88+I88 -> 514 | H88: 364 | I88: 150 | J88: =K88+L88 -> 538 | K88: 368 | L88: 170 | Q88: X
A89: =_xlfn.XLOOKUP(C89,'Annexe Etat'!$I$2:$I$164,'Annexe Etat'!$H$2:$H$164) -> TA | B89: =_xlfn.XLOOKUP(A89,'Annexe Etat'!$A$2:$A$164,'Annexe Etat'!$B$2:$B$164) -> Écologie, développement et mobilité durables | C89: 217 | D89: =_xlfn.XLOOKUP(C89,'Annexe Etat'!$I$2:$I$164,'Annexe Etat'!$J$2:$J$164) -> Conduite et pilotage des politiques de l'écologie, du développement et de la mobilité durables | E89: ENTPE - Ecole nationale des travaux publics de l'Etat | F89: 1 | G89: =H89+I89 -> 233 | H89: 183 | I89: 50 | J89: =K89+L89 -> 223 | K89: 181 | L89: 42 | Q89: X
A90: =_xlfn.XLOOKUP(C90,'Annexe Etat'!$I$2:$I$164,'Annexe Etat'!$H$2:$H$164) -> CB | B90: =_xlfn.XLOOKUP(A90,'Annexe Etat'!$A$2:$A$164,'Annexe Etat'!$B$2:$B$164) -> Culture | C90: 131 | D90: =_xlfn.XLOOKUP(C90,'Annexe Etat'!$I$2:$I$164,'Annexe Etat'!$J$2:$J$164) -> Création | E90: EPCMPP - Etablissement public de la Cité de la musique - Philharmonie de Paris | F90: 1 | G90: =H90+I90 -> 498 | H90: 498 | I90: 0 | J90: =K90+L90 -> 496 | K90: 496 | L90: 0 | P90: X
A91: =_xlfn.XLOOKUP(C91,'Annexe Etat'!$I$2:$I$164,'Annexe Etat'!$H$2:$H$164) -> TB | B91: =_xlfn.XLOOKUP(A91,'Annexe Etat'!$A$2:$A$164,'Annexe Etat'!$B$2:$B$164) -> Travail, emploi et administration des ministères sociaux | C91: 102 | D91: =_xlfn.XLOOKUP(C91,'Annexe Etat'!$I$2:$I$164,'Annexe Etat'!$J$2:$J$164) -> Accès et retour à l'emploi | E91: EPIDE - Etablissement pour l'insertion dans l'emploi | F91: 1 | G91: =H91+I91 -> 1142 | H91: 1142 | I91: 0 | J91: =K91+L91 -> 1142 | K91: 1142 | L91: 0 | Q91: X
A92: =_xlfn.XLOOKUP(C92,'Annexe Etat'!$I$2:$I$164,'Annexe Etat'!$H$2:$H$164) -> CB | B92: =_xlfn.XLOOKUP(A92,'Annexe Etat'!$A$2:$A$164,'Annexe Etat'!$B$2:$B$164) -> Culture | C92: 175 | D92: =_xlfn.XLOOKUP(C92,'Annexe Etat'!$I$2:$I$164,'Annexe Etat'!$J$2:$J$164) -> Patrimoines | E92: EPMQB - Etablissement public du musée du quai Branly | F92: 1 | G92: =H92+I92 -> 247 | H92: 247 | I92: 0 | J92: =K92+L92 -> 246 | K92: 246 | L92: 0 | P92: X
A93: =_xlfn.XLOOKUP(C93,'Annexe Etat'!$I$2:$I$164,'Annexe Etat'!$H$2:$H$164) -> CB | B93: =_xlfn.XLOOKUP(A93,'Annexe Etat'!$A$2:$A$164,'Annexe Etat'!$B$2:$B$164) -> Culture | C93: 175 | D93: =_xlfn.XLOOKUP(C93,'Annexe Etat'!$I$2:$I$164,'Annexe Etat'!$J$2:$J$164) -> Patrimoines | E93: EPMSM - Etablissement public du Mont-Saint-Michel | F93: 1 | G93: =H93+I93 -> 19 | H93: 16 | I93: 3 | J93: =K93+L93 -> 19 | K93: 16 | L93: 3 | P93: X
A94: =_xlfn.XLOOKUP(C94,'Annexe Etat'!$I$2:$I$164,'Annexe Etat'!$H$2:$H$164) -> CB | B94: =_xlfn.XLOOKUP(A94,'Annexe Etat'!$A$2:$A$164,'Annexe Etat'!$B$2:$B$164) -> Culture | C94: 175 | D94: =_xlfn.XLOOKUP(C94,'Annexe Etat'!$I$2:$I$164,'Annexe Etat'!$J$2:$J$164) -> Patrimoines | E94: EPPD - Etablissement public du palais de la porte Dorée | F94: 1 | G94: =H94+I94 -> 79 | H94: 75 | I94: 4 | J94: =K94+L94 -> 79 | K94: 75 | L94: 4 | P94: X
A95: =_xlfn.XLOOKUP(C95,'Annexe Etat'!$I$2:$I$164,'Annexe Etat'!$H$2:$H$164) -> CB | B95: =_xlfn.XLOOKUP(A95,'Annexe Etat'!$A$2:$A$164,'Annexe Etat'!$B$2:$B$164) -> Culture | C95: 131 | D95: =_xlfn.XLOOKUP(C95,'Annexe Etat'!$I$2:$I$164,'Annexe Etat'!$J$2:$J$164) -> Création | E95: EPPGHV - Etablissement public du parc et de la grande halle de la Villette | F95: 1 | G95: =H95+I95 -> 215 | H95: 215 | I95: 0 | J95: =K95+L95 -> 215 | K95: 215 | L95: 0 | P95: X
A96: =_xlfn.XLOOKUP(C96,'Annexe Etat'!$I$2:$I$164,'Annexe Etat'!$H$2:$H$164) -> CB | B96: =_xlfn.XLOOKUP(A96,'Annexe Etat'!$A$2:$A$164,'Annexe Etat'!$B$2:$B$164) -> Culture | C96: 175 | D96: =_xlfn.XLOOKUP(C96,'Annexe Etat'!$I$2:$I$164,'Annexe Etat'!$J$2:$J$164) -> Patrimoines | E96: EPRNDP - Etablissement public chargé de la conservation et de la restauration de la cathédrale Notre-Dame de Paris | F96: 1 | G96: =H96+I96 -> 35 | H96: 32 | I96: 3 | J96: =K96+L96 -> 34 | K96: 31 | L96: 3 | P96: X
A97: =_xlfn.XLOOKUP(C97,'Annexe Etat'!$I$2:$I$164,'Annexe Etat'!$H$2:$H$164) -> TA | B97: =_xlfn.XLOOKUP(A97,'Annexe Etat'!$A$2:$A$164,'Annexe Etat'!$B$2:$B$164) -> Écologie, développement et mobilité durables | C97: 203 | D97: =_xlfn.XLOOKUP(C97,'Annexe Etat'!$I$2:$I$164,'Annexe Etat'!$J$2:$J$164) -> Infrastructures et services de transports | E97: EPSF - Etablissement public de sécurité ferroviaire | F97: 1 | G97: =H97+I97 -> 106 | H97: 106 | I97: 0 | J97: =K97+L97 -> 106 | K97: 106 | L97: 0 | R97: X
A98: =_xlfn.XLOOKUP(C98,'Annexe Etat'!$I$2:$I$164,'Annexe Etat'!$H$2:$H$164) -> CB | B98: =_xlfn.XLOOKUP(A98,'Annexe Etat'!$A$2:$A$164,'Annexe Etat'!$B$2:$B$164) -> Culture | C98: 175 | D98: =_xlfn.XLOOKUP(C98,'Annexe Etat'!$I$2:$I$164,'Annexe Etat'!$J$2:$J$164) -> Patrimoines | E98: EPV - Etablissement public du musée et du domaine national de Versailles | F98: 1 | G98: =H98+I98 -> 1032 | H98: 951 | I98: 81 | J98: =K98+L98 -> 1029 | K98: 948 | L98: 81 | P98: X
A99: =_xlfn.XLOOKUP(C99,'Annexe Etat'!$I$2:$I$164,'Annexe Etat'!$H$2:$H$164) -> CB | B99: =_xlfn.XLOOKUP(A99,'Annexe Etat'!$A$2:$A$164,'Annexe Etat'!$B$2:$B$164) -> Culture | C99: 175 | D99: =_xlfn.XLOOKUP(C99,'Annexe Etat'!$I$2:$I$164,'Annexe Etat'!$J$2:$J$164) -> Patrimoines | E99: Etablissement public du château de Fontainebleau | F99: 1 | G99: =H99+I99 -> 12 | H99: 8 | I99: 4 | J99: =K99+L99 -> 12 | K99: 8 | L99: 4 | P99: X
A100: =_xlfn.XLOOKUP(C100,'Annexe Etat'!$I$2:$I$164,'Annexe Etat'!$H$2:$H$164) -> TA | B100: =_xlfn.XLOOKUP(A100,'Annexe Etat'!$A$2:$A$164,'Annexe Etat'!$B$2:$B$164) -> Écologie, développement et mobilité durables | C100: 113 | D100: =_xlfn.XLOOKUP(C100,'Annexe Etat'!$I$2:$I$164,'Annexe Etat'!$J$2:$J$164) -> Paysages, eau et biodiversité | E100: Etablissement public du Marais poitevin | F100: 1 | G100: =H100+I100 -> 9 | H100: 9 | I100: 0 | J100: =K100+L100 -> 8 | K100: 8 | L100: 0 | O100: X
A101: =_xlfn.XLOOKUP(C101,'Annexe Etat'!$I$2:$I$164,'Annexe Etat'!$H$2:$H$164) -> EC | B101: =_xlfn.XLOOKUP(A101,'Annexe Etat'!$A$2:$A$164,'Annexe Etat'!$B$2:$B$164) -> Enseignement scolaire | C101: 214 | D101: =_xlfn.XLOOKUP(C101,'Annexe Etat'!$I$2:$I$164,'Annexe Etat'!$J$2:$J$164) -> Soutien de la politique de l'éducation nationale | E101: FEI – France éducation international | F101: 1 | G101: =H101+I101 -> 277 | H101: 251 | I101: 26 | J101: =K101+L101 -> 281 | K101: 251 | L101: 30 | O101: X
...

Sheet ODAC-ODAL R
B1: Nb | C1: Opérateur déjà traité | D1: Vente | E1: Suppression | F1: EPIC - musée | G1: EPIC - études | H1: Internalisation
B2: =B4+B726+B752 -> 24000 | C2: =SUMIFS($B6:$B777,C6:C777,"oui") -> 384 | D2: =SUMIFS($B6:$B777,D6:D777,"X") -> 410 | E2: =SUMIFS($B6:$B777,E6:E777,"X") -> 13708 | F2: =SUMIFS($B6:$B777,F6:F777,"X") -> 4 | G2: =SUMIFS($B6:$B777,G6:G777,"X") -> 9172 | H2: =SUMIFS($B6:$B777,H6:H777,"X") -> 317
A4: ODAC 2023 Insee 2025 | B4: =SUM(B6:B724) -> 700 | C4: =SUMIFS($B7:$B724,C7:C724,"oui") -> 372 | D4: =SUMIFS($B7:$B724,D7:D724,"X") -> 63 | E4: =SUMIFS($B7:$B724,E7:E724,"X") -> 217 | F4: =SUMIFS($B7:$B724,F7:F724,"X") -> 4 | G4: =SUMIFS($B7:$B724,G7:G724,"X") -> 32 | H4: =SUMIFS($B7:$B724,H7:H724,"X") -> 12
A6: Fonction 1 : Services généraux des administrations publiques
A7: ADOM l'Agence de l'outre-mer pour la mobilité | B7: 1 | C7: oui
A8: AFA Groupement d'intérêt public Agence française de l'adoption | B8: 1 | H8: X
A9: ANTS Agence nationale des titres sécurisés | B9: 1 | C9: oui
A10: BPI_FSIPME FSI PME Portefeuille | B10: 1 | D10: X
A11: BPI_IC Bpifrance international capital | B11: 1 | D11: X
A12: BPI_PARTICIP Bpifrance Participations | B12: 1 | D12: X
A13: BRGM BRGM (Bureau de recherches géologiques et minières) | B13: 1 | C13: oui
A14: CDAD GIP Conseil départemental de laccès au droit de la Lozère | B14: 1 | E14: X
A15: CDAD GIP Conseil départemental de l'accès au droit de la Réunion | B15: 1 | E15: X
A16: CDAD GIP Conseil départemental de l'accès au droit de l'Hérault | B16: 1 | E16: X
A17: CDAD GIP Conseil départemental de l'accès au droit de Lot-et-Garonne | B17: 1 | E17: X
A18: CDAD GIP Conseil départemental de l'accès au droit de Maine-et-Loire | B18: 1 | E18: X
A19: CDAD GIP Conseil départemental de laccès au droit de Paris | B19: 1 | E19: X
A20: CDAD GIP Conseil départemental de l'accès au droit de Vaucluse | B20: 1 | E20: X
A21: CDAD GIP Conseil départemental de l'accès au droit des Alpes de Haute-Provence | B21: 1 | E21: X
A22: CDAD GIP Conseil départemental de l'accès au droit des Alpes Maritimes | B22: 1 | E22: X
A23: CDAD GIP Conseil Départemental de l'accès au droit des Côtes d'Armor | B23: 1 | E23: X
A24: CDAD GIP Conseil départemental de l'accès au droit du Bas-Rhin | B24: 1 | E24: X
A25: CDAD GIP Conseil départemental de l'accès au droit du Pas-de-Calais | B25: 1 | E25: X
... A99: CDAD Groupement d'intérêt public Conseil départemental de l'accès au droit du Var | B99: 1 | E99: X
A100: CDP Caisse de la dette publique | B100: 1 | H100: X
A101: CINES Centre informatique national de l'enseignement supérieur | B101: 1 | C101: oui
A102: CIVIQUE Groupement d'intérêt public Agence du service civique | B102: 1 | C102: oui
A103: CNG Centre national de gestion des praticiens hospitaliers et des personnels de direction de la fonction publique hospitalière | B103: 1 | E103: X
A104: CNRS Centre national de la recherche scientifique | B104: 1 | C104: oui
A105: COFRANCE Collège de France | B105: 1 | C105: oui
A106: CSA Conseil supérieur de l'audiovisuel | B106: 1 | E106: X
A107: CYCERON centre d'imagerie cérébrale et de recherches en neuroscience | B107: 1 | G107: X
A108: FGAO fonds de garantie des assurances obligatoires de dommage | B108: 1 | H108: X
A109: FGTI fonds de garantie des victimes des actes de terrorisme et d'autres infractions | B109: 1 | H109: X
A110: FSD Fonds de solidarité pour le développement | B110: 1 | E110: X
A111: HONNEUR Grande chancellerie de la Légion dhonneur | B111: 1 | C111: oui
A112: IFRTPE Groupement d'intérêt public Institut polaire français Paul-Emile Victor | B112: 1 | C112: oui
A113: IGNF Institut national de linformation géographique et forestière | B113: 1 | C113: oui
A114: IHESBY institut des hautes études scientifiques de Bures-sur-Yvette | B114: 1 | G114: X
A115: INED Institut national détudes démographiques | B115: 1 | C115: oui
A116: INRAP Institut national de recherches archéologiques préventives | B116: 1 | C116: oui
A117: INRIA Institut national de recherche en informatique et en automatique | B117: 1 | C117: oui
A118: IRD Institut de recherche pour le développement | B118: 1 | C118: oui
A119: LIBERATION Conseil national des communes Compagnon de la Libération | B119: 1 | C119: oui
A120: MRDJ mission de recherche droit et justice | B120: 1 | C120: oui
A121: MSH fondation maison des sciences de l'homme | B121: 1 | C121: oui
A122: OBPA Observatoire de Paris | B122: 1 | C122: oui
A123: OCA Observatoire de la Côte-d'Azur | B123: 1 | C123: oui
A124: OFFPRA Office français de protection des réfugiés et apatrides | B124: 1 | C124: oui
A125: OFII Office français de l’immigration et de l’intégration | B125: 1 | C125: oui
A126: SPPE Société de prise de participations de l'Etat | B126: 1 | D126: X
A128: Fonction 2 : Défense
A129: ECPAD Etablissement de communication et de production audiovisuelle de la défense | B129: 1 | C129: oui
A130: ENSOSP Ecole nationale supérieure des officiers de Sapeurs-Pompiers | B130: 1 | G130: X
A131: IHEDN Institut des hautes études de défense nationale | B131: 1 | C131: oui
A132: ISL institut franco allemand de recherches de Saint-Louis | B132: 1 | G132: X
A133: SHOM Etablissement public administratif Service hydrographique et océanographique de la marine | B133: 1 | C133: oui
A135: Fonction 3 : Ordre et sécurité publics
A136: ACMOSS Agence des communications mobiles opérationnelles de sécurité et de secours | B136: 1 | C136: oui
A137: AGRASC Agence de gestion et de recouvrement des avoirs saisis et confisqués | B137: 1 | C137: oui
A138: ANTAI Agence nationale de traitement automatisé des infractions | B138: 1 | C138: oui
A139: APIJ Agence publique pour limmobilier de la justice | B139: 1 | C139: oui
A140: CNAPS Conseil national des activités privées de sécurité | B140: 1 | C140: oui
A142: Fonction 4 : Affaires économiques
A143: ACTA association de coordination des techniques agricoles | B143: 1 | C143: oui
A144: ACTIA association de coordination techniques pour l'industrie agro-alimentaire | B144: 1 | C144: oui
A145: ADEME Agence de l'environnement et de la maîtrise de l'énergie | B145: 1 | C145: oui
A146: AFDPAB Groupement d'intérêt public Agence française pour le développement et la promotion de l'agriculture biologique | B146: 1 | C146: oui
A147: AFITF Agence de financement des infrastructures de transport de France | B147: 1 | C147: oui
A148: AMF Autorité des marchés financiers | B148: 1 | C148: oui
A149: ANACT Agence nationale pour lamélioration des conditions de travail | B149: 1 | C149: oui
A150: ANF Agence nationale des fréquences | B150: 1 | C150: oui
A151: ANR Agence nationale de la recherche | B151: 1 | C151: oui
A152: ARAF Autorité de régulation des transports | B152: 1 | C152: oui
A153: ARPE Autorité des Relations sociales des Plateformes d’Emploi | B153: 1 | E153: X
A154: ASIP Groupement dintérêt public Agence du numérique en santé (ANS) | B154: 1 | E154: X
A155: ASP Agence de services et de paiement | B155: 1 | C155: oui
A156: BPI_AE Bpifrance Assurance Export | B156: 1 | D156: X
A157: BPI_EPIC EPIC BPIFRANCE | B157: 1 | D157: X
A158: BPI_INVEST Bpifrance Investissement | B158: 1 | D158: X
A159: BUSINESS_FRANCE Business France | B159: 1 | C159: oui
A160: CDGX Gestionnaire d'infrastructures CDG-Express | B160: 1 | D160: X
A161: CDR consortium de réalisation | B161: 1 | D161: X
A162: CEA commissariat à l'énergie atomique | B162: 1 | C162: oui
A163: CEPREMAP centre pour la recherche économique et ses applications | B163: 1 | C163: oui
A164: CIRAD centre de coopération internationale en recherche agronomique | B164: 1 | C164: oui
A165: CNA Caisse nationale des autoroutes | B165: 1 | D165: X
A166: CNES Centre national détudes spatiales | B166: 1 | C166: oui
A167: CPSSP Comité professionnel des stocks stratégiques pétroliers | B167: 1 | H167: X
A168: EPSF Etablissement public de sécurité ferroviaire | B168: 1 | C168: oui
A169: FCOMPET France Compétences | B169: 1 | C169: oui
A170: FGDR Fonds de garantie des dépôts et de résolution | B170: 1 | H170: X
A171: FRANCE_AGRIMER Etablissement national des produits de l'agriculture et de la mer | B171: 1 | C171: oui
A172: H3C Haut-Conseil du commissariat aux comptes | B172: 1 | H172: X
A173: HCERES Haut Conseil de l'évaluation de la recherche et de l'enseignement supérieur | B173: 1 | H173: X
A174: IFCE Institut français du cheval et de l'équitation | B174: 1 | C174: oui
A175: IFPEN institut français du pétrole | B175: 1 | C175: oui
A176: IFREMER Institut français de recherche pour l'exploitation de la mer | B176: 1 | C176: oui
A177: INAO Institut national de l'origine et de la qualité | B177: 1 | C177: oui
A178: INFFO centre pour le développement de l'information sur la formation permanente | B178: 1 | C178: oui
...

Sheet Synthèse ETP
A1: Effectifs physiques de la fonction publique par statut au 31 décembre
A2: en milliers
C3: 2023
A4: Total | B4: Fonctionnaires(4) | C4: 3753.124
B5: Contractuels | C5: 1358.476
B6: Militaires | C6: 313.363
B7: Autres catégories et statuts(3) | C7: 378.899
B8: Total | C8: 5803.862
A9: FPE | B9: Fonctionnaires | C9: 1504.471
B10: Contractuels | C10: 582.699
B11: Militaires(2) | C11: 313.363
B12: Autres catégories et statuts(3) | C12: 169.704
B13: Total | C13: 2570.237
A14: FPT | B14: Fonctionnaires(4) | C14: 1422.029
B15: Contractuels | C15: 510.159
B16: Autres catégories et statuts(3) | C16: 62.002
B17: Total | C17: 1994.19
A18: FPH(6) | B18: Fonctionnaires | C18: 826.624
B19: Contractuels | C19: 265.618
B20: Autres catégories et statuts(3) | C20: 147.193
B21: Total | C21: 1239.435
A22: (1) Depuis 2005, les élèves de l'École polytechnique apparaissent dans le champ des EPA de la fonction publique de l'État.
A23: (2) Les militaires volontaires sont comptabilisés dans les effectifs de l'État à partir de 2004.
A24: (3) La catégorie "Autres catégories et statuts" recouvre principalement les enseignants et documentalistes des établissements privés sous contrat et les ouvriers d'État dans la FPE, les assistants maternels et familiaux dans la FPT, les médecins dans la FPH et les apprentis dans les trois versants.
A25: (4) Pour respecter le secret statistique, dans la FPT, les militaires (sapeurs-pompiers de Marseille) sont regroupés avec les fonctionnaires.

Sheet FPT
A1: Effectifs physiques de la fonction publique territoriale par statut des agents et type de collectivité au 31 décembre | F1: Effectifs physiques de la fonction publique territoriale par filière au 31 décembre
A2: en milliers | B2: 2023 | F2: en milliers | H2: 2023
A3: Total FPT (collectivités locales + EPA locaux) | B3: 1994.19 | F3: Total FPT | G3: Ensemble | H3: 1994.19
A4: Dont secteur communal(4) | B4: 1537.399 | G4: Administrative | H4: 447.053
A5: Total collectivités territoriales (communes + départements + régions) | B5: 1414.175 | G5: Animation | H5: 153.926
A6: Communes(1) | B6: 1028.952 | G6: Culturelle | H6: 78.478
A7: Départements | B7: 286.368 | G7: Incendie-secours | H7: 43.946
A8: Régions | B8: 98.855 | G8: Médico-sociale | H8: 87.319
A9: Total EPA locaux | B9: 580.015 | G9: Médico-technique | H9: 2.352
A10: Établissements communaux(1) | B10: 105.384 | G10: Sécurité | H10: 27.434
A11: Établissements intercommunaux(1) | B11: 391.844 | G11: Sociale | H11: 172.562
A12: Établissement départementaux | B12: 71.568 | G12: Sportive | H12: 17.762
A13: Autres EPA locaux | B13: 11.219 | G13: Technique | H13: 870.361
A14: (1) Les évolutions concernant les effectifs des communes et des établissements communaux et intercommunaux doivent être interprétées avec précaution compte tenu des possibles modifications (regroupements notamment), en relation avec la mise en place de structures intercommunales. | G14: Hors filière et indéterminée | H14: 92.997
A15: (2) Pour respecter le secret statistique, dans la FPT les militaires (sapeurs pompiers de Marseille) sont regroupés avec les fonctionnaires et les militaires volontaires avec les contractuels. | F15: Collectivités territoriales | G15: Ensemble | H15: 1414.175
A16: (3) Dans la FPT, la catégorie "autres catégories et statuts" recouvre les collaborateurs de cabinet, les assistants maternels et les apprentis. | G16: Administrative | H16: 314.893
A17: (4) Le secteur communal comprend les communes, les établissements communaux et intercommunaux et d'autres EPA locaux tels que les caisses du crédit municipal, les régies, etc. | G17: Animation | H17: 119.71
A18: (5) En 2018, une Collectivité Territoriale Unique a été mise en place à partir de la fusion des deux départements et de la Collectivité Territoriale de Corse. Les évolutions des effectifs des départements et régions s'expliquent en partie par cette mise en place. Les effectifs de cette nouvelle collectivité sont désormais décomptés avec les régions. A périmètre constant, l'évolution des départements serait de 0,0 % et celle des régions de +3,2 %. | G18: Culturelle | H18: 52.308
G19: Incendie-secours | H19: 0.189
G20: Médico-sociale | H20: 49.768
G21: Médico-technique | H21: 1.743
G22: Sécurité | H22: 26.49
G23: Sociale | H23: 105.408
G24: Sportive | H24: 11.079
G25: Technique | H25: 659.429
G26: Hors filière et indéterminée | H26: 73.158
F27: EPA | G27: Ensemble | H27: 580.015
G28: Administrative | H28: 132.16
G29: Animation | H29: 34.216
G30: Culturelle | H30: 26.17
G31: Incendie-secours | H31: 43.757
G32: Médico-sociale | H32: 37.551
G33: Médico-technique | H33: 0.609
G34: Sécurité | H34: 0.944
G35: Sociale | H35: 67.154
G36: Sportive | H36: 6.683
G37: Technique | H37: 210.932
G38: Hors filière et indéterminée | H38: 19.839

Sheet FPH
A1: Effectifs physiques des personnels non médicaux(1) de la fonction publique hospitalière par filière au 31 décembre
A2: en milliers | C2: 2023 | E2: dont | G2: 2023 | I2: dont | K2: 2023 | M2: dont | O2: 2023
A3: Total FPH | B3: Administrative | C3: 120.931 | E3: Hôpitaux | F3: Administrative | G3: 113.401 | I3: Établissements d'hébergement pour personnes âgées (EHPA) | J3: Administrative | K3: 4.766 | M3: Autres établissements médico-sociaux | N3: Administrative | O3: 2.764
B4: Médico-technique | C4: 47.758 | F4: Médico-technique | G4: 47.554 | J4: Médico-technique | K4: 0.182 | N4: Médico-technique | O4: 0.022
B5: Socio-éducative | C5: 30.542 | F5: Socio-éducative | G5: 18.616 | J5: Socio-éducative | K5: 1.619 | N5: Socio-éducative | O5: 10.307
B6: Soignante | C6: 763.474 | F6: Soignante | G6: 674.714 | J6: Soignante | K6: 73.473 | N6: Soignante | O6: 15.287
B7: Technique-ouvrière | C7: 122.969 | F7: Technique-ouvrière | G7: 106.407 | J7: Technique-ouvrière | K7: 10.295 | N7: Technique-ouvrière | O7: 6.267
B8: Hors filières et indéterminée | C8: 11.336 | F8: Hors filières et indéterminée | G8: 8.19 | J8: Hors filières et indéterminée | K8: 0.39 | N8: Hors filières et indéterminée | O8: 2.756
B9: Ensemble | C9: 1097.01 | F9: Ensemble | G9: 968.882 | J9: Ensemble | K9: 90.725 | N9: Ensemble | O9: 37.403
A10: (1) Les personnels non médicaux recouvrent les agents de la FPH hors médecins et internes.

Sheet FPE
A1: Effectifs des départements ministériels par statut et par ministère de tutelle au 31 décembre | H1: Effectifs des ministères par statut au 31 décembre
A2: en milliers | H2: en milliers
B3: 2023 | I3: 2023
B4: Fonctionnaires | C4: Contractuels | D4: Militaires et militaires volontaires | E4: Autres catégories et statuts(1) | F4: Total | I4: Fonctionnaires | J4: Contractuels | K4: Militaires et militaires volontaires | L4: Autres catégories et statuts(1) | M4: Total
A5: Agriculture et alimentation | B5: 22.029 | C5: 18.323 | D5: 0.023 | E5: 5.106 | F5: 45.481 | H5: Agriculture et alimentation | I5: 18.967 | J5: 5.519 | K5: 0.023 | L5: 4.879 | M5: 29.388
A6: Armées | B6: 39.321 | C6: 22.479 | D6: 212.292 | E6: 16.039 | F6: 290.131 | H6: Armées | I6: 37.622 | J6: 16.353 | K6: 211.61 | L6: 15.817 | M6: 281.402
A7: Culture | B7: 12.201 | C7: 12.482 | D7: 0.006 | E7: 0.388 | F7: 25.077 | H7: Culture | I7: 7.019 | J7: 1.723 | K7: 0.006 | L7: 0.12 | M7: 8.868
A8: Ministères économiques et financiers | B8: 123.242 | C8: 16.969 | D8: 0.067 | E8: 1.822 | F8: 142.1 | H8: Ministères économiques et financiers | I8: 118.401 | J8: 8.682 | K8: 0.065 | L8: 1.424 | M8: 128.572
A9: Éducation nationale, Jeunesse, Sports, Enseignement supérieur, Recherche et Innovation | B9: 967.412 | C9: 385.997 | D9: 0.089 | E9: 136.523 | F9: 1490.021 | H9: Éducation nationale, Jeunesse, Sports, Enseignement supérieur, Recherche et Innovation | I9: 801.726 | J9: 168.992 | K9: 0.07 | L9: 134.293 | M9: 1105.081
A10: Europe et Affaires étrangères(2) | B10: 3.004 | C10: 0.854 | D10: 0.004 | E10: 0.106 | F10: 3.968 | H10: Europe et Affaires étrangères(2) | I10: 2.834 | J10: 0.802 | K10: 0.004 | L10: 0.104 | M10: 3.744
A11: Intérieur et Outre-mer | B11: 181.356 | C11: 21.338 | D11: 100.413 | E11: 2.886 | F11: 305.993 | H11: Intérieur et Outre-mer | I11: 179.869 | J11: 19.211 | K11: 100.356 | L11: 2.838 | M11: 302.274
A12: Justice | B12: 81.91 | C12: 12.528 | D12: 0.091 | E12: 0.447 | F12: 94.976 | H12: Justice | I12: 79.049 | J12: 12.057 | K12: 0.086 | L12: 0.415 | M12: 91.607
A13: Services du Premier ministre | B13: 6.8 | C13: 4.5 | D13: 0.05 | E13: 0.215 | F13: 11.565 | H13: Services du Premier ministre | I13: 6.414 | J13: 4.322 | K13: 0.047 | L13: 0.204 | M13: 10.987
A14: Ministères sociaux | B14: 16.196 | C14: 75.322 | D14: 0.018 | E14: 2.849 | F14: 94.385 | H14: Ministères sociaux | I14: 10.105 | J14: 3.171 | K14: 0.015 | L14: 0.402 | M14: 13.693
A15: Solidarités et santé | B15: 9.536 | C15: 16.899 | D15: 0.008 | E15: 2.122 | F15: 28.565 | H15: Solidarités et santé | I15: 3.546 | J15: 1.896 | K15: 0.005 | L15: 0.235 | M15: 5.682
A16: Travail | B16: 6.66 | C16: 58.423 | D16: 0.01 | E16: 0.727 | F16: 65.82 | H16: Travail | I16: 6.559 | J16: 1.275 | K16: 0.01 | L16: 0.167 | M16: 8.011
... A19: Total hors enseignants(3) | B19: 739.245 | C19: 512.707 | D19: 313.344 | E19: 31.86 | F19: 1597.156 | H19: Total hors enseignants(3) | I19: 599.108 | J19: 188.289 | K19: 312.544 | L19: 24.72 | M19: 1124.661
A22: Effectifs par statut et par catégorie selon la nature de l'employeur au 31 décembre
A23: en milliers
B24: 2023
B25: Catégorie A | C25: Catégorie B | D25: Catégorie C | E25: Indéterminé | F25: Effectifs physiques
A26: Ministères | B26: 1164.361 | C26: 435.925 | D26: 391.483 | E26: 29.489 | F26: 2021.258
A27: EPA | B27: 245.725 | C27: 168.542 | D27: 105.405 | E27: 29.307 | F27: 548.979
A28: Ensemble FPE | B28: 1410.086 | C28: 604.467 | D28: 496.888 | E28: 58.796 | F28: 2570.237

Sheet Emplois Etat RAP 2024
E1: Emplois rémunérés par le programme | R1: Evolution des emplois à périmètre constant
A2: Nature de la | B2: Budget | C2: Code | D2: Libellé de la mission Libellé du programme | E2: Transferts de gestion (1) | F2: Réalisation (2) | G2: LFI + LFR (3) | H2: Transferts de gestion (4) | I2: Réalisation (5) | J2: Ecart à LFI + LFR après transferts de gestion (5- (3+4) | K2: Mesures de périmètre en LFI (6) | L2: Mesures de transfert en LFI (7) | M2: Corrections techniques (8) | N2: Impact des schémas d'emploi (5-4)-(2-1)-(6+7+8) | O2: dont extension en année pleine des schémas d'emploi | P2: dont impact des schémas d'emploi | R2: Sorties | S2: dont départs en retraite | T2: Mois moyen des sorties | U2: Entrées | V2: dont primo recrutements | W2: Mois moyen des entrées | X2: Shéma d'emplois | Y2: Shéma d'emplois
A3: ligne | D3: Libellé de la catégorie d'emploi | E3: 2023 | F3: 2023 | G3: 2024 | H3: 2024 | I3: 2024 | J3: 2024 | K3: 2024 | L3: 2024 | M3: 2024 | O3: 2023 pour 2024 | P3: 2024 sur 2024 | X3: Réalisation | Y3: Prévision PAP
A4: Budget | B4: BA | D4: Budget annexe | F4: 10693.72 | G4: 10923.42 | I4: 10707.33 | J4: -216.09 | M4: 0.89 | N4: 12.72 | O4: 33.71 | P4: -20 | R4: 528.5 | S4: 313.8 | U4: 536.7 | V4: 363.6 | X4: 8.2 | Y4: 13
A5: Mission | B5: BA | C5: XC | D5: Contrôle et exploitation aériens | F5: 10215 | G5: 10439 | I5: 10251 | J5: -188 | M5: 1.83 | N5: 34.17 | O5: 43.6 | P5: -9 | R5: 407 | S5: 270 | U5: 435 | V5: 281 | X5: 28 | Y5: 28
A6: Programme | B6: BA | C6: 613 | D6: Soutien aux prestations de l'aviation civile | F6: 10215 | G6: 10439 | I6: 10251 | J6: -188 | M6: 1.83 | N6: 34.17 | O6: 43.6 | P6: -9 | R6: 407 | S6: 270 | U6: 435 | V6: 281 | X6: 28 | Y6: 28
A7: Catégorie d'emploi | B7: BA | C7: 613-1200 | D7: Administratifs et cadres | F7: 2743 | G7: 2761 | I7: 2737 | J7: -24 | M7: -22.85 | N7: 16.85 | O7: 18.32 | P7: -1 | R7: 163 | S7: 83 | T7: 6.7 | U7: 174 | V7: 55 | W7: 7.2 | X7: 11 | Y7: 3
A8: Catégorie d'emploi | B8: BA | C8: 613-1201 | D8: Ingénieurs du contrôle de la navigation aérienne | F8: 3936 | G8: 3991 | I8: 3996 | J8: 5 | M8: 21.19 | N8: 38.81 | O8: 5.5 | P8: 33 | R8: 73 | S8: 48 | T8: 7.7 | U8: 138 | V8: 123 | W8: 7.3 | X8: 65 | Y8: 61
A9: Catégorie d'emploi | B9: BA | C9: 613-1202 | D9: Ingénieurs électroniciens des systèmes de sécurité aérienne et techniciens supérieurs des études et de l'exploitation de l'aviation civile | F9: 2990 | G9: 3090 | I9: 2987 | J9: -103 | M9: -1.63 | N9: -1.37 | O9: 27.43 | P9: -29 | R9: 135 | S9: 115 | T9: 6.2 | U9: 108 | V9: 103 | W9: 7.7 | X9: -27 | Y9: -13
A10: Catégorie d'emploi | B10: BA | C10: 613-1203 | D10: Ouvriers et personnels navigants | F10: 546 | G10: 597 | I10: 531 | J10: -66 | M10: 5.12 | N10: -20.12 | O10: -7.65 | P10: -12 | R10: 36 | S10: 24 | T10: 6.3 | U10: 15 | W10: 6.9 | X10: -21 | Y10: -23
A11: Mission | B11: BA | C11: XJ | D11: Publications officielles et information administrative | F11: 478.72 | G11: 484.42 | I11: 456.33 | J11: -28.09 | M11: -0.94 | N11: -21.45 | O11: -9.89 | P11: -11 | R11: 121.5 | S11: 43.8 | U11: 101.7 | V11: 82.6 | X11: -19.8 | Y11: -15
A12: Programme | B12: BA | C12: 624 | D12: Pilotage et ressources humaines | F12: 478.72 | G12: 484.42 | I12: 456.33 | J12: -28.09 | M12: -0.94 | N12: -21.45 | O12: -9.89 | P12: -11 | R12: 121.5 | S12: 43.8 | U12: 101.7 | V12: 82.6 | X12: -19.8 | Y12: -15
A13: Catégorie d'emploi | B13: BA | C13: 624-1205 | D13: Catégorie A+ | F13: 10.07 | G13: 8 | I13: 9.75 | J13: 1.75 | N13: -0.32 | O13: 0.01 | R13: 5 | T13: 6.61 | U13: 4 | V13: 3 | W13: 6 | X13: -1
A14: Catégorie d'emploi | B14: BA | C14: 624-1206 | D14: Catégorie A | F14: 83.97 | G14: 88.92 | I14: 80.9 | J14: -8.02 | M14: -0.39 | N14: -2.68 | O14: -1.16 | P14: -2 | R14: 14.3 | S14: 4 | T14: 7.34 | U14: 8.7 | V14: 4.8 | W14: 5.8 | X14: -5.6 | Y14: 3
A15: Catégorie d'emploi | B15: BA | C15: 624-1207 | D15: Catégorie B | F15: 19.16 | G15: 16.25 | I15: 18.95 | J15: 2.7 | N15: -0.21 | O15: 0.09 | R15: 3.8 | S15: 0.8 | T15: 5.13 | U15: 5 | V15: 4 | W15: 7.73 | X15: 1.2 | Y15: -1
A16: Catégorie d'emploi | B16: BA | C16: 624-1208 | D16: Catégorie C | F16: 38.18 | G16: 44.92 | I16: 32.7 | J16: -12.22 | M16: -0.19 | N16: -5.29 | O16: -0.26 | P16: -5 | R16: 8.2 | S16: 4 | T16: 5.45 | U16: 0.2 | W16: 5.03 | X16: -8 | Y16: -3
A17: Catégorie d'emploi | B17: BA | C17: 624-1209 | D17: Contractuels | F17: 327.34 | G17: 326.33 | I17: 314.03 | J17: -12.3 | M17: -0.36 | N17: -12.95 | O17: -8.57 | P17: -4 | R17: 90.2 | S17: 35 | T17: 7.4 | U17: 83.8 | V17: 70.8 | W17: 7.6 | X17: -6.4 | Y17: -14
A18: Budget | B18: BG | D18: Budget général | E18: -1.16 | F18: 1913776.2 | G18: 1974383.5 | H18: -1.0658141e-14 | I18: 1954922.4 | J18: -19461.18 | K18: 20682 | L18: -125 | M18: 8569.92 | N18: 12018.03 | O18: 11107.7 | P18: 914 | R18: 171922.16 | S18: 40130.14 | U18: 178641.46 | V18: 82330.73 | X18: 6719.3 | Y18: 6681.87
A19: Mission | B19: BG | C19: AA | D19: Action extérieure de l'État | F19: 12113.83 | G19: 12289.37 | H19: 1.42 | I19: 12211.84 | J19: -78.95 | M19: 8.31 | N19: 88.28 | O19: 59.41 | P19: 30 | R19: 3471.8 | S19: 170 | U19: 3621.8 | X19: 150 | Y19: 145.87
A20: Programme | B20: BG | C20: 105 | D20: Action de la France en Europe et dans le monde | F20: 8185.54 | G20: 8214 | H20: -0.58 | I20: 8252.28 | J20: 38.86 | M20: 8.35 | N20: 58.97 | O20: 17.12 | P20: 42 | R20: 2182.33 | S20: 117 | U20: 2295.33 | X20: 113 | Y20: 109.87
A21: Catégorie d'emploi | B21: BG | C21: 105-1101 | D21: Titulaires et CDI en administration centrale | F21: 2079.95 | G21: 2306 | H21: -0.58 | I21: 2099.77 | J21: -205.65 | M21: 8 | N21: 12.4 | O21: 60.37 | P21: -48 | R21: 578.9 | S21: 117 | T21: 7.42 | U21: 574.6 | W21: 8.38 | X21: -4.3 | Y21: 35.87
A22: Catégorie d'emploi | B22: BG | C22: 105-1102 | D22: Titulaires et CDI dans le réseau | F22: 1549.81 | G22: 1576.8 | I22: 1539.13 | J22: -37.67 | M22: 0.35 | N22: -11.03 | O22: -44.81 | P22: 34 | R22: 556.7 | T22: 8.55 | U22: 570.83 | W22: 7.95 | X22: 14.13 | Y22: 54
A23: Catégorie d'emploi | B23: BG | C23: 105-1103 | D23: CDD et volontaires internationaux | F23: 947.76 | G23: 594.2 | I23: 1043.05 | J23: 448.85 | N23: 95.29 | O23: 54.6 | P23: 41 | R23: 724.4 | T23: 7.47 | U23: 827.67 | W23: 7.57 | X23: 103.27 | Y23: 20
A24: Catégorie d'emploi | B24: BG | C24: 105-1104 | D24: Militaires | F24: 641.88 | G24: 640 | I24: 621.49 | J24: -18.51 | N24: -20.39 | O24: -18.55 | P24: -2 | R24: 175.44 | T24: 8.23 | U24: 147.34 | W24: 7.47 | X24: -28.1
A25: Catégorie d'emploi | B25: BG | C25: 105-1105 | D25: Agents de droit local | F25: 2966.14 | G25: 3097 | I25: 2948.84 | J25: -148.16 | N25: -17.3 | O25: -34.49 | P25: 17 | R25: 146.89 | T25: 7.63 | U25: 174.89 | W25: 7.31 | X25: 28
A26: Programme | B26: BG | C26: 185 | D26: Diplomatie culturelle et d'influence | F26: 763.88 | G26: 800.37 | I26: 789.22 | J26: -11.15 | N26: 25.34 | O26: 10.56 | P26: 15 | R26: 263.41 | S26: 4 | U26: 280.41 | X26: 17 | Y26: 16
A27: Catégorie d'emploi | B27: BG | C27: 185-1101 | D27: Titulaires et CDI en administration centrale | F27: 58.06 | G27: 79 | I27: 57.52 | J27: -21.48 | N27: -0.54 | O27: -2.41 | P27: 2 | R27: 19.17 | S27: 4 | T27: 7.73 | U27: 23.17 | W27: 7.67 | X27: 4
A28: Catégorie d'emploi | B28: BG | C28: 185-1102 | D28: Titulaires et CDI dans le réseau | F28: 69.19 | G28: 71.92 | I28: 72.22 | J28: 0.3 | N28: 3.03 | O28: -0.19 | P28: 3 | R28: 23.63 | T28: 8.1 | U28: 31.65 | W28: 8.12 | X28: 8.02 | Y28: 2
A29: Catégorie d'emploi | B29: BG | C29: 185-1103 | D29: CDD et volontaires internationaux | F29: 547.74 | G29: 552.45 | I29: 566.61 | J29: 14.16 | N29: 18.87 | O29: 14.36 | P29: 5 | R29: 203.61 | T29: 7.16 | U29: 211.42 | W29: 7.12 | X29: 7.81 | Y29: 14
A30: Catégorie d'emploi | B30: BG | C30: 185-1105 | D30: Agents de droit local | F30: 88.89 | G30: 97 | I30: 92.87 | J30: -4.13 | N30: 3.98 | O30: -1.2 | P30: 5 | R30: 17 | T30: 9.99 | U30: 14.17 | W30: 5 | X30: -2.83
A31: Programme | B31: BG | C31: 151 | D31: Français à l'étranger et affaires consulaires | F31: 3164.41 | G31: 3275 | H31: 2 | I31: 3170.34 | J31: -106.66 | M31: -0.04 | N31: 3.97 | O31: 31.73 | P31: -27 | R31: 1026.06 | S31: 49 | U31: 1046.06 | X31: 20 | Y31: 20
A32: Catégorie d'emploi | B32: BG | C32: 151-1101 | D32: Titulaires et CDI en administration centrale | F32: 468.06 | G32: 527.54 | H32: 2 | I32: 466.18 | J32: -63.36 | M32: -0.04 | N32: -3.84 | O32: -15.9 | P32: 12 | R32: 128.97 | S32: 49 | T32: 8.52 | U32: 124.58 | W32: 7.2 | X32: -4.39 | Y32: 8
A33: Catégorie d'emploi | B33: BG | C33: 151-1102 | D33: Titulaires et CDI dans le réseau | F33: 1028.68 | G33: 1049 | I33: 1046.98 | J33: -2.02 | N33: 18.3 | O33: 32.3 | P33: -14 | R33: 226.2 | T33: 7.37 | U33: 251.26 | W33: 8.6 | X33: 25.06 | Y33: 11
A34: Catégorie d'emploi | B34: BG | C34: 151-1103 | D34: CDD et volontaires internationaux | F34: 80.46 | G34: 101.46 | I34: 97.49 | J34: -3.97 | N34: 17.03 | O34: 12.39 | P34: 5 | R34: 169.5 | T34: 7.7 | U34: 177.34 | W34: 7.62 | X34: 7.84 | Y34: 1
A35: Catégorie d'emploi | B35: BG | C35: 151-1105 | D35: Agents de droit local | F35: 1587.21 | G35: 1597 | I35: 1559.69 | J35: -37.31 | N35: -27.52 | O35: 2.94 | P35: -30 | R35: 501.39 | T35: 7.69 | U35: 492.88 | W35: 8.34 | X35: -8.51
A36: Mission | B36: BG | C36: AB | D36: Administration générale et territoriale de l'État | E36: 149 | F36: 40586.52 | G36: 40616.01 | H36: 148.67 | I36: 40405.64 | J36: -359.04 | L36: -141 | M36: 39.8 | N36: -79.35 | O36: 232.11 | P36: -312 | R36: 13459.6 | S36: 1209.3 | U36: 13736.3 | V36: 1840.2 | X36: 276.7 | Y36: 361
A37: Programme | B37: BG | C37: 354 | D37: Administration territoriale de l'État | E37: 146 | F37: 29422.65 | G37: 29448.08 | H37: 131.08 | I37: 29201.98 | J37: -377.18 | M37: 5.61 | N37: -211.36 | O37: 125.15 | P37: -337 | R37: 10729.7 | S37: 926.4 | U37: 10886.4 | V37: 587.2 | X37: 156.7 | Y37: 232
A38: Catégorie d'emploi | B38: BG | C38: 354-1160 | D38: Hauts fonctionnaires | F38: 1316.75 | G38: 1394 | I38: 1329.37 | J38: -64.63 | M38: 67.42 | N38: -54.8 | O38: -25.59 | P38: -29 | R38: 336 | S38: 28 | T38: 6.23 | U38: 359 | V38: 22 | W38: 7.64 | X38: 23 | Y38: 86
A39: Catégorie d'emploi | B39: BG | C39: 354-1174 | D39: Personnels administratifs cat A | E39: 119 | F39: 5592 | G39: 5440.43 | H39: 126.04 | I39: 5730.13 | J39: 163.66 | M39: -310.79 | N39: 441.88 | O39: 326.75 | P39: 115 | R39: 1164 | S39: 163.3 | T39: 6.1 | U39: 1515.8 | V39: 111 | W39: 6.79 | X39: 351.8 | Y39: 176
A40: Catégorie d'emploi | B40: BG | C40: 354-1175 | D40: Personnels administratifs cat B | E40: 22 | F40: 7945.9 | G40: 7728.12 | H40: 11.34 | I40: 8110.33 | J40: 370.87 | M40: -131.49 | N40: 306.58 | O40: 316.56 | P40: -10 | R40: 2267.6 | S40: 234.1 | T40: 6.25 | U40: 2501.9 | V40: 184.2 | W40: 6.93 | X40: 234.3 | Y40: 70
A41: Catégorie d'emploi | B41: BG | C41: 354-1176 | D41: Personnels administratifs cat C | E41: 4 | F41: 10703.2 | G41: 10291.53 | H41: -6.3 | I41: 10470.64 | J41: 185.41 | M41: 1009.18 | N41: -1231.44 | O41: -896.57 | P41: -335 | R41: 6162.4 | S41: 322.7 | T41: 6.46 | U41: 5687.1 | V41: 192 | W41: 6.62 | X41: -475.3 | Y41: -100
A42: Catégorie d'emploi | B42: BG | C42: 354-1162 | D42: Personnels techniques | E42: 1 | F42: 3864.8 | G42: 4594 | I42: 3561.51 | J42: -1032.49 | M42: -628.71 | N42: 326.42 | O42: 404 | P42: -78 | R42: 799.7 | S42: 178.3 | T42: 5.88 | U42: 822.6 | V42: 78 | W42: 7.21 | X42: 22.9
A43: Programme | B43: BG | C43: 232 | D43: Vie politique | F43: 52.71 | G43: 55 | I43: 54.17 | J43: -0.83 | M43: 1.46 | N43: -8.8817842e-16
A44: Catégorie d'emploi | B44: BG | C44: 232-1160 | D44: Hauts fonctionnaires | F44: 2 | G44: 2 | I44: 2 | T44: 0 | W44: 0
A45: Catégorie d'emploi | B45: BG | C45: 232-1174 | D45: Personnels administratifs cat A | F45: 32.83 | G45: 35 | I45: 34.08 | J45: -0.92 | M45: 1.25 | T45: 0 | W45: 0
A46: Catégorie d'emploi | B46: BG | C46: 232-1175 | D46: Personnels administratifs cat B | F46: 9 | G46: 10 | I46: 10.42 | J46: 0.42 | M46: 1.42 | T46: 0 | W46: 0
A47: Catégorie d'emploi | B47: BG | C47: 232-1176 | D47: Personnels administratifs cat C | F47: 8.88 | G47: 8 | I47: 7.67 | J47: -0.33 | M47: -1.21 | N47: -8.8817842e-16 | T47: 0 | W47: 0
A48: Programme | B48: BG | C48: 216 | D48: Conduite et pilotage des politiques de l'intérieur | E48: 3 | F48: 11111.16 | G48: 11112.93 | H48: 17.59 | I48: 11149.49 | J48: 18.97 | L48: -141 | M48: 32.73 | N48: 132.01 | O48: 106.96 | P48: 25 | R48: 2729.9 | S48: 282.9 | U48: 2849.9 | V48: 1253 | X48: 120 | Y48: 129
A49: Catégorie d'emploi | B49: BG | C49: 216-1160 | D49: Hauts fonctionnaires | E49: 1 | F49: 486.2 | G49: 506.43 | H49: 1 | I49: 515.15 | J49: 7.72 | L49: 1 | M49: 18.74 | N49: 9.21 | O49: 15.06 | P49: -6 | R49: 234 | S49: 27.4 | T49: 6.8 | U49: 220.2 | V49: 28 | W49: 6.73 | X49: -13.8 | Y49: 9
A50: Catégorie d'emploi | B50: BG | C50: 216-1174 | D50: Personnels administratifs cat A | E50: 2 | F50: 2060.32 | G50: 1824.48 | H50: -0.91 | I50: 2246.97 | J50: 423.4 | L50: -14 | M50: 45.38 | N50: 158.18 | O50: 87.35 | P50: 71 | R50: 667 | S50: 27.8 | T50: 6.33 | U50: 837.1 | V50: 488 | W50: 6.67 | X50: 170.1 | Y50: 81
A51: Catégorie d'emploi | B51: BG | C51: 216-1175 | D51: Personnels administratifs cat B | F51: 1418.68 | G51: 1372.91 | H51: 1.5 | I51: 1427.77 | J51: 53.36 | L51: -26 | M51: -60.38 | N51: 93.97 | O51: 76.62 | P51: 17 | R51: 432.6 | S51: 31.6 | T51: 6.43 | U51: 492 | V51: 218 | W51: 6.8 | X51: 59.4
A52: Catégorie d'emploi | B52: BG | C52: 216-1176 | D52: Personnels administratifs cat C | F52: 2097.2 | G52: 2011.57 | H52: 16 | I52: 1956.28 | J52: -71.29 | L52: -96 | M52: -74.35 | N52: 13.43 | O52: -16.7 | P52: 30 | R52: 800 | S52: 35.4 | T52: 6.63 | U52: 826.9 | V52: 329 | W52: 6.4 | X52: 26.9
A53: Catégorie d'emploi | B53: BG | C53: 216-1162 | D53: Personnels techniques | F53: 2126.3 | G53: 2301.13 | I53: 2145.54 | J53: -155.59 | L53: -6 | M53: 103.28 | N53: -78.04 | O53: -14.25 | P53: -64 | R53: 312.3 | S53: 58.4 | T53: 5.83 | U53: 240.4 | V53: 55 | W53: 6.87 | X53: -71.9 | Y53: 1
A54: Catégorie d'emploi | B54: BG | C54: 216-1163 | D54: Personnels des cultes | F54: 1185.51 | G54: 1186.45 | I54: 1151.94 | J54: -34.51 | M54: 0.11 | N54: -33.68 | O54: -14.67 | P54: -19 | R54: 87 | S54: 38 | T54: 7.43 | U54: 57 | V54: 46 | W54: 8.5 | X54: -30
A55: Catégorie d'emploi | B55: BG | C55: 216-1165 | D55: Ouvriers d'Etat | F55: 174.98 | G55: 249.02 | I55: 149.29 | J55: -99.73 | M55: -5.42 | N55: -20.27 | O55: -7.28 | P55: -13 | R55: 34.8 | S55: 19.5 | T55: 5.27 | U55: 12.3 | W55: 3.8 | X55: -22.5
A56: Catégorie d'emploi | B56: BG | C56: 216-1166 | D56: Hauts fonctionnaires, corps de conception et de direction et corps de commandement (police nationale) | F56: 20.55 | G56: 33.83 | I56: 19.78 | J56: -14.05 | M56: 2.65 | N56: -3.42 | O56: -0.17 | P56: -3 | R56: 8 | S56: 5 | T56: 8.13 | W56: 0 | X56: -8
A57: Catégorie d'emploi | B57: BG | C57: 216-1167 | D57: Corps d'encadrement et d'application (police nationale) | F57: 21.47 | G57: 32.83 | I57: 24.23 | J57: -8.6 | M57: 1.69 | N57: 1.07 | O57: 0.99 | R57: 2 | T57: 9.53 | U57: 2 | W57: 9.03
A58: Catégorie d'emploi | B58: BG | C58: 216-1177 | D58: Officiers de gendarmerie | F58: 15.25 | G58: 28 | I58: 21.88 | J58: -6.12 | M58: 7.39 | N58: -0.76 | O58: -0.51 | R58: 5 | S58: 1 | T58: 9.23 | U58: 4 | W58: 9.03 | X58: -1
A59: Catégorie d'emploi | B59: BG | C59: 216-1178 | D59: Officiers du corps technique et administratif de la gendarmerie nationale | F59: 36.29 | G59: 42 | I59: 25.97 | J59: -16.03 | M59: -7.35 | N59: -2.97 | O59: -2.88 | R59: 6 | T59: 9.17 | U59: 5 | W59: 8.63 | X59: -1
A60: Catégorie d'emploi | B60: BG | C60: 216-1179 | D60: Sous-officiers de gendarmerie | F60: 10.08 | G60: 28 | I60: 7.43 | J60: -20.57 | M60: -0.83 | N60: -1.82 | O60: -0.25 | P60: -2 | R60: 3 | S60: 2 | T60: 3.73 | U60: 1 | W60: 4.03 | X60: -2
A61: Catégorie d'emploi | B61: BG | C61: 216-1180 | D61: Sous-officiers du corps de soutien technique et administratif de la gendarmerie nationale | F61: 94.77 | G61: 96 | I61: 84.62 | J61: -11.38 | M61: -5.72 | N61: -4.43 | O61: -4.02 | R61: 9 | S61: 2 | T61: 7.93 | U61: 10 | W61: 8.93 | X61: 1
A62: Catégorie d'emploi | B62: BG | C62: 216-1172 | D62: Volontaires (gendarmes) | G62: 5 | J62: -5 | T62: 0 | W62: 0
A63: Catégorie d'emploi | B63: BG | C63: 216-1173 | D63: Inspecteurs et délégués du permis du conduire | F63: 1363.56 | G63: 1395.28 | I63: 1372.64 | J63: -22.64 | M63: 7.54 | N63: 1.54 | O63: -12.33 | P63: 14 | R63: 129.2 | S63: 34.8 | T63: 4.43 | U63: 142 | V63: 89 | W63: 4.03 | X63: 12.8 | Y63: 38
A64: Mission | B64: BG | C64: AC | D64: Agriculture, alimentation, forêt et affaires rurales | E64: -7.3 | F64: 11394.22 | G64: 11813 | H64: -17.89 | I64: 11609 | J64: -186.11 | M64: -196.07 | N64: 421.44 | O64: 62.84 | P64: 359 | R64: 1863 | S64: 302 | U64: 2015 | V64: 37 | X64: 152 | Y64: 152
A65: Programme | B65: BG | C65: 206 | D65: Sécurité et qualité sanitaires de l'alimentation | F65: 5022 | G65: 5158 | I65: 5141 | J65: -17 | M65: -97.08 | N65: 216.08 | O65: 1 | P65: 215 | R65: 893 | S65: 134 | U65: 946 | V65: 37 | X65: 53 | Y65: 53
A66: Catégorie d'emploi | B66: BG | C66: 206-1013 | D66: Enseignants | F66: 2 | I66: 2 | J66: 2 | T66: 0 | W66: 0
A67: Catégorie d'emploi | B67: BG | C67: 206-1014 | D67: A - Administratifs et Techniques | F67: 1140.4 | G67: 1311 | I67: 1158 | J67: -153 | M67: -23.15 | N67: 40.75 | O67: 6.89 | P67: 34 | R67: 173 | S67: 24 | T67: 6.96 | U67: 225 | V67: 5 | W67: 6.55 | X67: 52 | Y67: 53
A68: Catégorie d'emploi | B68: BG | C68: 206-1015 | D68: B et C - Administratifs et Techniques | F68: 3879.6 | G68: 3847 | I68: 3981 | J68: 134 | M68: -73.93 | N68: 175.33 | O68: -5.89 | P68: 181 | R68: 720 | S68: 110 | T68: 8.56 | U68: 721 | V68: 32 | W68: 5.55 | X68: 1
A69: Programme | B69: BG | C69: 215 | D69: Conduite et pilotage des politiques de l'agriculture | E69: -7.3 | F69: 6372.22 | G69: 6655 | H69: -17.89 | I69: 6468 | J69: -169.11 | M69: -98.99 | N69: 205.36 | O69: 61.84 | P69: 144 | R69: 970 | S69: 168 | U69: 1069 | X69: 99 | Y69: 99
A70: Catégorie d'emploi | B70: BG | C70: 215-1013 | D70: Enseignants | F70: 51.49 | I70: 54.85 | J70: 54.85 | M70: 3.36 | N70: -4.4408921e-16 | T70: 0 | W70: 0
A71: Catégorie d'emploi | B71: BG | C71: 215-1014 | D71: A - Administratifs et Techniques | E71: -7.3 | F71: 2545.1 | G71: 2957 | I71: 2575.53 | J71: -381.47 | M71: -123.98 | N71: 147.11 | O71: 79.25 | P71: 68 | R71: 399 | S71: 79 | T71: 7.39 | U71: 498 | W71: 6.87 | X71: 99 | Y71: 99
A72: Catégorie d'emploi | B72: BG | C72: 215-1015 | D72: B et C - Administratifs et Techniques | F72: 3775.63 | G72: 3698 | H72: -17.89 | I72: 3837.62 | J72: 157.51 | M72: 21.63 | N72: 58.25 | O72: -17.41 | P72: 76 | R72: 571 | S72: 89 | T72: 8.22 | U72: 571 | W72: 6.63
A73: Mission | B73: BG | C73: AD | D73: Aide publique au développement | E73: 1 | F73: 1460.05 | G73: 1472 | H73: 5 | I73: 1471.82 | J73: -5.18 | N73: 7.77 | O73: 74.51 | P73: -67 | R73: 386.71 | S73: 8 | U73: 401.71 | X73: 15 | Y73: 19
A74: Programme | B74: BG | C74: 209 | D74: Solidarité à l'égard des pays en développement | E74: 1 | F74: 1460.05 | G74: 1472 | H74: 5 | I74: 1471.82 | J74: -5.18 | N74: 7.77 | O74: 74.51 | P74: -67 | R74: 386.71 | S74: 8 | U74: 401.71 | X74: 15 | Y74: 19
A75: Catégorie d'emploi | B75: BG | C75: 209-1101 | D75: Titulaires et CDI en administration centrale | F75: 170.03 | G75: 156.92 | H75: 5 | I75: 170.86 | J75: 8.94 | N75: -4.17 | O75: 12.66 | P75: -17 | R75: 54.25 | S75: 8 | T75: 6.53 | U75: 37.25 | W75: 9 | X75: -17 | Y75: 2
A76: Catégorie d'emploi | B76: BG | C76: 209-1102 | D76: Titulaires et CDI dans le réseau | F76: 90.06 | G76: 89.97 | I76: 90.73 | J76: 0.76 | N76: 0.67 | O76: 1.65 | P76: -1 | R76: 17.14 | T76: 7 | U76: 21.14 | W76: 8.69 | X76: 4 | Y76: 2
A77: Catégorie d'emploi | B77: BG | C77: 209-1103 | D77: CDD et volontaires internationaux | E77: 1 | F77: 1009.9 | G77: 1022.91 | I77: 1006.65 | J77: -16.26 | M77: -0.01 | N77: -2.24 | O77: 52.81 | P77: -55 | R77: 298.99 | T77: 6.66 | U77: 307.99 | W77: 8.99 | X77: 9 | Y77: 15
A78: Catégorie d'emploi | B78: BG | C78: 209-1105 | D78: Agents de droit local | F78: 190.06 | G78: 202.2 | I78: 203.58 | J78: 1.38 | M78: 0.01 | N78: 13.51 | O78: 7.39 | P78: 6 | R78: 16.33 | T78: 8.5 | U78: 35.33 | W78: 8.84 | X78: 19
A79: Mission | B79: BG | C79: MB | D79: Anciens combattants, mémoire et liens avec la Nation | F79: 16.55 | G79: 17 | I79: 16.53 | J79: -0.47 | M79: 0.45 | N79: -0.47 | O79: 0.03 | R79: 2 | U79: 3 | X79: 1 | Y79: 1
A80: Programme | B80: BG | C80: 158 | D80: Indemnisation des victimes des persécutions antisémites et des actes de barbarie pendant la seconde guerre mondiale | F80: 16.55 | G80: 17 | I80: 16.53 | J80: -0.47 | M80: 0.45 | N80: -0.47 | O80: 0.03 | R80: 2 | U80: 3 | X80: 1 | Y80: 1
A81: Catégorie d'emploi | B81: BG | C81: 158-1135 | D81: Catégorie A | F81: 4.63 | G81: 7 | I81: 4.8 | J81: -2.2 | N81: 0.17 | O81: 0.17 | T81: 0 | W81: 0 | Y81: 1
A82: Catégorie d'emploi | B82: BG | C82: 158-1136 | D82: Catégorie B | F82: 3.8 | G82: 4 | I82: 3.8 | J82: -0.2 | T82: 0 | W82: 0
A83: Catégorie d'emploi | B83: BG | C83: 158-1137 | D83: Catégorie C | F83: 2 | G83: 2 | I83: 2 | T83: 0 | W83: 0
A84: Catégorie d'emploi | B84: BG | C84: 158-1138 | D84: Contractuels | F84: 6.12 | G84: 4 | I84: 5.93 | J84: 1.93 | M84: 0.45 | N84: -0.64 | O84: -0.14 | R84: 2 | T84: 7.6 | U84: 3 | W84: 11.4 | X84: 1
A85: Mission | B85: BG | C85: VA | D85: Cohésion des territoires | E85: -249.25 | G85: 391 | H85: -249.37 | I85: 62.38 | J85: -79.25 | M85: 62.5 | Y85: 100
A86: Programme | B86: BG | C86: 112 | D86: Impulsion et coordination de la politique d'aménagement du territoire | G86: 100 | H86: -7 | I86: 61.91 | J86: -31.09 | M86: 68.91 | Y86: 100
A87: Catégorie d'emploi | B87: BG | C87: 112-1052 | D87: Catégorie A | G87: 100 | H87: -7 | I87: 61.91 | J87: -31.09 | M87: 68.91 | T87: 0 | W87: 0 | Y87: 100
A88: Programme | B88: BG | C88: 147 | D88: Politique de la ville | E88: -249.25 | G88: 291 | H88: -242.37 | I88: 0.47 | J88: -48.16 | M88: -6.41
A89: Catégorie d'emploi | B89: BG | C89: 147-1052 | D89: Catégorie A | E89: -225 | G89: 225 | H89: -234.78 | I89: 0.47 | J89: 10.25 | M89: 10.25 | T89: 0 | W89: 0
A90: Catégorie d'emploi | B90: BG | C90: 147-1053 | D90: Catégorie B | E90: -24.25 | G90: 66 | H90: -7.59 | J90: -58.41 | M90: -16.66 | T90: 0 | W90: 0
A91: Mission | B91: BG | C91: CA | D91: Conseil et contrôle de l'État | E91: 1 | F91: 6178.82 | G91: 6483.76 | H91: -21.5 | I91: 6400.9 | J91: -61.36 | L91: 143 | M91: 2.65 | N91: 98.93 | O91: 41.13 | P91: 59 | R91: 1265.6 | S91: 161.2 | U91: 1325.1 | V91: 336.2 | X91: 59.5 | Y91: 42
A92: Programme | B92: BG | C92: 165 | D92: Conseil d'État et autres juridictions administratives | E92: 1 | F92: 4260.64 | G92: 4503 | H92: -16.5 | I92: 4447.35 | J92: -39.15 | L92: 143 | N92: 61.21 | O92: 16.96 | P92: 44 | R92: 980.2 | S92: 99.8 | U92: 1024.8 | V92: 271.8 | X92: 44.6 | Y92: 41
A93: Catégorie d'emploi | B93: BG | C93: 165-1130 | D93: Membres du Conseil d'Etat | F93: 230.51 | G93: 235.77 | I93: 232.99 | J93: -2.78 | N93: 2.48 | O93: -4.6 | P93: 7 | R93: 46 | S93: 13 | T93: 6.81 | U93: 51 | V93: 11 | W93: 5.75 | X93: 5 | Y93: 1
A94: Catégorie d'emploi | B94: BG | C94: 165-1131 | D94: Magistrats de l'ordre administratif | F94: 1267.72 | G94: 1328.69 | I94: 1313.91 | J94: -14.78 | N94: 46.19 | O94: 9.14 | P94: 37 | R94: 172.9 | S94: 39 | T94: 5.99 | U94: 211.3 | V94: 70 | W94: 5.16 | X94: 38.4 | Y94: 25
A95: Catégorie d'emploi | B95: BG | C95: 165-1135 | D95: Catégorie A | E95: 1 | F95: 957.52 | G95: 1081.5 | H95: 0.5 | I95: 949.57 | J95: -132.43 | L95: 18 | N95: -25.45 | O95: -76.27 | P95: 51 | R95: 295.6 | S95: 9 | T95: 7.6 | U95: 277.5 | V95: 48.8 | W95: 5.05 | X95: -18.1 | Y95: 4
A96: Catégorie d'emploi | B96: BG | C96: 165-1136 | D96: Catégorie B | F96: 524.15 | G96: 500 | H96: -1.5 | I96: 551.06 | J96: 52.56 | L96: 30.5 | N96: -2.09 | O96: 13.07 | P96: -15 | R96: 105 | S96: 16 | T96: 5.01 | U96: 107 | V96: 28 | W96: 6.86 | X96: 2 | Y96: 6
A97: Catégorie d'emploi | B97: BG | C97: 165-1137 | D97: Catégorie C | F97: 1280.74 | G97: 1357.04 | H97: -15.5 | I97: 1399.82 | J97: 58.28 | L97: 94.5 | N97: 40.08 | O97: 75.62 | P97: -36 | R97: 360.7 | S97: 22.8 | T97: 5.53 | U97: 378 | V97: 114 | W97: 7 | X97: 17.3 | Y97: 5
A98: Programme | B98: BG | C98: 126 | D98: Conseil économique, social et environnemental | F98: 148.39 | G98: 154 | I98: 150.7 | J98: -3.3 | M98: -2.35 | N98: 4.66 | O98: 0.99 | P98: 5 | R98: 8 | S98: 1 | U98: 13 | X98: 5 | Y98: 1
A99: Catégorie d'emploi | B99: BG | C99: 126-1134 | D99: Catégorie A + | F99: 18.7 | G99: 19 | I99: 16.51 | J99: -2.49 | M99: 0.06 | N99: -2.25 | O99: -0.75 | P99: -1 | R99: 2 | T99: 4 | W99: 0 | X99: -2 | Y99: 1
A100: Catégorie d'emploi | B100: BG | C100: 126-1135 | D100: Catégorie A | F100: 33.75 | G100: 22 | I100: 33.75 | J100: 11.75 | O100: -0.67 | P100: 1 | R100: 2 | T100: 11 | U100: 2 | W100: 7 | Y100: 1
...

Sheet Annexe Etat
B1: MISSIONS | J1: PROGRAMMES
A2: AA | B2: Action extérieure de l'État | G2: M | H2: AA | I2: Action extérieure de l'État
A3: AB | B3: Administration générale et territoriale de l'État | G3: P | H3: AA | I3: 105 | J3: Action de la France en Europe et dans le monde
A4: AC | B4: Agriculture, alimentation, forêt et affaires rurales | G4: P | H4: AA | I4: 151 | J4: Français à l'étranger et affaires consulaires
A5: AD | B5: Aide publique au développement | G5: P | H5: AA | I5: 185 | J5: Diplomatie culturelle et d'influence
A6: VA | B6: Cohésion des territoires | G6: M | H6: AB | I6: Administration générale et territoriale de l'État
A7: CA | B7: Conseil et contrôle de l'État | G7: P | H7: AB | I7: 216 | J7: Conduite et pilotage des politiques de l'intérieur
A8: CB | B8: Culture | G8: P | H8: AB | I8: 232 | J8: Vie politique
A9: DA | B9: Défense | G9: P | H9: AB | I9: 354 | J9: Administration territoriale de l'État
A10: DC | B10: Direction de l'action du Gouvernement | G10: M | H10: AC | I10: Agriculture, alimentation, forêt et affaires rurales
A11: TA | B11: Écologie, développement et mobilité durables | G11: P | H11: AC | I11: 149 | J11: Compétitivité et durabilité de l'agriculture, de l'agroalimentaire et de la forêt
A12: DB | B12: Économie | G12: P | H12: AC | I12: 206 | J12: Sécurité et qualité sanitaires de l'alimentation
A13: EC | B13: Enseignement scolaire | G13: P | H13: AC | I13: 215 | J13: Conduite et pilotage des politiques de l'agriculture
A14: GA | B14: Gestion des finances publiques | G14: P | H14: AC | I14: 381 | J14: Allègements du coût du travail en agriculture (TODE-AG)
A15: IA | B15: Immigration, asile et intégration | G15: M | H15: AD | I15: Aide publique au développement
A16: AV | B16: Investir pour la France de 2030 | G16: P | H16: AD | I16: 110 | J16: Aide économique et financière au développement
A17: JA | B17: Justice | G17: P | H17: AD | I17: 209 | J17: Solidarité à l'égard des pays en développement
A18: MA | B18: Médias, livre et industries culturelles | G18: P | H18: AD | I18: 365 | J18: Renforcement des fonds propres de l'Agence française de développement
A19: MB | B19: Monde combattant, mémoire et liens avec la Nation | G19: P | H19: AD | I19: 384 | J19: Fonds de solidarité pour le développement
A20: OA | B20: Outre-mer | G20: M | H20: VA | I20: Cohésion des territoires
A21: RA | B21: Recherche et enseignement supérieur | G21: P | H21: VA | I21: 109 | J21: Aide à l'accès au logement
A22: RB | B22: Régimes sociaux et de retraite | G22: P | H22: VA | I22: 112 | J22: Impulsion et coordination de la politique d'aménagement du territoire
A23: RC | B23: Relations avec les collectivités territoriales | G23: P | H23: VA | I23: 135 | J23: Urbanisme, territoires et amélioration de l'habitat
A24: SA | B24: Santé | G24: P | H24: VA | I24: 147 | J24: Politique de la ville
A25: SB | B25: Sécurités | G25: P | H25: VA | I25: 162 | J25: Interventions territoriales de l'État
A26: SE | B26: Solidarité, insertion et égalité des chances | G26: P | H26: VA | I26: 177 | J26: Hébergement, parcours vers le logement et insertion des personnes vulnérables
A27: SF | B27: Sport, jeunesse et vie associative | G27: M | H27: CA | I27: Conseil et contrôle de l'État
A28: TR | B28: Transformation et fonction publiques | G28: P | H28: CA | I28: 126 | J28: Conseil économique, social et environnemental
A29: TB | B29: Travail, emploi et administration des ministères sociaux | G29: P | H29: CA | I29: 164 | J29: Cour des comptes et autres juridictions financières
A30: XC | B30: Contrôle et exploitation aériens | G30: P | H30: CA | I30: 165 | J30: Conseil d'État et autres juridictions administratives
A31: XJ | B31: Publications officielles et information administrative | G31: M | H31: CB | I31: Culture
A32: YK | B32: Financement des aides aux collectivités pour l'électrification rurale | G32: P | H32: CB | I32: 131 | J32: Création
A33: YB | B33: Gestion du patrimoine immobilier de l'État | G33: P | H33: CB | I33: 175 | J33: Patrimoines
A34: YE | B34: Contrôle de la circulation et du stationnement routiers | G34: P | H34: CB | I34: 224 | J34: Soutien aux politiques du ministère de la culture
A35: YF | B35: Développement agricole et rural | G35: P | H35: CB | I35: 361 | J35: Transmission des savoirs et démocratisation de la culture
A36: ZD | B36: Avances à l'audiovisuel public | G36: M | H36: DA | I36: Défense
G37: P | H37: DA | I37: 144 | J37: Environnement et prospective de la politique de défense
G38: P | H38: DA | I38: 146 | J38: Équipement des forces
G39: P | H39: DA | I39: 178 | J39: Préparation et emploi des forces
G40: P | H40: DA | I40: 212 | J40: Soutien de la politique de la défense
G41: M | H41: DC | I41: Direction de l'action du Gouvernement
G42: P | H42: DC | I42: 129 | J42: Coordination du travail gouvernemental
G43: P | H43: DC | I43: 308 | J43: Protection des droits et libertés
G44: M | H44: TA | I44: Écologie, développement et mobilité durables
G45: P | H45: TA | I45: 113 | J45: Paysages, eau et biodiversité
G46: P | H46: TA | I46: 159 | J46: Expertise, information géographique et météorologie
G47: P | H47: TA | I47: 174 | J47: Énergie, climat et après-mines
G48: P | H48: TA | I48: 181 | J48: Prévention des risques
G49: P | H49: TA | I49: 203 | J49: Infrastructures et services de transports
G50: P | H50: TA | I50: 205 | J50: Affaires maritimes, pêche et aquaculture
G51: P | H51: TA | I51: 217 | J51: Conduite et pilotage des politiques de l'écologie, du développement et de la mobilité durables
G52: P | H52: TA | I52: 235 | J52: Sûreté nucléaire et radioprotection
G53: P | H53: TA | I53: 345 | J53: Service public de l'énergie
G54: P | H54: TA | I54: 380 | J54: Fonds d'accélération de la transition écologique dans les territoires
G55: M | H55: DB | I55: Économie
G56: P | H56: DB | I56: 134 | J56: Développement des entreprises et régulations
G57: P | H57: DB | I57: 220 | J57: Statistiques et études économiques
G58: P | H58: DB | I58: 305 | J58: Stratégies économiques
G59: P | H59: DB | I59: 343 | J59: Plan France Très haut débit
G60: M | H60: EC | I60: Enseignement scolaire
G61: P | H61: EC | I61: 139 | J61: Enseignement privé du premier et du second degrés
G62: P | H62: EC | I62: 140 | J62: Enseignement scolaire public du premier degré
G63: P | H63: EC | I63: 141 | J63: Enseignement scolaire public du second degré
G64: P | H64: EC | I64: 143 | J64: Enseignement technique agricole
G65: P | H65: EC | I65: 214 | J65: Soutien de la politique de l'éducation nationale
G66: P | H66: EC | I66: 230 | J66: Vie de l'élève
G67: M | H67: GA | I67: Gestion des finances publiques
G68: P | H68: GA | I68: 156 | J68: Gestion fiscale et financière de l'État et du secteur public local
G69: P | H69: GA | I69: 218 | J69: Conduite et pilotage des politiques économiques et financières
G70: P | H70: GA | I70: 302 | J70: Facilitation et sécurisation des échanges
G71: M | H71: IA | I71: Immigration, asile et intégration
G72: P | H72: IA | I72: 104 | J72: Intégration et accès à la nationalité française
G73: P | H73: IA | I73: 303 | J73: Immigration et asile
G74: M | H74: AV | I74: Investir pour la France de 2030
G75: P | H75: AV | I75: 421 | J75: Soutien des progrès de l'enseignement et de la recherche
G76: P | H76: AV | I76: 422 | J76: Valorisation de la recherche
G77: P | H77: AV | I77: 423 | J77: Accélération de la modernisation des entreprises
G78: P | H78: AV | I78: 424 | J78: Financement des investissements stratégiques
G79: P | H79: AV | I79: 425 | J79: Financement structurel des écosystèmes d'innovation
G80: M | H80: JA | I80: Justice
G81: P | H81: JA | I81: 101 | J81: Accès au droit et à la justice
G82: P | H82: JA | I82: 107 | J82: Administration pénitentiaire
G83: P | H83: JA | I83: 166 | J83: Justice judiciaire
G84: P | H84: JA | I84: 182 | J84: Protection judiciaire de la jeunesse
G85: P | H85: JA | I85: 310 | J85: Conduite et pilotage de la politique de la justice
G86: P | H86: JA | I86: 335 | J86: Conseil supérieur de la magistrature
G87: M | H87: MA | I87: Médias, livre et industries culturelles
G88: P | H88: MA | I88: 180 | J88: Presse et médias
G89: P | H89: MA | I89: 334 | J89: Livre et industries culturelles
G90: M | H90: MB | I90: Monde combattant, mémoire et liens avec la Nation
G91: P | H91: MB | I91: 158 | J91: Indemnisation des victimes des persécutions antisémites et des actes de barbarie pendant la seconde guerre mondiale
G92: P | H92: MB | I92: 169 | J92: Reconnaissance et réparation en faveur du monde combattant, mémoire et liens avec la Nation
G93: M | H93: OA | I93: Outre-mer
G94: P | H94: OA | I94: 123 | J94: Conditions de vie outre-mer
G95: P | H95: OA | I95: 138 | J95: Emploi outre-mer
G96: M | H96: RA | I96: Recherche et enseignement supérieur
G97: P | H97: RA | I97: 142 | J97: Enseignement supérieur et recherche agricoles
G98: P | H98: RA | I98: 150 | J98: Formations supérieures et recherche universitaire
G99: P | H99: RA | I99: 172 | J99: Recherches scientifiques et technologiques pluridisciplinaires
G100: P | H100: RA | I100: 190 | J100: Recherche dans les domaines de l'énergie, du développement et de la mobilité durables
...

Sheet Commissions R
A1: Ministère de rattachement | B1: Instance | C1: Texte institutif | D1: Nombre de membres | E1: Coût de fonctionnement 2022 (k€) | F1: Coût de fonctionnement 2023 (k€) | G1: Coût de fonctionnement 2024 (k€) | H1: Réunions 2022 | I1: Réunions 2023 | J1: Réunions 2024 | K1: Statut au Jaune 2026 | L1: Page du Jaune | M1: Observations du Jaune
A2: Premier ministre | B2: Autorité nationale d'Audit pour les Fonds européens | C2: Article 60 de la Loi n° 2002-1576 du 30 décembre 2002 de finances rectificative pour 2002 Décret n° 2008-548 modifié du 11 juin 2008 relatif à la commission interministérielle de coordination des contrôles portant sur les opérations cofinancées par les fonds européens Décret n°2023- 1067 du 30 novembre 2023 relatif à l'Autorité nationale d'audit pour les Fonds européens. Arrêté du 7 janvier 2009 relatif au fonctionnement, aux moyens et à l'organisation interne de la commission interministérielle de coordination des contrôles | D2: 9 | E2: 15.45 | F2: 14.5 | G2: 13.2 | H2: 6 | I2: 6 | J2: 5 | K2: en vigueur | L2: 4 | M2: En 2024, cinq réunions ont été organisées, complétées par une consultation écrite.
A3: Premier ministre | B3: Comité consultatif national d'éthique du numérique | C3: Décret n° 2024-463 du 23 mai 2024 portant création du Comité consultatif national d'éthique du numérique | D3: 21 | E3: 0 | F3: 0 | G3: 0 | H3: 0 | I3: 0 | J3: 0 | K3: en vigueur | L3: 4 | M3: Le CCNE du numérique est un comité créé en mai 2024. Les membres étant toujours en cours de nomination (excepté le président qui a été nommé en février 2025), il n’a pas encore commencé à fonctionner. Ses dépenses de fonctionnement restent réduites et absorbées par le CCNE santé.
A4: Premier ministre | B4: Comité de suivi des retraites | C4: Articles L .114-4 et R. 114-1 à R.114-6 du code de la sécurité sociale | D4: 5 | E4: 16.4 | F4: 12.39 | G4: 20.84 | H4: 8 | I4: 7 | J4: 7 | K4: en vigueur | L4: 5 | M4: Les cinq membres du CSR ont cessé leurs fonctions le 31 juillet 2024. Le nouveau président a été nommé en avril 2025 et les quatre membres en mai 2025. La hausse des coûts entre 2023 et 2024 s'explique par l’augmentation des membres rémunérés (remise d’un rapport) et par la réduction des surfaces occupées en 2023.
A5: Premier ministre | B5: Comité de surveillance des investissements d'avenir | C5: Loi n° 2010-237 du 9 mars 2010 de finances rectificative pour 2010 Décret n° 2010-80 du 22 janvier 2010 relatif au secrétariat général pour l'investissement Décret n° 2021-9 du 7 janvier 2021 modifiant le décret n° 2010-80 du 22 janvier 2010 | D5: 18 | E5: 0 | F5: 0 | G5: 1.5 | H5: 6 | I5: 26 | J5: 5 | K5: en vigueur | L5: 5 | M5: En 2024, cinq réunions plénières ont été organisées. Chacune d’entre elles a été suivie d’un déjeuner, pour un coût global de 1,5 k€.
A6: Premier ministre | B6: Comité directeur de la certification en sécurité des technologies de l'information | C6: Décret n° 2002-535 du 18 avril 2002 relatif à l'évaluation et à la certification de la sécurité offerte par les produits et les systèmes des technologies de l'information | D6: 11 | E6: 0.64 | F6: 0.64 | G6: 0.64 | H6: 1 | I6: 1 | J6: 1 | K6: en vigueur | L6: 5
A7: Premier ministre | B7: Commission chargée de donner un avis sur certaines opérations relatives aux matériels aéronautiques et aux matériels d'armement complexes | C7: Décret n° 2024-509 du 5 juin 2024 renouvelant la commission consultative chargée de donner un avis sur certaines opérations relatives aux matériels aéronautiques et aux matériels d'armement complexes | D7: 8 | E7: 38.68 | F7: 38.68 | G7: 38.68 | H7: 5 | I7: 5 | J7: 5 | K7: en vigueur | L7: 5
A8: Premier ministre | B8: Commission consultative chargée d'émettre un avis sur les matériels susceptibles de porter atteinte à l'intimité de la vie privée et au secret des correspondances | C8: Décret n° 2024-501 du 3 juin 2024 renouvelant la commission consultative chargée d'émettre un avis sur les matériels susceptibles de porter | D8: 11 | E8: 16.19 | F8: 16.19 | G8: 16.19 | H8: 6 | I8: 6 | J8: 6 | K8: en vigueur | L8: 5
A9: Premier ministre | B9: Commission d'enrichissement de la langue française | C9: Décret n° 96-602 modifié du 3 juillet 1996 relatif à l'enrichissement de la langue française | D9: 19 | E9: 0 | F9: 0 | G9: 0 | H9: 11 | I9: 11 | J9: 11 | K9: en vigueur | L9: 6 | M9: La commission ne supporte pas de coût spécifique.
A10: Premier ministre | B10: Commission du droit local d'Alsace- Moselle | C10: Décret n° 2021-1580 du 7 décembre 2021 relatif à la commission du droit local d'Alsace-Moselle. | D10: 24 | E10: 0 | F10: 0 | G10: 0 | H10: 0 | I10: 0 | J10: 3 | K10: en vigueur | L10: 6 | M10: La commission ne supporte pas de coût spécifique car ses membres exercent leurs missions à titre gratuit. De plus, son fonctionnement est indissociable de celui de la préfecture du Bas-Rhin qui assure son secrétariat.
A11: Premier ministre | B11: Commission interministérielle de défense et de sécurité des secteurs d'activités d'importance vitale | C11: Articles R. 1332-10 à R. 1332-12 du code de la défense | D11: 13 | E11: 2.15 | F11: 2.15 | G11: 2.15 | H11: 2 | I11: 2 | J11: 2 | K11: en vigueur | L11: 6
A12: Premier ministre | B12: Commission interministérielle de la sûreté aérienne | C12: Articles D*. 1443-1 et D.1443-4 du code de la défense | D12: 12 | E12: 5.31 | F12: 5.31 | G12: 2.66 | H12: 2 | I12: 2 | J12: 1 | K12: en vigueur | L12: 6
A13: Premier ministre | B13: Commission interministérielle des biens à double usage | C13: Décret n° 2010-294 du 18 mars 2010 portant création d'une commission interministérielle des biens à double usage ; Décret n° 2020-367 du 26 mars 2020 portant prorogation de la commission interministérielle des biens à double usage ; Décret n° 2023-471 du 19 juin 2023 relatif à la présidence de la commission interministérielle des biens à double usage. | D13: 12 | E13: 0.65 | F13: 0.3 | G13: 0.3 | H13: 12 | I13: 12 | J13: 12 | K13: en vigueur | L13: 6
A14: Premier ministre | B14: Commission interministérielle pour l'étude des exportations de matériels de guerre | C14: Article D. 1132-53 du code de la défense Décret n° 55- 965 du 16 juillet 1955 portant réorganisation de la commission | D14: 12 | E14: 1255.13 | F14: 1255.13 | G14: 1255.13 | H14: 11 | I14: 11 | J14: 11 | K14: en vigueur | L14: 6
A15: Premier ministre | B15: Commission nationale consultative des gens du voyage | C15: Article 10-1 de la loi n° 2000-614 du 5 juillet 2000 relative à l’accueil et à l’habitat des gens du voyage Décret n° 2015-563 du 20 mai 2015 relatif à la Commission nationale consultative des gens du voyage | D15: 33 | E15: 6.35 | F15: 7.07 | G15: 6.4 | H15: 7 | I15: 15 | J15: 14 | K15: en vigueur | L15: 7 | M15: En 2024, la Commission a été très active, avec plusieurs réunions plénières (5 janvier, 27 mars, 26 juin, 23 octobre) et de nombreux groupes de travail, notamment sur le projet mémoriel de Montreuil-Bellay (7 réunions) et sur les difficultés de stationnement (2 réunions en janvier et mars, co-présidé par le ministère de l’Intérieur). Les frais engagés concernent principalement le transport et la restauration du Président et de certains membres lors des réunions, ainsi que des déplacements conjoints du Président avec la Dihal (Perpignan, Tours, Angers) et des rendez-vous avec des cabinets ministériels ou groupes de travail délocalisés. Par ailleurs, un travail préparatoire a été mené pour améliorer le fonctionnement de la Commission en vue de la nouvelle mandature qui débutera en 2026.
A16: Premier ministre | B16: Commission nationale d'orientation et d'intégration | C16: Articles R.* 4139-14 et suivants du code de la défense | D16: 5 | E16: 0 | F16: 0 | G16: 0 | H16: 10 | I16: 10 | J16: 8 | K16: en vigueur | L16: 8
A17: Premier ministre | B17: Commission nationale des professions foraines et circassiennes | C17: Décret n°2017-1501 du 27 octobre 2017 relatif à la Commission nationale des professions foraines et circassiennes Décret n°2023-7 du 6 janvier 2023 modifiant le décret n° 2017-1501 du 27 octobre 2017 | D17: 24 | E17: 7.6 | F17: 6.6 | G17: 7.8 | H17: 3 | I17: 3 | J17: 3 | K17: en vigueur | L17: 8 | M17: La légère évolution du budget de fonctionnement de la Commission est liée à la création de la cellule d'accompagnement individualisée à destination des circassiens, dans le cadre de l'application de la loi n° 2021-1536 du 30 novembre 2021.
A18: Premier ministre | B18: Commission pour la restitution des biens et l'indemnisation des victimes de spoliations antisémites (CIVS) | C18: Décret n° 2024-11 du 5 janvier 2024 instituant une commission pour la restitution des biens et l'indemnisation des victimes de spoliations antisémites et pris en application des articles L. 115-3, L. 115-4 et L. 451-10-1 du code du patrimoine | D18: 14 | E18: 134.67 | F18: 126.75 | G18: 116.47 | H18: 15 | I18: 17 | J18: 15 | K18: en vigueur | L18: 8 | M18: Les coûts de fonctionnement de la commission peuvent varier en fonction du taux de présence en réunion et du calendrier de tenue des réunions.
A19: Premier ministre | B19: Commission supérieure de codification | C19: Articles L. 315-1 et L. 351-1-I du code des relations entre le public et l’administration ; Décret n° 89-647 du 12 septembre 1989 modifié relatif à la composition et au fonctionnement de la Commission supérieure de codification ; Article 29 de la loi n° 2018-699 du 3 août 2018 visant à garantir la présence des parlementaires dans certains organismes extérieurs au Parlement et à simplifier les modalités de leur nomination. | D19: 18 | E19: 66.81 | F19: 68.98 | G19: 95.76 | H19: 7 | I19: 8 | J19: 13 | K19: en vigueur | L19: 8 | M19: Les coûts de fonctionnement de la Commission supérieure de codification (CSC) correspondent à l'indemnisation de certains de ses membres (vice- président, rapporteurs général et adjoint) et à celle des rapporteurs particuliers désignés pour coordonner les travaux, ainsi qu'aux frais de déplacement des membres pour les séances plénières. L’activité de la CSC a été très soutenue en 2024 avec 13 séances plénières (contre 8 en 2023) en présentiel consacrées au nouveau code des impositions sur les biens et
A20: Premier ministre | B20: Conseil d'analyse économique | C20: Décret n° 97-766 du 22 juillet 1997 portant création du Conseil d'analyse économique Décret n° 2017-14 du 6 janvier 2017 modifiant le décret n° 97-766 du 22 juillet 1997 modifié portant création du Conseil d'analyse économique Décret n° 2018-261 du 11 avril 2018 modifiant le décret n° 97-766 du 22 juillet 1997 modifié portant création du Conseil d'analyse économique | D20: 17 | E20: 836.99 | F20: 809 | G20: 831 | H20: 14 | I20: 18 | J20: 16 | K20: en vigueur | L20: 9 | M20: L'augmentation constatée en 2024 est due à un versement effectué dans le cadre d'un partenariat avec l'Institut des politiques publiques relatif au programme de recherche « développement du modèle de micro simulation TAXIPP ».
A21: Premier ministre | B21: Conseil d'orientation des politiques de jeunesse | C21: Décret n° 2016-1377 du 12 octobre 2016 portant création du Conseil d'orientation des politiques de jeunesse | D21: 108 | E21: 27.5 | F21: 44.15 | G21: 29.15 | H21: 25 | I21: 31 | J21: 39 | K21: en vigueur | L21: 9 | M21: Les coûts 2024 sont revenus à un niveau habituel. Pour mémoire, en 2023, deux séminaires spécifiques avaient été mis en place pour les membres du collège jeune et pour mettre en place une concertation avec des jeunes de l'ASE dans le cadre de la rédaction d'un rapport sur le sujet.
A22: Premier ministre | B22: Conseil d'orientation des retraites | C22: Articles L. 114-2 et D. 114-4- 0-1 à D. 114-4-0-4 du code de la sécurité sociale | D22: 41 | E22: 938.53 | F22: 1096 | G22: 1122 | H22: 16 | I22: 16 | J22: 11 | K22: en vigueur | L22: 9 | M22: L’augmentation des coûts de fonctionnement constatée en 2024 s’explique, d’une part, par une évolution de la
A23: Premier ministre | B23: Conseil d'orientation pour l'emploi | C23: Décret n° 2005-326 du 7 avril 2005 portant création du Conseil d'orientation pour l'emploi Décret n° 2019-1087 du 25 octobre 2019 modifiant la composition du Conseil d’orientation pour l’emploi | D23: 35 | E23: 0.05 | F23: 0 | G23: 0 | H23: 4 | I23: 2 | J23: 0 | K23: en vigueur | L23: 10 | M23: L’absence de réunion du COE en 2024 s’explique par plusieurs facteurs, notamment l'absence de saisine par le Gouvernement et le départ non remplacé du commissaire général de France Stratégie, qui en assurait la présidence.
A24: Premier ministre | B24: Conseil national consultatif pour la biosécurité | C24: Vu la loi n° 2006-450 du 18 avril 2006 modifiée de programme pour la recherche, notamment son titre IV, Décret n° 2015- 1095 du 31 août 2015 relatif au Conseil national consultatif pour la biosécurité (NOR : PRMD1519765D) | D24: 12 | E24: 39.38 | F24: 39.38 | G24: 39.38 | H24: 8 | I24: 8 | J24: 8 | K24: en vigueur | L24: 10
A25: Premier ministre | B25: Conseil national de la montagne | C25: Loi n° 85-30 du 9 janvier 1985 relative au développement et à la protection de la montagne Décret n° 2017-754 du 3 mai 2017 relatif à la composition et au fonctionnement du conseil national de la montagne | D25: 90 | E25: 0 | F25: 5 | G25: 0 | H25: 0 | I25: 1 | J25: 0 | K25: en vigueur | L25: 10 | M25: La réunion initialement prévue en 2024 a été annulée en raison de la dissolution de l'Assemblée nationale. Lorsque le Conseil se réunit, les seules dépenses imputables concernent la location de salle ainsi que les frais de restauration des participants.
A26: Premier ministre | B26: Conseil national des politiques de lutte contre la pauvreté et l'exclusion sociale | C26: Articles L. 143-1, R. 143-1 à D. 143-8 du code de l'action sociale et des familles | D26: 65 | E26: 235 | F26: 235 | G26: 235 | H26: 10 | I26: 10 | J26: 20 | K26: en vigueur | L26: 10 | M26: Le budget est stable depuis 2019 pour financer l'accompagnement logistique et méthodologique du 5ème collège malgré l'inflation
A27: Premier ministre | B27: Conseil national des villes | C27: Décret n° 2015-77 du 27 janvier 2015 relatif aux instances en charge de la politique de la ville | D27: 64 | E27: 124 | F27: 75 | G27: 43 | H27: 3 | I27: 8 | J27: 7 | K27: en vigueur | L27: 11 | M27: Le nombre de réunions mentionné correspond à la tenue des assemblées plénières, dont deux ont été organisées à titre exceptionnel en distanciel. Par ailleurs, deux séminaires internes ont été organisés. La diminution progressive du budget du CNV s’explique notamment par le recours accru à des formats de réunion mixtes (présentiel/distanciel) et par l’ajustement des modalités de prise en charge des frais de déplacement des membres.
A28: Premier ministre | B28: Conseil scientifique sur les processus de radicalisation | C28: Article L. 123-2 du code de la sécurité intérieure Décret n° 2017-693 du 3 mai 2017 créant un conseil scientifique sur les processus de radicalisation | D28: 31 | E28: 146.5 | F28: 149.8 | G28: 180.11 | H28: 8 | I28: 9 | J28: 16 | K28: en vigueur | L28: 11 | M28: Grâce à l’attribution d’un budget dédié, le Conseil a pu déployer de nombreuses actions inscrites dans sa feuille de route (RIM). Quatre réunions plénières ont été tenues, et un Plan national de formation (PNF) a été mis en œuvre avec le ministère de l’Éducation nationale, formant près de 3000 référents en région. Ce programme s’est appuyé sur
A29: Premier ministre | B29: Haut Comité pour le logement des personnes défavorisées et le suivi du droit au logement opposable | C29: Décret n° 2021-386 du 1er avril 2021 relatif au Haut Comité pour le logement des personnes défavorisées et le suivi du droit au logement opposable (LOGL2006338D) | D29: 50 | E29: 29 | F29: 33 | G29: 34 | H29: 20 | I29: 24 | J29: 20 | K29: en vigueur | L29: 12 | M29: En 2024, la hausse des coûts s’explique par une augmentation des travaux d’impression.
A30: Premier ministre | B30: Haut conseil à l'égalité entre les femmes et les hommes | C30: Article 9-1 de la loi n° 2008- 496 du 27 mai 2008 portant diverses dispositions d'adaptation au droit communautaire dans le domaine de la lutte contre les discriminations modifiée ; - Décret n° 2013- 8 du 3 janvier 2013 portant création du Haut Conseil à l'égalité entre les femmes et les hommes ; - Décret n° 2021-921 du 9 juillet 2021 relatif à la composition et au fonctionnement du | D30: 96 | E30: 52.1 | F30: 52.5 | G30: 29.5 | H30: 44 | I30: 46 | J30: 20 | K30: en vigueur | L30: 12 | M30: En 2024, l’instance n’a été active que durant quelques mois, en raison d’une période de transition liée au renouvellement de sa présidence. La nomination des membres pour la période 2025-2028 est intervenue par arrêté du 19 juin 2025 portant désignation de la présidence et des membres du Haut Conseil à l’égalité entre les femmes et les hommes.
A31: Premier ministre | B31: Haut Conseil à la vie associative | C31: Loi n° 2014-856 du 31 juillet 2014 relative à l'économie sociale et solidaire Décret n° 2011-773 du 28 juin 2011 relatif au Haut Conseil à la vie associative | D31: 35 | E31: 8.5 | F31: 22.08 | G31: 21.03 | H31: 2 | I31: 2 | J31: 1 | K31: en vigueur | L31: 13 | M31: Le Haut conseil s’est réuni une fois en formation plénière en 2024 (il s’était réuni deux fois dans ce même format en 2022 et en 2023). Il a également tenu : - des réunions mensuelles du bureau ; - deux réunions par mois des commissions pour les travaux permanents ; - des réunions de commissions plus ponctuelles pour produire les publications du HCVA ; - des rencontres avec certains partenaires institutionnels. Sans effet sur la productivité de l'instance, les coûts de fonctionnement sont maitrisés et restent stables depuis la nouvelle prise en compte, sur le budget de l'instance, depuis 2023, de l'intervention de sténotypistes lors des commissions. Le nombre de membres ne prend pas en compte les représentants des administrations.
A32: Premier ministre | B32: Haut conseil de la famille, de l'enfance et de l'âge | C32: Articles L. 142-1 et D. 141-1 à D. 141-7 du code de l’action sociale et des familles | D32: 230 | E32: 794.49 | F32: 807 | G32: 773 | H32: 29 | I32: 27 | J32: 33 | K32: en vigueur | L32: 13 | M32: La baisse des coûts de fonctionnement du Haut Conseil s’explique par le départ à la retraite, en mars 2024, de la secrétaire générale adjointe en charge du Conseil de l’âge, dont le remplacement n’est
A33: Premier ministre | B33: Haut conseil du financement de la protection sociale | C33: Articles L. 114-1 A.-I. et D. 114-0-4 du code de la sécurité sociale | D33: 56 | E33: 419.37 | F33: 465 | G33: 599 | H33: 11 | I33: 12 | J33: 11 | K33: en vigueur | L33: 14 | M33: L'augmentation en 2024 est le résultat de plusieurs facteurs : - comptabilisation en année pleine de la rémunération du secrétaire général adjoint arrivé courant 2023 ; - plusieurs paiements effectués dans le cadre de projets de recherche (partenariat OCDE sur la comparaison franco- allemande en matière de protection sociale et étude sur les freins à la progression des salaires).
A34: Premier ministre | B34: Haut Conseil pour le climat | C34: Article 9 de la loi n° 2019- 1147 du 8 novembre 2019 relative à l'énergie et au climat Articles L. 132-4 et L. 132-5, article L. 222-1, articles D. 132-1 à D. 132-7 du code de l'environnement | D34: 13 | E34: 801.05 | F34: 682 | G34: 1063 | H34: 10 | I34: 12 | J34: 12 | K34: en vigueur | L34: 14 | M34: On note en 2024 une forte augmentation de la masse salariale malgré les départs du directeur et de la présidente, principalement liée au recrutement de plusieurs postes pourvus en cours d’année 2023 mais comptabilisés en année pleine en 2024, ainsi qu’aux recrutements intervenus en 2024. A cela s'ajoute une forte augmentation des frais de déplacement temporaire avec la régularisation des remboursements des frais de déplacement sur 2023 et 2024 ; et enfin une action de formation importante des agents du Haut conseil à l'évaluation des politiques publiques. Pour autant il s'agit ici davantage d'une remise à niveau après deux
A35: Éducation nationale, enseignement supérieur et recherche | B35: Comité consultatif du fonds pour le développement de la vie associative | C35: Loi n° 2018-699 du 3 août 2018 visant à garantir la présence des parlementaires dans certains organismes extérieurs au Parlement et à simplifier les modalités de leur nomination Décret n° 2011-2121 du 30 décembre 2011 relatif au fonds pour le développement de la vie associative Décret n° 2018- 460 du 8 juin 2018 relatif au fonds pour le développement de la vie associative | D35: 25 | E35: 0 | F35: 0.13 | G35: 0.12 | H35: 1 | I35: 1 | J35: 6 | K35: en vigueur | L35: 16 | M35: En 2022, les réunions ont eu lieu en visio-conférence, n'entraînant pas de frais spécifiques. En 2023 le comité FDVA s'est tenu en présentiel, ce qui a engendré un coût. En 2024 il s'est tenu 6 comités FDVA, dont 5 en présentiel et 1 en visio- conférence. – NB: Un comité FDVA s'est tenu au cabinet de la ministre, en présence de la ministre, il n’y a donc pas de décompte de frais. Le maintien de la dépense par rapport à 2023 malgré l'augmentation du nombre de réunions s'explique par une rationalisation des frais de bouche.
A36: Éducation nationale, enseignement supérieur et recherche | B36: Comité d'histoire de l'éducation nationale | C36: Décision au BO n°21 du 23 mai 2019 Arrêté du 22 avril 2024, BO n°17 du 25 avril 2024 | D36: 15 | E36: 0 | F36: 46 | G36: 0 | H36: 0 | I36: 1 | J36: 1 | K36: en vigueur | L36: 16 | M36: Le coût nul pour l’année 2024 s’explique par la fin de mission de la secrétaire générale et l’arrêt de la convention de mise à disposition de bureaux au campus Condorcet.
... A66: Éducation nationale, enseignement supérieur et recherche | B66: Conseil national des astronomes et physiciens | C66: Décret n° 86-433 du 12 mars 1986 modifié relatif au Conseil national des astronomes et des physiciens | D66: 32 | E66: 71 | F66: 57 | G66: 53.8 | H66: 29 | I66: 22 | J66: 33 | K66: en vigueur | L66: 26 | M66: Contrairement à l'année 2023, le coût de fonctionnement pour l'année 2024 n’intègre pas les frais de déplacement des membres du CNAP, dont le montant ne sera exceptionnellement connu qu'à la fin de l'année 2025.
A67: Éducation nationale, enseignement supérieur et recherche | B67: Conseil national des universités pour les disciplines de santé | C67: Décret n° 92-70 du 16 janvier 1992 relatif au Conseil national des universités Décret n° 87-31 du 20 janvier 1987 relatif au Conseil national des universités pour les disciplines de santé | E67: 5024 | F67: 5184 | G67: 6486 | H67: 565 | I67: 696 | J67: 504 | K67: en vigueur | L67: 26 | M67: La hausse du coût de fonctionnement en 2024 est essentiellement due à une forte hausse du montant des frais de mission remboursés aux établissements d’enseignement supérieur en 2024 au titre des déplacements effectués en 2023 par les membres du CNU. Ils s’expliquent par l’augmentation des tarifs de transport ferroviaire et la hausse réglementaire des forfaits d’hébergement, ainsi que par un nombre plus important de réunions en 2023 pour l’installation des sections suite aux élections de fin 2023 et, en 2024, par des déplacements plus nombreux
A68: Éducation nationale, enseignement supérieur et recherche | B68: Conseil stratégique de la recherche | C68: Article L. 120-1 du code de la recherche - Décret n° 2013-943 du 21 octobre 2013 relatif au Conseil stratégique de la recherche | D68: 26 | E68: 0 | F68: 0 | G68: 0 | H68: 0 | I68: 0 | J68: 0 | K68: en vigueur | L68: 27 | M68: Il n’y a eu aucune réunion en 2024, car les ministres chargés de la recherche n’ont pas convoqué ces instances.
A69: Éducation nationale, enseignement supérieur et recherche | B69: Conseils scientifiques en médecine, pharmacie et odontologie | C69: Articles R. 632-3, D. 633-2 et R. 634-2 du code de l'éducation Arrêté du 3 avril 2017 relatif à l'organisation et au fonctionnement des conseils scientifiques en médecine, en odontologie et en pharmacie. | D69: 27 | E69: 77.79 | F69: 95 | G69: 102.43 | H69: 100 | I69: 115 | J69: 111 | K69: en vigueur | L69: 27 | M69: De nouveaux membres ont été recrutés par les présidents des conseils scientifiques pour renforcer les groupes d'experts dans leur travail de rédaction des épreuves. De plus, les réunions se sont davantage tenues en présentiel, nécessitant des déplacements d'experts venant des universités non franciliennes et des frais de transport associés.
A70: Éducation nationale, enseignement supérieur et recherche | B70: Observatoire national de la vie étudiante | C70: Arrêté du 14 février 1989 relatif à l'Observatoire de la vie étudiante | D70: 26 | E70: 121.3 | F70: 379.08 | G70: 113.97 | H70: 3 | I70: 3 | J70: 4 | K70: en vigueur | L70: 27 | M70: Les réunions se sont tenues en présentiel. Le conseil et le collège scientifique se sont réunis 2 fois chacun. En 2023, l’OVE a produit une enquête sur les conditions de vie des étudiants (CDV 2023). L’OVE fait cette enquête tous les trois ans (environ 300 000€). La réunion de début d’année n’a pas eu lieu car l’OVE a été très occupé par la diffusion des résultats de cette enquête. Une conférence de presse pour la diffusion des résultats de l’enquête conditions de vie a été organisée en février 2024.
A71: Outre-mer | B71: Conseil consultatif de l'île de La Passion-Clipperton | C71: Décret n° 2023-1182 du 13 décembre 2023 relatif à l'administration de l'île de La Passion-Clipperton | D71: 13 | F71: 0 | G71: 0 | I71: 0 | J71: 0 | K71: en vigueur | L71: 29 | M71: Créé par décret le 13 décembre 2023, le conseil consultatif de l’île de La Passion-Clipperton ne s’est pas encore réuni en réunion plénière. La réunion inaugurale de l’instance est prévue en 2025.
A72: Justice | B72: Comité d’orientation stratégique de l’Agence du travail d'intérêt général et de l'insertion professionnelle des personnes placées sous main de justice | C72: Décret n° 2018-1098 du 7 décembre 2018 portant création d'un service à compétence nationale dénommé « Agence du travail d'intérêt général et de l'insertion professionnelle des personnes placées sous main de justice » | D72: 23 | E72: 4 | F72: 8.4 | G72: 7.3 | H72: 2 | I72: 2 | J72: 2 | K72: en vigueur | L72: 30 | M72: Le COS de l'ATIGIP continue d’être actif sous la présidence du directeur de l'administration pénitentiaire. Comme chaque année, il se réunit à raison de deux fois par an.
A73: Justice | B73: Comité ministériel de transaction (justice) | C73: Article 24 de la loi n° 2018- 727 du 10 août 2018 pour un Etat au service d'une société de confiance Décret n° 2018-1029 du 23 novembre 2018 relatif aux comités ministériels de transaction Arrêté du 7 octobre 2019 portant création et composition du comité ministériel de transaction du ministère de la justice | D73: 3 | E73: 0 | F73: 0 | G73: 0 | H73: 0 | I73: 0 | J73: 0 | K73: en vigueur | L73: 30 | M73: Le coût de fonctionnement est nul car il est indissociable du fonctionnement normal du ministère. Ses membres, des fonctionnaires, sont appelés à siéger au titre de leurs fonctions. Le secrétariat est quant à lui assuré de manière accessoire par des agents permanents assurant de nombreuses autres missions à teneur juridique. En outre, aucune réunion n’a été organisée en 2024 car aucune transaction supérieure au seuil de 500 000 euros n’a été conclue au titre de l’année 2024.
A74: Justice | B74: Commission chargée d'agréer les personnes habilitées à effectuer des missions d'identification par empreintes génétiques dans le cadre de procédures judiciaires | C74: Décret n° 97-109 du 6 février 1997 relatif aux conditions d'agrément des personnes habilitées à procéder à des | D74: 11 | E74: 0.15 | F74: 0.21 | G74: 1.02 | H74: 5 | I74: 5 | J74: 5 | K74: en vigueur | L74: 30 | M74: L’augmentation des coûts est attribuable à une participation en présentiel accrue de la part des membres qui résident en
A75: Justice | B75: Commission de proposition aux offices vacants d'avocat au Conseil d'Etat et à la Cour de cassation | C75: Décret n° 91-1125 du 28 octobre 1991 relatif aux conditions d'accès à la profession d'avocat au Conseil d'Etat et à la Cour de cassation. Commission renouvelée par le décret n° 2021-665 du 26 mai 2021 relatif à certaines commissions administratives à caractère consultatif relevant du ministère de la justice et du ministère de l'enseignement supérieur, de la recherche et de l'innovation JUST2036619D | D75: 5 | E75: 0 | F75: 0 | G75: 0 | H75: 0 | I75: 1 | J75: 0 | K75: en vigueur | L75: 31 | M75: La commission prévue à l’article 28 du décret n°91- 1125 du 28 octobre 1991 relatif aux conditions d'accès à la profession d'avocat au Conseil d'Etat et à la Cour de cassation donne son avis pour deux types d’opérations : les nominations sur office vacant et les nominations sur office créé. Si cette commission n’a pas eu l’occasion de se réunir en 2024 pour une nomination sur un office vacant (ce qui ne s’est pas présenté depuis sa création), celle-ci se réunit pour chaque création d'office d'avocat aux conseils. Pour 2024, elle ne s'est pas réunie car elle suit le rythme biannuel du calendrier de publication de l'avis de l'Autorité de la concurrence. Ainsi, à la suite de la publication du nouvel avis n°25-A-06 du 16 avril 2025 de l'Autorité de la concurrence, elle devrait se réunir dans le courant de cette année, si des candidatures sont transmises à la Chancellerie d'ici le 21 juin 2025 pour la création d'un office. Cette commission ne génère pas de coût particulier.
A76: Justice | B76: Commission de surveillance et de contrôle des publications destinées à l'enfance et à l'adolescence | C76: Loi n° 49-956 du 16 juillet 1949 sur les publications destinées à la jeunesse. Décret n° 50-143 du 1er février 1950 portant règlement d'administration publique pour l'exécution de la loi n° 49-956 du 16 juillet 1949 sur les publications destinées à la jeunesse. | D76: 18 | E76: 3.2 | F76: 3.36 | G76: 3.85 | H76: 4 | I76: 4 | J76: 4 | K76: en vigueur | L76: 32 | M76: L’augmentation des coûts de la commission en 2024 s’explique par l’augmentation des tarifs postaux.
A77: Justice | B77: Commission nationale d'inscription et de discipline des administrateurs judiciaires et des mandataires judiciaires | C77: Articles L. 814-1 et R. 814-1 et suivants du code de commerce | D77: 9 | E77: 14.22 | F77: 21.61 | G77: 17.2 | H77: 13 | I77: 12 | J77: 12 | K77: en vigueur | L77: 32 | M77: La commission nationale d'inscription et de discipline des administrateurs judiciaires et des mandataires judiciaires (CNIDAJMJ) siège en moyenne 1 fois/mois. Ses membres sont rétribués forfaitairement (entre 80 et 300 euros en fonction de leur rôle) pour chaque séance lors de laquelle ils siègent, et remboursés de leurs dépenses de transport. La variation d'une année à l'autre s'explique par ces frais de déplacement qui varient en fonction de la résidence des membres (qui viennent de toute la France) et du nombre de séances auxquelles ils siègent.
A78: Justice | B78: Conseil national de l'aide juridique | C78: Loi n° 91-647 du 10 juillet 1991 relative à l’aide juridique Décret n° 91-1266 du 19 décembre 1991 portant application de la loi n° 91-647 du 10 juillet 1991 relative à l'aide juridique | D78: 26 | E78: 0 | F78: 0 | G78: 0 | H78: 5 | I78: 3 | J78: 2 | K78: en vigueur | L78: 32 | M78: Le coût de fonctionnement est nul car il est indissociable du fonctionnement du ministère.
A79: Justice | B79: Conseil national de la médiation | C79: Article 45 de la loi n°2021- 1729 du 22 décembre 2021 pour la confiance dans l’institution judiciaire Articles 21-6 et 21-7 de la loi du n° 95-125 du 8 février 1995 relative à l'organisation des juridictions et à la procédure civile, pénale et administrative Décret n° 2022-1353 du 25 octobre 2022 relatif à la composition et aux modalités de fonctionnement du Conseil national de la médiation Arrêté du 25 mai 2023 portant nomination au Conseil national de la médiation" | D79: 27 | F79: 4 | G79: 5 | I79: 4 | J79: 4 | K79: en vigueur | L79: 33 | M79: Le CNM a été installé par le garde des Sceaux le 12 juin 2023. Dès cette date, ses travaux ont été amorcés et ils ont pu prendre leur plein essor pendant l’année 2024. En décembre 2024, le Conseil a élaboré son premier rapport d’étape contenant de premières pistes de réflexion et préconisations qui ont largement été commentées, partagées entre les différents acteurs de la médiation, sur les différents réseaux publics et professionnels. Ainsi, 11 réunions dont 7 commissions permanentes et 4 réunions plénières se sont tenues durant l’année 2024. Les membres suppléants ont également été invités à participer aux plénières, s’ils le souhaitaient, afin de pouvoir nourrir les réflexions communes.
A80: Justice | B80: Conseil national des tribunaux de commerce | C80: Articles L. 721-8 et R. 721-7 et suivants du code de commerce | D80: 20 | E80: 1.2 | F80: 1.6 | G80: 1.2 | H80: 9 | I80: 5 | J80: 1 | K80: en vigueur | L80: 33 | M80: Le CNTC a été renouvelé par arrêté du 18 octobre 2024. Une seule assemblée générale s'est tenue le 19/12/2024, ce qui s'explique par la fin de la mandature 2020-2024. Au 9 juillet 2025, 6 réunions s’étaient déjà tenues au sein des commissions de la nouvelle mandature.
A81: Intérieur | B81: Commission compétente pour l'attribution de la qualité d'officier de police judiciaire aux militaires de la gendarmerie et aux fonctionnaires du corps d'encadrement et d'application de la police nationale | C81: Articles 16, 16-2, 16-3 et R. 3 à R. 10 du code de procédure pénale | D81: 12 | E81: 19.29 | F81: 44.64 | G81: 66.3 | H81: 9 | I81: 8 | J81: 8 | K81: en vigueur | L81: 34 | M81: La très forte progression du nombre de candidats passant l'examen et du nombre de centres d’examen a eu pour effet de multiplier les vacations et les déplacements en métropole des membres du jury technique pour assurer les épreuves orales.
A82: Intérieur | B82: Commission consultative des établissements de jeux | C82: Articles R. 321-8 à R. 321-12 du code de la sécurité intérieure | D82: 10 | E82: 3.02 | F82: 2.8 | G82: 3.09 | H82: 5 | I82: 6 | J82: 5 | K82: en vigueur | L82: 34 | M82: Les coûts de fonctionnement de la commission consultative des établissements de jeux sont stables. Ils varient légèrement en fonction du nombre de dossiers examinés et de leur nature (55 dossiers pour 159 vacations en 2023 contre 64 dossiers pour 194 vacations en 2024).
A83: Intérieur | B83: Commission consultative des polices municipales | C83: Articles L. 514-1 et R. 514-1 à R. 514-11 du code de la sécurité intérieure | D83: 24 | E83: 0 | F83: 2.91 | G83: 0 | H83: 0 | I83: 1 | J83: 0 | K83: en vigueur | L83: 34 | M83: La commission consultative des polices municipales ne s'est pas réunie en 2024. Elle le sera nécessairement en 2025, suite aux travaux parlementaires visant à renforcer les pouvoirs de la police municipale.
A84: Intérieur | B84: Commission de recours contre les décisions de refus de visa d'entrée en France | C84: Articles D. 312-3 et suivants du code de l’entrée et du séjour des étrangers et du droit | D84: 5 | E84: 39.62 | F84: 41.93 | G84: 40.67 | H84: 59 | I84: 59 | J84: 59 | K84: en vigueur | L84: 34 | M84: Les coûts de fonctionnement correspondent aux indemnités des membres pour leur participation aux
A85: Intérieur | B85: Commission nationale consultative de prévention des violences lors des manifestations sportives | C85: Articles L. 332-18 et R. 332- 10 et suivants du code du sport | D85: 8 | E85: 0 | F85: 0 | G85: 0 | H85: 1 | I85: 0 | J85: 0 | K85: en vigueur | L85: 35 | M85: La commission nationale consultative de prévention des violences lors des manifestations sportives ne s'est pas réunie en 2024.
A86: Intérieur | B86: Commission nationale consultative des catastrophes naturelles | C86: Décret n° 2022-1737 du 30 décembre 2022 relatif à l'indemnisation des catastrophes naturelles | D86: 29 | F86: 0 | G86: 0 | I86: 0 | J86: 0 | K86: en vigueur | L86: 35 | M86: La commission ne s'est pas réunie en 2024.
A87: Intérieur | B87: Commission nationale d'examen des circuits de vitesse | C87: Articles R. 331-35 à R. 331- 44 du code du sport | D87: 8 | E87: 1 | F87: 1.5 | G87: 0.41 | H87: 11 | I87: 12 | J87: 9 | K87: en vigueur | L87: 35 | M87: En 2024, les membres de la commission se sont réunis à 9 reprises et ont réalisé 12 visites de circuits permettant la publication de 11 arrêtés préfectoraux.
A88: Intérieur | B88: Commission nationale de protection et de réinsertion | C88: Article 706-63-1 du code de procédure pénale Décret n° 2014-346 du 17 mars 2014 relatif à la protection des personnes mentionnées à l'article 706-63-1 du code de procédure pénale bénéficiant d'exemptions ou de réductions de peines | D88: 8 | E88: 0.59 | F88: 6.99 | G88: 1.9 | H88: 2 | I88: 6 | J88: 3 | K88: en vigueur | L88: 35 | M88: Le coût des réunions de la commission nationale de protection et de réinsertion est intégralement financé par le budget de l'Agence de gestion et de recouvrement des avoirs saisis et confisqués, qui est dédié à la mise en œuvre des programmes de protection au bénéfice de "repentis", témoins menacés ou victimes de traite des êtres humains jugés éligibles. Par ailleurs, le nombre annuel de réunions varie en fonction du nombre de cas que la commission nationale de protection et de réinsertion
A89: Intérieur | B89: Commission nationale des experts en automobile | C89: Articles L. 326-5, R. 326-14 et D. 326-15 du code de la route | D89: 13 | E89: 0 | F89: 0.6 | G89: 0 | H89: 2 | I89: 4 | J89: 2 | K89: en vigueur | L89: 36 | M89: En 2024, la commission s'est réunie à deux reprises sans coûts de fonctionnement.
A90: Intérieur | B90: Commission pour la désignation des agents des services fiscaux des catégories A et B habilités à effectuer des enquêtes judiciaires | C90: Articles 28-2 et R. 15-33-29- 5 et suivants du code de procédure pénale | D90: 9 | E90: 0 | F90: 0 | G90: 0 | H90: 1 | I90: 0 | J90: 1 | K90: en vigueur | L90: 36 | M90: Les réunions plénières ont lieu dans des salles mises à disposition gracieusement par l'administration, et il n'y a pas de frais de déplacement de ses membres.
A91: Intérieur | B91: Commission technique consultative sur les demandes d'agrément des dispositifs de nouvelles technologies et de transports de fonds | C91: Articles R. 613-47 et R. 613- 57 du code de la sécurité intérieure | D91: 6 | E91: 0 | F91: 0 | G91: 0 | H91: 2 | I91: 1 | J91: 2 | K91: en vigueur | L91: 36 | M91: Il n'y a pas eu d'évolution des coûts de fonctionnement en 2024. L’organisation de la commission ne génère pas de frais et les réunions se déroulent dans les locaux du ministère de l'intérieur.
A92: Intérieur | B92: Conférence nationale des services d'incendie et de secours | C92: Articles L. 1424-4-1 et R. 1424-59 à R. 1424-68 du code général des collectivités territoriales | D92: 43 | E92: 6.13 | F92: 3.02 | G92: 0 | H92: 8 | I92: 4 | J92: 4 | K92: en vigueur | L92: 36 | M92: Le coût des réunions de la commission est nul en 2024 suite à la décision de ne plus faire appel à un service de sténotypie.
A93: Intérieur | B93: Conseil national de la sécurité routière | C93: Article L. 130-10 du code de la route Décret n° 2001- 784 du 28 août 2001 portant création du conseil national de la sécurité routière et modifiant le décret n° 75-360 du 15 mai 1975 relatif au comité interministériel de la sécurité routière | D93: 67 | E93: 9.49 | F93: 24.43 | G93: 7.97 | H93: 2 | I93: 3 | J93: 0 | K93: en vigueur | L93: 36 | M93: Les coûts de fonctionnement correspondent à la dernière réunion plénière de l'instance en décembre 2023. Le conseil ne s'est pas réuni en 2024 en raison de la modification de sa composition suite à la fin du mandat 2021-2024. Le décret de nomination des députés membres, retardé par les élections législatives anticipées, a été signé le 29 avril 2025.
A94: Intérieur | B94: Conseil national des sapeurs- pompiers volontaires | C94: Articles L. 723-21 et D. 723- 64 à D. 723-72 du code de la sécurité intérieure | D94: 24 | E94: 1 | F94: 0.1 | G94: 0.14 | H94: 2 | I94: 1 | J94: 3 | K94: en vigueur | L94: 36 | M94: Les coûts de fonctionnement correspondent à l'accueil des membres.
A95: Intérieur | B95: Conseil supérieur de l'éducation routière | C95: Articles D. 214-1 et suivants du code de la route | D95: 29 | E95: 0.1 | F95: 0 | G95: 4.16 | H95: 1 | I95: 0 | J95: 3 | K95: en vigueur | L95: 37 | M95: L'augmentation des coûts de fonctionnement est liée à l'organisation de réunions supplémentaires en raison de l'absence de réunion en 2023.
A96: Travail, santé, solidarités et familles | B96: Centre national des soins palliatifs et de la fin de vie | C96: Décret n° 2016-5 du 5 janvier 2016 portant création du Centre national des soins palliatifs et de la fin de vie | D96: 23 | E96: 1308 | F96: 1441 | G96: 1383.54 | H96: 2 | I96: 3 | J96: 2 | K96: en vigueur | L96: 38 | M96: Seulement deux réunions se sont déroulées en 2024 car une commission d’expertise avait initialement été programmée en décembre 2024 puis finalement reportée en février 2025. Les 1,3M€ correspondent au budget de fonctionnement courant du CNSPFV, qui n’a pas bénéficié de crédits supplémentaires, comme en 2023 (avec le financement d’une étude exploratoire et d’un poste temporaire de chargé de projet).
A97: Travail, santé, solidarités et familles | B97: Comité chargé de la simplification et de la qualité des déclarations des données sociales | C97: Décret n° 2023-1385 du 29 décembre 2023 relatif aux modalités de vérification et de correction des déclarations sociales nominatives (article D. 133- 8 et suivants du code de la sécurité sociale) Arrêté du 29 janvier 2024 relatif au comité chargé de la simplification et de la qualité des déclarations des données sociales. | D97: 81 | G97: 0 | J97: 3 | K97: en vigueur | L97: 38 | M97: Ce comité s’est réuni trois fois en 2024. Il est composé de 81 membres, pour un coût de fonctionnement nul.
A98: Travail, santé, solidarités et familles | B98: Comité consultatif national de l'enseignement des jeunes sourds | C98: Arrêté du 20 août 1987 instituant un comité consultatif national de l'enseignement des jeunes sourds. | D98: 17 | E98: 1.88 | F98: 0.65 | G98: 0 | H98: 7 | I98: 3 | J98: 0 | K98: en vigueur | L98: 38 | M98: La diminution du nombre de réunions à partir de l’année 2023 s’explique par le départ de l’un des deux inspecteurs pour jeunes sourds et la
A99: Travail, santé, solidarités et familles | B99: Comité de sélection des laboratoires de biologie médicale de référence | C99: Article D. 6211-19 du code de la santé publique, créé par le décret n° 2016-1989 du 30 décembre 2016 fixant les missions et les modalités de désignation des laboratoires de biologie médicale de référence. | D99: 90 | E99: 48 | F99: 76 | G99: 50 | H99: 1 | I99: 1 | J99: 1 | K99: en vigueur | L99: 39 | M99: La baisse des coûts de fonctionnement (-34%) s'explique par une baisse de la masse salariale due à une réduction des ETP en corrélation avec l'activité de la commission qui se réunit exclusivement en distanciel.
A100: Travail, santé, solidarités et familles | B100: Comité de suivi de la réforme 100% Santé | C100: Décret n° 2019-21 du 11 janvier 2019 visant à garantir un accès sans reste à charge à certains équipements d'optique, aides auditives et soins prothétiques dentaires | D100: 24 | E100: 0 | F100: 0 | G100: 0 | H100: 1 | I100: 1 | J100: 0 | K100: en vigueur | L100: 39 | M100: Le comité de suivi du 100% santé ne s'est pas réuni en 2024. Le comité n’a pas vocation à se réunir à une fréquence annuelle, dès lors qu’il doit pouvoir disposer d’un recul suffisant pour l’évaluation du dispositif, d’autant que celui-ci est encore en période de montée en charge.
A101: Travail, santé, solidarités et familles | B101: Comité du dialogue social pour les questions européennes et internationales | C101: Décret n° 98-1080 du 30 novembre 1998 portant création d'un comité du dialogue social pour les questions européennes et internationales. | D101: 16 | E101: 0 | F101: 0 | G101: 0 | H101: 8 | I101: 8 | J101: 7 | K101: en vigueur | L101: 39 | M101: Aucun coût n’est pris en charge par les ministères sociaux, sachant que lorsque les CDSEI se déroulent en mixte présentiel/distanciel, une salle du ministère est utilisée.
A102: Travail, santé, solidarités et familles | B102: Comité économique de l'hospitalisation publique et privée | C102: Article L. 162-21-3 du code de la sécurité sociale ; Article D. 162-10-1 du code de la sécurité sociale, créé par le décret n° 2020-1687 du 23 décembre 2020 relatif à la composition et au fonctionnement du comité économique de | D102: 15 | E102: 7.61 | F102: 7.61 | G102: 18.85 | H102: 3 | I102: 3 | J102: 6 | K102: en vigueur | L102: 39 | M102: Les coûts de fonctionnement se justifient par l'organisation de six instances et la rédaction d'un rapport. Le tout a mobilisé environ 64 jours/agent
A103: Travail, santé, solidarités et familles | B103: Comité économique des produits de santé | C103: Article L. 162-17-3, D. 162-2- 1 et suivants du code de la sécurité sociale | D103: 34 | E103: 1989 | F103: 1989 | G103: 1987 | H103: 70 | I103: 70 | J103: 70 | K103: en vigueur | L103: 40 | M103: Stabilité de l'organisation et du financement par rapport à 2023
A104: Travail, santé, solidarités et familles | B104: Comité national de l'organisation sanitaire et sociale | C104: Loi n° 91-748 du 31 juillet 1991 modifiée portant réforme hospitalière ; Articles L. 6121-7, L. 6121-8 et L. 6121-11 du code de la santé publique. | D104: 69 | E104: 9.22 | F104: 9.2 | G104: 131.46 | H104: 10 | I104: 12 | J104: 9 | K104: en vigueur | L104: 40 | M104: L'instance est composée d'une section sociale et d'une section sanitaire. Pour la section sociale, 1 séance plénière s’est déroulée en 2024 pour un coût de fonctionnement de 7 913,25 euros. Le secrétariat de la section sociale du CNOSS représente 20 % de la masse salariale d'un agent de catégorie A en charge du secrétariat de la section sociale. Pour la section sanitaire, 8 réunions plénières se sont déroulées en 2024 pour un coût de fonctionnement de 123 554 euros. Les coûts de fonctionnement intègrent désormais un nouveau calcul de valorisation de la masse salariale (123 554€) correspondant au temps de travail consacré à la préparation des comités et à la rédaction des notes à l’attention du ministre sur les recours hiérarchiques. La section sanitaire a mobilisé un ETP B à 70% pour le secrétariat, un ETP A en qualité de chargée de mission, deux ETP A+ à 5% chacun en tant qu’encadrants supérieurs non valorisés précédemment. La quotité
A105: Travail, santé, solidarités et familles | B105: Comité national pour l'emploi | C105: Article 4 de la loi n° 2023- 1196 du 18 décembre 2023 pour le plein emploi. Décret n° 2024-252 du 22 mars 2024 relatif au Comité national pour l'emploi | D105: 49 | G105: 33.5 | J105: 4 | K105: en vigueur | L105: 41 | M105: Le Comité national pour l'emploi a été créé par la loi du 18 décembre 2023 pour le plein emploi et a été installé le 11 avril 2024. Aucune dépense n'a donc été réalisée en 2023. En 2024, le Comité national pour l'emploi s'est réuni lors de : - 4 séances plénières ; - 4 réunions du Bureau du CNE ; - 10 réunions des commissions thématiques qui sont organisées pour mettre en œuvre les différents travaux. La masse salariale dédiée exclusivement à l'organisation de l'instance en 2024 est la suivante : t 25% d'un agent administrateur de l'Etat sur 12 mois et 50% d'un agent attaché territorial de l'Etat sur 4 mois
A106: Travail, santé, solidarités et familles | B106: Comité stratégique des données de santé | C106: Article R. 1461-10 du code de la santé publique ; Arrêté du 29 juin 2021 portant création du comité stratégique des données de santé. | D106: 25 | E106: 0 | F106: 0 | G106: 0 | H106: 1 | I106: 1 | J106: 0 | K106: en vigueur | L106: 41 | M106: L’année 2024 a été marquée par la forte mobilisation de l’ensemble des acteurs (ministères et membres du comité stratégique) dans l’élaboration de la stratégie nationale des données de santé. Ce travail s’étant déroulé sur l’ensemble de
A107: Travail, santé, solidarités et familles | B107: Commission consultative de suivi des conséquences des essais nucléaires | C107: Article 7 de la loi n° 2010-2 du 5 janvier 2010 relative à la reconnaissance et à l'indemnisation des victimes des essais nucléaires français ; Décret n° 2014-1049 du 15 septembre 2014 relatif à la reconnaissance et à l'indemnisation des victimes des essais nucléaires français. | D107: 19 | E107: 0 | F107: 0 | G107: 0 | H107: 0 | I107: 0 | J107: 0 | K107: en vigueur | L107: 42 | M107: Les remaniements ministériels successifs ont eu pour conséquence de reporter, à plusieurs reprises, la réunion de cette commission. A titre d'information, une réunion a eu lieu le 1er avril 2025 au ministère de la santé à Paris.
A108: Travail, santé, solidarités et familles | B108: Commission consultative nationale d'agrément des établissements de formation en chiropraxie et en ostéopathie | C108: Décret n° 2020-518 du 4 mai 2020 modifiant le décret n° 2018-90 du 13 février 2018 relatif à l'agrément des établissements de formation en chiropraxie et portant fusion de commissions administratives à caractère consultatif | D108: 16 | E108: 6.69 | F108: 6.4 | G108: 9.06 | H108: 5 | I108: 4 | J108: 1 | K108: en vigueur | L108: 42 | M108: La séance tenue en 2024 a demandé des travaux relatifs à la complétude des dossiers, à l’analyse du contenu des pièces des dossiers, à la préparation, à l’animation des séances et aux suites des séances (rédaction de documents et décisions). L’augmentation du coût est due à l’inclusion de dépenses RH qui n’étaient jusqu’ici pas comptabilisées.
A109: Travail, santé, solidarités et familles | B109: Commission consultative relative aux régimes de sécurité sociale des ministres des cultes et membres des congrégations religieuses | C109: Articles L. 382-15 et R. 382- 58 à R. 382-69 du code de la sécurité sociale | D109: 11 | E109: 0 | F109: 0 | G109: 0 | H109: 3 | I109: 2 | J109: 2 | K109: en vigueur | L109: 42 | M109: La commission consultative des cultes instituée par la loi n° 78-4 du 2 janvier 1978 relative aux régimes d’assurance maladie, maternité, invalidité et vieillesse applicables aux ministres du culte et aux membres des associations, congrégations et collectivités religieuses permet principalement au ministre chargé de la sécurité sociale de recueillir son avis sur la qualité cultuelle d’associations ayant
A110: Travail, santé, solidarités et familles | B110: Commission d'évaluation de la sous- déclaration des accidents du travail et des maladies professionnelles | C110: Articles L. 176-1 et L. 176-2 du code de la sécurité sociale ; Arrêté du 14 février 2011 relatif à la composition de la commission prévue à l'article L. 176-2 du code de la sécurité sociale ; Arrêté du 5 décembre 2016 relatif à la composition de la commission prévue à l'article L. 176-2 du code de la sécurité sociale. | D110: 12 | E110: 0 | F110: 0 | G110: 0 | H110: 0 | I110: 0 | J110: 7 | K110: en vigueur | L110: 43
A111: Travail, santé, solidarités et familles | B111: Commission de labellisation du label diversité | C111: Article 1er du décret n° 2008-1344 du 17 décembre 2008 relatif à la création d'un label en matière de promotion de la diversité et de prévention des discriminations dans le cadre de la gestion des ressources humaines et à la mise en place d'une commission de labellisation ; Décret n° 2019-296 du 9 avril 2019 relatif à la commission de labellisation du label diversité ; Décret n° 2024- 328 du 10 avril 2024 | D111: 20 | E111: 0 | F111: 30.54 | G111: 30.54 | H111: 12 | I111: 9 | J111: 8 | K111: en vigueur | L111: 43 | M111: En 2024, la Commission a été réunie 8 fois. La baisse du nombre de réunions depuis 2022 s’explique par la densification du nombre de demandes examinées par séance. Les coûts de fonctionnement intègrent la masse salariale (à hauteur de 30 540 €) correspondant à la valorisation du temps de travail consacré à la préparation des commissions par les 2 agentes concernées (1 chargée de mission, 1 apprentie). Ces coûts sont restés stables entre 2022 et
A112: Travail, santé, solidarités et familles | B112: Commission de référencement des services et outils numériques au catalogue de service de l'espace numérique de santé | C112: Article R. 1111-38 du code de la santé publique, tel que modifié par l'article 2 du décret n° 2021-1048 du 4 août 2021 relatif à la mise en œuvre de l'espace numérique de santé ; Arrêté du 24 février 2022 relatif à la composition et au fonctionnement de la commission de référencement des services et outils numériques au catalogue de service de l'espace numérique de santé (SSAD2206388A). | D112: 9 | E112: 14 | F112: 10 | G112: 11.68 | H112: 5 | I112: 6 | J112: 9 | K112: en vigueur | L112: 44 | M112: L'usage en constante augmentation de "Mon espace santé" incite les éditeurs à se faire référencer dans l'outil, les candidatures sont donc plus nombreuses en 2024 qu'en 2023, justifiant l’augmentation du nombre de réunions. Par ailleurs, les membres de la commission ont été aussi plus présents dans plus de séances dont le montant des indemnisations lié à leur participation est plus importante également.
A113: Travail, santé, solidarités et familles | B113: Commission des comptes de la sécurité sociale | C113: Articles L. 114-1 et D. 114-1 et suivants du code de la sécurité sociale | D113: 67 | E113: 42 | F113: 42.5 | G113: 42.5 | H113: 2 | I113: 2 | J113: 2 | K113: en vigueur | L113: 44 | M113: Stabilité de la fréquence et des conditions de réunion.
A114: Travail, santé, solidarités et familles | B114: Commission d’accès des personnes nées d’une assistance médicale à la procréation aux données des tiers donneurs | C114: Article 5 de la loi n° 2021- 1017 du 2 août 2021 relative à la bioéthique ; Décret n° 2022-1187 du 25 août 2022 relatif à l’accès aux données non identifiantes et à l’identité du tiers donneur pris en application de l’article 5 de la loi n° 2021-1017 du 2 août 2021 relative à la bioéthique et portant modification des dispositions relatives à l’assistance médicale à la procréation. | D114: 16 | E114: 107.74 | F114: 436 | G114: 389.7 | H114: 4 | I114: 8 | J114: 5 | K114: en vigueur | L114: 44 | M114: La diminution d'environ 10% des coûts de fonctionnement de la CAPADD entre 2023 et 2024 tient pour l'essentiel à la réduction de 60% de la quotité de travail d'un des quatre agents du secrétariat général de la commission.
A115: Travail, santé, solidarités et familles | B115: Commission nationale d'agrément des associations représentant les | C115: Articles L. 1114-1 et R. 1114- 5 à R. 1114-8 du code de la santé publique | D115: 14 | E115: 65 | F115: 191 | G115: 128.58 | H115: 10 | I115: 10 | J115: 10 | K115: en vigueur | L115: 44 | M115: La baisse des coûts de fonctionnement (-33%) s'explique par une baisse de
A116: Travail, santé, solidarités et familles | B116: Commission nationale d'agrément des conventions collectives des établissements et services sociaux et médico-sociaux à but non lucratif | C116: Articles L. 314-6, R. 314-197 et R. 314-198 du code de l'action sociale et des familles. | D116: 13 | E116: 44 | F116: 44 | G116: 44 | H116: 12 | I116: 12 | J116: 11 | K116: en vigueur | L116: 45 | M116: Il n'y a pas d'évolution des coûts de fonctionnement de l'instance.
A117: Travail, santé, solidarités et familles | B117: Commission nationale de biologie médicale | C117: Article L. 6213-12 et R. 6213-15 à R. 6213-27 du code de la santé publique | D117: 30 | E117: 12.35 | F117: 10 | G117: 11.73 | H117: 3 | I117: 3 | J117: 3 | K117: en vigueur | L117: 45 | M117: Pour l’année 2024 le coût de fonctionnement comprend la masse salariale suivante : 10% d’un ETP chargé de mission, 6 jours/agent pour un poste de chargé de mission + 0,5 jour/agent pour un chef de bureau.
A118: Travail, santé, solidarités et familles | B118: Commission nationale de conciliation des conflits collectifs de travail | C118: Articles L. 2522-1 à L. 2522- 7, articles R. 2522-3, R. 2522-4, R. 2522-8, R. 2522- 13 et suivants du code du travail. | D118: 12 | E118: 0 | F118: 0 | G118: 0 | H118: 7 | I118: 0 | J118: 0 | K118: en vigueur | L118: 45
A119: Travail, santé, solidarités et familles | B119: Commission nationale de la négociation collective de l'emploi et de la formation professionnelle | C119: Articles L. 2271-1 à L. 2272- 2, R. 2272-1 à R.2272-16 du code du travail. | D119: 40 | E119: 0 | F119: 0 | G119: 13.59 | H119: 7 | I119: 3 | J119: 4 | K119: en vigueur | L119: 45 | M119: En 2024, la CNNCEFP s'est réunie 4 fois en formation plénière. Les coûts de fonctionnement de l’instance sont évalués à 13 590 euros. L'écart en la matière par rapport à l'année précédente s'explique par une évolution de la méthodologie de calcul des coûts, qui conduit désormais à intégrer, au prorata, les coûts de masse salariale, y compris pour les agents dont le temps de travail n’est pas intégralement dédié à la gestion de l’instance
A120: Travail, santé, solidarités et familles | B120: Commission nationale des accidents médicaux | C120: Articles L. 1142-10, L. 1142- 11 et R. 1142-24 à R. 1142-29 | D120: 19 | E120: 94 | F120: 94 | G120: 99.73 | H120: 9 | I120: 8 | J120: 9 | K120: en vigueur | L120: 45 | M120: L’année 2024 est marquée par une légère augmentation
A121: Travail, santé, solidarités et familles | B121: Commission professionnelle consultative cohésion sociale et santé | C121: Article 3 du décret n° 2019- 958 du 13 septembre 2019 instituant des commissions professionnelles consultatives chargées d'examiner les projets de création, de révision ou de suppression de diplômes et titres à finalité professionnelle délivrés au nom de l’État. | D121: 22 | E121: 8.62 | F121: 10 | G121: 10 | H121: 5 | I121: 5 | J121: 5 | K121: en vigueur | L121: 46 | M121: Le nombre de réunions et les coûts sont stables par rapport aux années précédentes.
A122: Travail, santé, solidarités et familles | B122: Commissions professionnelles consultatives | C122: Articles L. 6113-3, R. 6113-21 à R. 6113-26 du code du travail ; Décret n° 2019-958 du 13 septembre 2019 instituant les commissions professionnelles consultatives chargées d'examiner les projets de création, de révision ou de suppression de diplômes et titres à finalité professionnelle délivrés au nom de l’État. | D122: 66 | E122: 576 | F122: 758 | G122: 581 | H122: 51 | I122: 76 | J122: 48 | K122: en vigueur | L122: 46 | M122: Entre 2023 et 2024, le coût de fonctionnement diminue, passant de 758 000 euros à 581 000 euros. Cette diminution s'explique par la baisse du nombre de réunions organisées (48 en 2024 contre 76 en 2023), liée à un recul du nombre de révisions de titres professionnels avec modifications (49 en 2024 contre 57 en 2023). Certaines révisions ont été validées sans modification (23 titres professionnel) après analyse des données de veille sur le secteur
A123: Travail, santé, solidarités et familles | B123: Conférence nationale de santé | C123: Articles L. 1411-3 et D. 1411- 37 et suivants du code de la santé publique | D123: 97 | E123: 517.07 | F123: 234 | G123: 232.75 | H123: 6 | I123: 6 | J123: 4 | K123: en vigueur | L123: 47 | M123: La diminution du nombre de réunions plénières traduit de manière très imparfaite l'activité de la CNS dans la mesure où sa commission permanente dispose de pouvoirs délibératifs équivalents en cas d'urgence. Cette formation s'est réunie 11 fois en 2024. Par ailleurs, l’année 2024 a été marquée par la constitution d'un groupe de travail sur la santé buccodentaire qui s'est réuni environ 40 fois et d’un groupe de travail sur la santé dans les outre-mer occasionnant plusieurs déplacements du président.
A124: Travail, santé, solidarités et familles | B124: Conseil d'orientation sur les conditions de travail | C124: Articles L. 4641-1 à L.4641- 3, R. 4641-1 à R.4641-14 du code du travail. | D124: 54 | E124: 227.3 | F124: 14 | G124: 19 | H124: 76 | I124: 53 | J124: 47 | K124: en vigueur | L124: 47 | M124: L’année 2024 a vu la poursuite des travaux liés à la mise en œuvre de plusieurs dispositifs structurants prévus par la loi du 2 août 2021. Le cadre de la prévention en santé au travail a été profondément renouvelé avec la mise en œuvre, désormais presque achevée, de la loi du 2 août 2021. Cette évolution explique la diminution du nombre de réunions du COCT en 2024 par rapport à 2023 et 2022. Le COCT mobilise par ailleurs un ETP A+ à 20 % et un ETP A à 50 %.
A125: Travail, santé, solidarités et familles | B125: Conseil national consultatif des personnes handicapées | C125: Articles L. 146-1 et D. 146-1 à D. 146-12 du code de | D125: 89 | E125: 626.7 | F125: 463.35 | G125: 687.5 | H125: 13 | I125: 13 | J125: 14 | K125: en vigueur | L125: 47 | M125: Les coûts ont augmenté du fait notamment de
A126: Travail, santé, solidarités et familles | B126: Conseil national de l'urgence hospitalière | C126: Décret n° 2012-1138 du 9 octobre 2012 relatif au Conseil national de l'urgence hospitalière | D126: 50 | E126: 1.39 | F126: 0.64 | G126: 1.28 | H126: 3 | I126: 1 | J126: 1 | K126: en vigueur | L126: 48 | M126: Le travail de fond conséquent réalisé sur les processus et l’organisation a rendu nécessaire l’accroissement de la mobilisation de la masse salariale (4 jours/agent de chargé de mission au lieu de 2 jours/agent en 2023), ce qui explique la légère augmentation des frais de fonctionnement, avec un nombre d’instances annuelles inchangé.
A127: Travail, santé, solidarités et familles | B127: Conseil national de pilotage des agences régionales de santé | C127: Articles L. 1433-1, D. 1433-1 et suivants du code de la santé publique | D127: 18 | E127: 49 | F127: 48.9 | G127: 48.9 | H127: 32 | I127: 34 | J127: 33 | K127: en vigueur | L127: 48 | M127: Le nombre de réunions et les coûts sont stables par rapport aux années précédentes.
A128: Travail, santé, solidarités et familles | B128: Conseil national du syndrome immunodéficitaire acquis et des hépatites virales chroniques | C128: Articles L. 3121-3 et D. 3121-1 à D. 3121-14 du code de la santé publique | D128: 26 | E128: 326.17 | F128: 405 | G128: 345.21 | H128: 10 | I128: 10 | J128: 10 | K128: en vigueur | L128: 48 | M128: La baisse des coûts de fonctionnement de 15% entre 2023 et 2024 s'explique par une légère baisse de masse salariale (- 4%) qui constitue l'essentiel des coûts, et des dépenses courantes moindres, notamment de sténographie (-81%).
A129: Travail, santé, solidarités et familles | B129: Conseil supérieur de la Fonction publique hospitalière | C129: Articles L. 245-1 à L. 245-3 du code général de la fonction publique ; Décret | D129: 33 | E129: 17.25 | F129: 10.41 | G129: 30.9 | H129: 11 | I129: 6 | J129: 20 | K129: en vigueur | L129: 48 | M129: Les 20 CSFPH (dont 1 commission formations professionnelles et 6
...
